Workbook

Sheet Classificados (v2)
A1: title | B1: authors | C1: year | D1: venue | E1: cluster | F1: paper_type | G1: citations | H1: doi | I1: Scopus (Percentil) | J1: SJR Quartile | K1: ISSN / e-ISSN | M1: ID | N1: Título | O1: Venue | P1: DOI | Q1: Qualis (2025-2028) | R1: Scopus (Percentil) | S1: SJR Quartile | T1: ISSN / e-ISSN | U1: Year | V1: Citações OpenAlex | W1: Citações Crossref | X1: Citações Scopus | Y1: Citações (verificado em) | Z1: ID
A2: Transforming cybersecurity with agentic AI to combat emerging cyber threats | B2: Nir Kshetri | C2: 2025 | D2: Telecommunications Policy | E2: Security IR / SOC | F2: unscreened(rule-classified) | G2: 51 | H2: 10.1016/j.telpol.2025.102976 | I2: =VLOOKUP($D2,Scopus!$A$2:$K$49,3,FALSE) -> 97.0% 14/541 Communication | J2: =VLOOKUP($D2,Scopus!$A$2:$K$49,10,FALSE) -> Q1 | K2: =VLOOKUP($D2,Scopus!$A$2:$K$49,11,FALSE) -> 0308-5961 | L2: =VLOOKUP(H2,$M$1:$Z$40,14,FALSE) -> #N/A | M2: P01 | N2: Trustworthy agentic AI systems: a cross-layer review of architectures, threat models and governance strategies | O2: F1000Research | P2: 10.12688/f1000research.169927.1 | Q2: A2 | R2: 0.77 | S2: Q1 | T2: 2046-1402 | U2: 2025 | V2: 19 | W2: 21 | X2: NÃO INDEXADO | Y2: 46230 | Z2: P01
A3: Deep Learning for Time Series Anomaly Detection: A Survey | B3: Zahra Zamanzadeh Darban; Geoffrey I. Webb; Shirui Pan; Charų C. Aggarwal; Mahsa Salehi | C3: 2024 | D3: ACM Computing Surveys | E3: Detection (classical ML) | F3: survey/position | G3: 506 | H3: 10.1145/3691338 | I3: =VLOOKUP($D3,Scopus!$A$2:$K$49,3,FALSE) -> 99.0% 1/241 General Computer Science | J3: =VLOOKUP($D3,Scopus!$A$2:$K$49,10,FALSE) -> Q1 | K3: =VLOOKUP($D3,Scopus!$A$2:$K$49,11,FALSE) -> 0360-0300 | L3: =VLOOKUP(H3,$M$1:$Z$40,14,FALSE) -> #N/A | M3: P02 | N3: The role of agentic AI in shaping a smart future: A systematic review | O3: Array | P3: 10.1016/j.array.2025.100399 | Q3: A1 | R3: 0.88 | S3: Q1 | T3: 2590-0056 | U3: 2025 | V3: 180 | W3: 190 | X3: 175 | Y3: 46230 | Z3: P02
A4: AgentAI: A comprehensive survey on autonomous agents in distributed AI for industry 4.0 | B4: Francesco Piccialli; Diletta Chiaro; Sundas Sarwar; Donato Cerciello; Pian Qi; Valeria Mele | C4: 2025 | D4: Expert Systems with Applications | E4: Agent foundations | F4: unscreened(rule-classified) | G4: 59 | H4: 10.1016/j.eswa.2025.128404 | I4: =VLOOKUP($D4,Scopus!$A$2:$K$49,3,FALSE) -> 97.0% 10/351 General Engineering | J4: =VLOOKUP($D4,Scopus!$A$2:$K$49,10,FALSE) -> Q1 | K4: =VLOOKUP($D4,Scopus!$A$2:$K$49,11,FALSE) -> 0957-4174 | L4: =VLOOKUP(H4,$M$1:$Z$40,14,FALSE) -> #N/A | M4: P03 | N4: A Research Landscape of Agentic AI and Large Language Models | O4: Algorithms | P4: 10.3390/a18080499 | Q4: A2 | R4: 0.78 | S4: Q2 | T4: 1999-4893 | U4: 2025 | V4: 38 | W4: 45 | X4: 39 | Y4: 46230 | Z4: P03
A5: LLM-Based Multi-Agent Systems for Software Engineering: Literature Review, Vision, and the Road Ahead | B5: Junda He; Christoph Treude; David Lo | C5: 2025 | D5: ACM Transactions on Software Engineering and Methodology | E5: Agent foundations | F5: unscreened(rule-classified) | G5: 177 | H5: 10.1145/3712003 | I5: =VLOOKUP($D5,Scopus!$A$2:$K$49,3,FALSE) -> 89.0% 53/503 Software | J5: =VLOOKUP($D5,Scopus!$A$2:$K$49,10,FALSE) -> Q1 | K5: =VLOOKUP($D5,Scopus!$A$2:$K$49,11,FALSE) -> 1049-331X | L5: =VLOOKUP(H5,$M$1:$Z$40,14,FALSE) -> #N/A | M5: P04 | N5: LLM-Based Multi-Agent Systems for Software Engineering | O5: ACM TRANSACTIONS ON SOFTWARE ENGINEERING AND METHODOLOGY | P5: 10.1145/3712003 | Q5: A2 | R5: 0.82 | S5: Q1 | T5: 1049-331X | U5: 2024 | V5: 144 | W5: 173 | X5: 134 | Y5: 46230 | Z5: P04
A6: AI Agents vs. Agentic AI: A Conceptual taxonomy, applications and challenges | B6: Ranjan Sapkota; Konstantinos I. Roumeliotis; Manoj Karkee | C6: 2025 | D6: Information Fusion | E6: Agent foundations | F6: survey/position | G6: 169 | H6: 10.1016/j.inffus.2025.103599 | I6: =VLOOKUP($D6,Scopus!$A$2:$K$49,3,FALSE) -> 99.0% 1/203 Signal Processing | J6: =VLOOKUP($D6,Scopus!$A$2:$K$49,10,FALSE) -> Q1 | K6: =VLOOKUP($D6,Scopus!$A$2:$K$49,11,FALSE) -> 1566-2535 | L6: =VLOOKUP(H6,$M$1:$Z$40,14,FALSE) -> #N/A | M6: P05 | N6: A Survey of AIOps in the Era of Large Language Models | O6: ACM Computing Surveys | P6: 10.1145/3746635 | Q6: A1 | R6: 0.99 | S6: Q1 | T6: 0360-0300 | U6: 2025 | V6: 19 | W6: 28 | X6: 24 | Y6: 46230 | Z6: P05
A7: Task Failure Prediction in Cloud Data Centers Using Deep Learning | B7: Jiechao Gao; Haoyu Wang; Haiying Shen | C7: 2020 | D7: IEEE Transactions on Services Computing | E7: Detection (classical ML) | F7: unscreened(rule-classified) | G7: 217 | H7: 10.1109/tsc.2020.2993728 | I7: =VLOOKUP($D7,Scopus!$A$2:$K$49,3,FALSE) -> 93.0% 17/245 Hardware and Architecture | J7: =VLOOKUP($D7,Scopus!$A$2:$K$49,10,FALSE) -> Q1 | K7: =VLOOKUP($D7,Scopus!$A$2:$K$49,11,FALSE) -> 1939-1374 | L7: =VLOOKUP(H7,$M$1:$Z$40,14,FALSE) -> #N/A | M7: P06 | N7: Agentic AI: A Comprehensive Survey of Technologies, Applications, and Societal Implications | O7: IEEE Access | P7: 10.1109/ACCESS.2025.3585609 | Q7: A1 | R7: 0.9 | S7: Q1 | T7: 2169-3536 | U7: 2025 | V7: 48 | W7: 57 | X7: 44 | Y7: 46230 | Z7: P06
A8: TAMO:Fine-Grained Root Cause Analysis via Tool-Assisted LLM Agent With Multi-Modality Observation Data in Cloud-Native Systems | B8: Xiao Zhang; Qi Wang; Mingyi Li; Yuan Yuan; Mengbai Xiao; Fuzhen Zhuang; Dongxiao Yu | C8: 2025 | D8: IEEE Transactions on Services Computing | E8: LLM / agentic ops | F8: unscreened(rule-classified) | G8: 7 | H8: 10.1109/TSC.2025.3629066 | I8: =VLOOKUP($D8,Scopus!$A$2:$K$49,3,FALSE) -> 93.0% 17/245 Hardware and Architecture | J8: =VLOOKUP($D8,Scopus!$A$2:$K$49,10,FALSE) -> Q1 | K8: =VLOOKUP($D8,Scopus!$A$2:$K$49,11,FALSE) -> 1939-1374 | L8: =VLOOKUP(H8,$M$1:$Z$40,14,FALSE) -> #N/A | M8: P07 | N8: Artificial Empathy: A New Perspective for Analyzing and Designing Multi-Agent Systems | O8: IEEE Access | P8: 10.1109/ACCESS.2020.3029502 | Q8: A1 | R8: 0.9 | S8: Q1 | T8: 2169-3536 | U8: 2020 | V8: 10 | W8: 9 | X8: 8 | Y8: 46230 | Z8: P07
A9: Surveying Root Cause Analysis Techniques: A Comprehensive Review of Aspects for Multi-Service Applications | B9: Zhijing Li; Jianbo Yu; Zhijun Huang; Yusheng Huang | C9: 2025 | D9: IEEE Transactions on Services Computing | E9: Root-cause analysis | F9: unscreened(rule-classified) | G9: 0 | H9: 10.1109/TSC.2025.3631913 | I9: =VLOOKUP($D9,Scopus!$A$2:$K$49,3,FALSE) -> 93.0% 17/245 Hardware and Architecture | J9: =VLOOKUP($D9,Scopus!$A$2:$K$49,10,FALSE) -> Q1 | K9: =VLOOKUP($D9,Scopus!$A$2:$K$49,11,FALSE) -> 1939-1374 | L9: =VLOOKUP(H9,$M$1:$Z$40,14,FALSE) -> #N/A | M9: P08 | N9: Applications, Challenges, and Future Directions of Human-in-the-Loop Learning | O9: IEEE Access | P9: 10.1109/ACCESS.2024.3401547 | Q9: A1 | R9: 0.9 | S9: Q1 | T9: 2169-3536 | U9: 2024 | V9: 135 | W9: 134 | X9: 141 | Y9: 46230 | Z9: P08
A10: A Research Landscape of Agentic AI and Large Language Models: Applications, Challenges and Future Directions | B10: Sarfraz Nawaz Brohi; Qurat-ul-ain Mastoi; N. Z. Jhanjhi; Thulasyammal Ramiah Pillai | C10: 2025 | D10: Algorithms | E10: Security IR / SOC | F10: unscreened(rule-classified) | G10: 44 | H10: 10.3390/a18080499 | I10: =VLOOKUP($D10,Scopus!$A$2:$K$49,3,FALSE) -> 84.0% 34/212 Computational Mathematics | J10: =VLOOKUP($D10,Scopus!$A$2:$K$49,10,FALSE) -> Q2 | K10: =VLOOKUP($D10,Scopus!$A$2:$K$49,11,FALSE) -> 1999-4893 | L10: =VLOOKUP(H10,$M$1:$Z$40,14,FALSE) -> #N/A | M10: P09 | N10: AI Agents vs. Agentic AI: A Conceptual taxonomy, applications and challenges | O10: Information Fusion | P10: 10.1016/j.inffus.2025.103599 | Q10: A1 | R10: 0.99 | S10: Q1 | T10: 1566-2535 | U10: 2025 | V10: 132 | W10: 149 | X10: 136 | Y10: 46230 | Z10: P09
A11: The Rise of Agentic AI: A Review of Definitions, Frameworks, Architectures, Applications, Evaluation Metrics, and Challenges | B11: Ajay Bandi; Bhavani Kongari; Roshini Naguru; Sahitya Pasnoor; Sri Vidya Vilipala | C11: 2025 | D11: Future Internet | E11: Security IR / SOC | F11: unscreened(rule-classified) | G11: 126 | H11: 10.3390/fi17090404 | I11: =VLOOKUP($D11,Scopus!$A$2:$K$49,3,FALSE) -> 88.0% 65/568 Computer Networks and Communications | J11: =VLOOKUP($D11,Scopus!$A$2:$K$49,10,FALSE) -> Q1 | K11: =VLOOKUP($D11,Scopus!$A$2:$K$49,11,FALSE) -> 1999-5903 | L11: =VLOOKUP(H11,$M$1:$Z$40,14,FALSE) -> #N/A | M11: P10 | N11: Agentic AI: Autonomous Intelligence for Complex Goals — A Comprehensive Survey | O11: IEEE Access | P11: 10.1109/ACCESS.2025.3532853 | Q11: A1 | R11: 0.9 | S11: Q1 | T11: 2169-3536 | U11: 2025 | V11: 487 | W11: 534 | X11: 509 | Y11: 46230 | Z11: P10
A12: Trustworthy agentic AI systems: a cross-layer review of architectures, threat models, and governance strategies for real-world deployment | B12: IBRAHIM ADABARA; Bashir Olaniyi Sadiq; Aliyu Nuhu Shuaibu; Yale Ibrahim Danjuma; Maninti Venkateswarlu | C12: 2025 | D12: F1000Research | E12: LLM / agentic ops | F12: unscreened(rule-classified) | G12: 21 | H12: 10.12688/f1000research.169927.1 | I12: =VLOOKUP($D12,Scopus!$A$2:$K$49,3,FALSE) -> 79.0% 139/692 Arts and Humanities (miscellaneous) | J12: =VLOOKUP($D12,Scopus!$A$2:$K$49,10,FALSE) -> Q1 | K12: =VLOOKUP($D12,Scopus!$A$2:$K$49,11,FALSE) -> 2046-1402 | L12: =VLOOKUP(H12,$M$1:$Z$40,14,FALSE) -> #N/A | M12: P11 | N12: Co-Evolving Multi-Agent Transfer Reinforcement Learning via Scenario Independent Representation | O12: IEEE Access | P12: 10.1109/ACCESS.2024.3430037 | Q12: A1 | R12: 0.9 | S12: Q1 | T12: 2169-3536 | U12: 2024 | V12: 9 | W12: 9 | X12: 10 | Y12: 46230 | Z12: P11
A13: A Review of Agentic AI in Cybersecurity: Cognitive Autonomy, Ethical Governance, and Quantum-Resilient Defense | B13: IBRAHIM ADABARA; Bashir Olaniyi Sadiq; Aliyu Nuhu Shuaibu; Yale Ibrahim Danjuma; Maninti Venkateswarlu | C13: 2025 | D13: F1000Research | E13: Security IR / SOC | F13: survey/position | G13: 13 | H13: 10.12688/f1000research.169337.1 | I13: =VLOOKUP($D13,Scopus!$A$2:$K$49,3,FALSE) -> 79.0% 139/692 Arts and Humanities (miscellaneous) | J13: =VLOOKUP($D13,Scopus!$A$2:$K$49,10,FALSE) -> Q1 | K13: =VLOOKUP($D13,Scopus!$A$2:$K$49,11,FALSE) -> 2046-1402 | L13: =VLOOKUP(H13,$M$1:$Z$40,14,FALSE) -> #N/A | M13: P12 | N13: Enhancing autonomous system security and resilience with generative AI | O13: IEEE Access | P13: 10.1109/ACCESS.2024.3439363 | Q13: A1 | R13: 0.9 | S13: Q1 | T13: 2169-3536 | U13: 2024 | V13: 86 | W13: 93 | X13: 101 | Y13: 46230 | Z13: P12
A14: A Practical Approach to Defining a Framework for Developing an Agentic AIOps System | B14: Răzvan Daniel Zota; Corneliu Bărbulescu; Radu Constantinescu | C14: 2025 | D14: Electronics | E14: LLM / agentic ops | F14: systems/empirical | G14: 24 | H14: 10.3390/electronics14091775 | I14: =VLOOKUP($D14,Scopus!$A$2:$K$49,3,FALSE) -> 83.0% 35/203 Signal Processing | J14: =VLOOKUP($D14,Scopus!$A$2:$K$49,10,FALSE) -> Q2 | K14: =VLOOKUP($D14,Scopus!$A$2:$K$49,11,FALSE) -> 2079-9292 | L14: =VLOOKUP(H14,$M$1:$Z$40,14,FALSE) -> #N/A | M14: P13 | N14: Retail Resilience Engine: An Agentic AI Framework for Building Reliable Retail Systems | O14: IEEE Access | P14: 10.1109/ACCESS.2025.3552592 | Q14: A1 | R14: 0.9 | S14: Q1 | T14: 2169-3536 | U14: 2025 | V14: 29 | W14: 33 | X14: 31 | Y14: 46230 | Z14: P13
... A40: Variational LSTM Enhanced Anomaly Detection for Industrial Big Data | B40: Xiaokang Zhou; Yiyong Hu; Wei Liang; Jianhua Ma; Qun Jin | C40: 2020 | D40: IEEE Transactions on Industrial Informatics | E40: Automated remediation | F40: unscreened(rule-classified) | G40: 401 | H40: 10.1109/tii.2020.3022432 | I40: =VLOOKUP($D40,Scopus!$A$2:$K$49,3,FALSE) -> 98.0% 10/519 Information Systems | J40: =VLOOKUP($D40,Scopus!$A$2:$K$49,10,FALSE) -> Q1 | K40: =VLOOKUP($D40,Scopus!$A$2:$K$49,11,FALSE) -> 1551-3203 | L40: =VLOOKUP(H40,$M$1:$Z$40,14,FALSE) -> #N/A | M40: P40 | N40: A Comprehensive Survey on LLM-Based Network Management and Operations | O40: International Journal of Network Management | P40: 10.1002/nem.70029 | Q40: A3 | R40: 0.68 | S40: Q2 | T40: 1055-7148 | U40: 2025 | V40: 11 | W40: 13 | X40: 7 | Y40: 46230 | Z40: P40
A41: Artificial Intelligence for Predictive Maintenance Applications: Key Components, Trustworthiness, and Future Trends | B41: Ayşegül Uçar; Mehmet Karaköse; Necim Kırımça | C41: 2024 | D41: Applied Sciences | E41: Detection (classical ML) | F41: survey/position | G41: 396 | H41: 10.3390/app14020898 | I41: =VLOOKUP($D41,Scopus!$A$2:$K$49,3,FALSE) -> 82.0% 18/99 Fluid Flow and Transfer Processes | J41: =VLOOKUP($D41,Scopus!$A$2:$K$49,10,FALSE) -> Q2 | K41: =VLOOKUP($D41,Scopus!$A$2:$K$49,11,FALSE) -> 2076-3417 | L41: =VLOOKUP(H41,$M$1:$Z$40,14,FALSE) -> #N/A
A42: Deep Industrial Image Anomaly Detection: A Survey | B42: Jiaqi Liu; Guoyang Xie; Jinbao Wang; Shangnian Li; Chengjie Wang; Feng Zheng; Yaochu Jin | C42: 2024 | D42: Machine Intelligence Research | E42: Detection (classical ML) | F42: survey/position | G42: 389 | H42: 10.1007/s11633-023-1459-z | I42: =VLOOKUP($D42,Scopus!$A$2:$K$49,3,FALSE) -> 99.0% 2/397 Modeling and Simulation | J42: =VLOOKUP($D42,Scopus!$A$2:$K$49,10,FALSE) -> Q1 | K42: =VLOOKUP($D42,Scopus!$A$2:$K$49,11,FALSE) -> 2731-538X | L42: =VLOOKUP(H42,$M$1:$Z$40,14,FALSE) -> #N/A
A43: Anomaly detection with density estimation | B43: Benjamin Nachman; David Shih | C43: 2020 | D43: Physical review D | E43: Detection (classical ML) | F43: systems/empirical | G43: 315 | H43: 10.1103/physrevd.101.075042 | I43: =VLOOKUP($D43,Scopus!$A$2:$K$49,3,FALSE) -> 93.0% 7/97 Nuclear and High Energy Physics | J43: =VLOOKUP($D43,Scopus!$A$2:$K$49,10,FALSE) -> Q1 | K43: =VLOOKUP($D43,Scopus!$A$2:$K$49,11,FALSE) -> 2470-0010 | L43: =VLOOKUP(H43,$M$1:$Z$40,14,FALSE) -> #N/A
A44: From Corrective to Predictive Maintenance—A Review of Maintenance Approaches for the Power Industry | B44: Marek Molęda; Bożena Małysiak-Mrozek; Weiping Ding; Vaidy Sunderam; Dariusz Mrozek | C44: 2023 | D44: Sensors | E44: Detection (classical ML) | F44: survey/position | G44: 264 | H44: 10.3390/s23135970 | I44: =VLOOKUP($D44,Scopus!$A$2:$K$49,3,FALSE) -> 91.0% 19/206 Instrumentation | J44: =VLOOKUP($D44,Scopus!$A$2:$K$49,10,FALSE) -> Q1 | K44: =VLOOKUP($D44,Scopus!$A$2:$K$49,11,FALSE) -> 1424-8220 | L44: =VLOOKUP(H44,$M$1:$Z$40,14,FALSE) -> #N/A
A45: From knowledge-based to big data analytic model: a novel IoT and machine learning based decision support system for predictive maintenance in Industry 4.0 | B45: Riccardo Rosati; Luca Romeo; Gianalberto Cecchini; F. Tonetto; Paolo Viti; Adriano Mancini; Emanuele Frontoni | C45: 2022 | D45: Journal of Intelligent Manufacturing | E45: Detection (classical ML) | F45: systems/empirical | G45: 247 | H45: 10.1007/s10845-022-01960-x | I45: =VLOOKUP($D45,Scopus!$A$2:$K$49,3,FALSE) -> 96.0% 17/503 Software | J45: =VLOOKUP($D45,Scopus!$A$2:$K$49,10,FALSE) -> Q1 | K45: =VLOOKUP($D45,Scopus!$A$2:$K$49,11,FALSE) -> 0956-5515 | L45: =VLOOKUP(H45,$M$1:$Z$40,14,FALSE) -> #N/A
A46: A Neuroergonomics Approach to Mental Workload, Engagement and Human Performance | B46: Frédéric Dehais; Alex Lafont; Raphaëlle N. Roy; Stephen Fairclough | C46: 2020 | D46: Frontiers in Neuroscience | E46: Human factors | F46: survey/position | G46: 245 | H46: 10.3389/fnins.2020.00268 | I46: =VLOOKUP($D46,Scopus!$A$2:$K$49,3,FALSE) -> 74.0% 29/112 General Neuroscience | J46: =VLOOKUP($D46,Scopus!$A$2:$K$49,10,FALSE) -> Q2 | K46: =VLOOKUP($D46,Scopus!$A$2:$K$49,11,FALSE) -> 1662-453X | L46: =VLOOKUP(H46,$M$1:$Z$40,14,FALSE) -> #N/A
A47: The Chatbot Usability Scale: the Design and Pilot of a Usability Scale for Interaction with AI-Based Conversational Agents | B47: Simone Borsci; Alessio Malizia; Martin Schmettow; Frank van der Velde; Gunay Tariverdiyeva; Divyaa Balaji; Alan Chamberlain | C47: 2021 | D47: Personal and Ubiquitous Computing | E47: Benchmarks & evaluation | F47: unscreened(rule-classified) | G47: 233 | H47: 10.1007/s00779-021-01582-9 | I47: =VLOOKUP($D47,Scopus!$A$2:$K$49,3,FALSE) -> 92.0% 24/296 Library and Information Sciences | J47: =VLOOKUP($D47,Scopus!$A$2:$K$49,10,FALSE) -> Q2 | K47: =VLOOKUP($D47,Scopus!$A$2:$K$49,11,FALSE) -> 1617-4909 | L47: =VLOOKUP(H47,$M$1:$Z$40,14,FALSE) -> #N/A
A48: A Review of Machine Learning and Deep Learning Techniques for Anomaly Detection in IoT Data | B48: Redhwan Al-amri; Raja Kumar Murugesan; Mustafa Man; Alaa Fareed; Mohammed A. Al‐Sharafi; Ammar Ahmed Alkahtani | C48: 2021 | D48: Applied Sciences | E48: Detection (classical ML) | F48: survey/position | G48: 202 | H48: 10.3390/app11125320 | I48: =VLOOKUP($D48,Scopus!$A$2:$K$49,3,FALSE) -> 82.0% 18/99 Fluid Flow and Transfer Processes | J48: =VLOOKUP($D48,Scopus!$A$2:$K$49,10,FALSE) -> Q2 | K48: =VLOOKUP($D48,Scopus!$A$2:$K$49,11,FALSE) -> 2076-3417 | L48: =VLOOKUP(H48,$M$1:$Z$40,14,FALSE) -> #N/A
A49: Deep learning for anomaly detection in log data: A survey | B49: Max Landauer; Sebastian Onder; Florian Skopik; Markus Wurzenberger | C49: 2023 | D49: Machine Learning with Applications | E49: Detection (classical ML) | F49: survey/position | G49: 194 | H49: 10.1016/j.mlwa.2023.100470 | I49: =VLOOKUP($D49,Scopus!$A$2:$K$49,3,FALSE) -> 93.0% 13/203 Computational Theory and Mathematics | J49: =VLOOKUP($D49,Scopus!$A$2:$K$49,10,FALSE) -> Q1 | K49: =VLOOKUP($D49,Scopus!$A$2:$K$49,11,FALSE) -> 2666-8270 | L49: =VLOOKUP(H49,$M$1:$Z$40,14,FALSE) -> #N/A
A50: Zero Touch Management: A Survey of Network Automation Solutions for 5G and 6G Networks | B50: Estefanía Coronado; Rasoul Behravesh; Tejas Subramanya; Adriana Fernández–Fernández; Muhammad Shuaib Siddiqui; Xavier Costa‐Pérez; Roberto Riggio | C50: 2022 | D50: IEEE Communications Surveys and Tutorials | E50: Security IR / SOC | F50: unscreened(rule-classified) | G50: 176 | H50: 10.1109/comst.2022.3212586 | I50: =VLOOKUP($D50,Scopus!$A$2:$K$49,3,FALSE) -> 99.0% 1/1030 Electrical and Electronic Engineering | J50: =VLOOKUP($D50,Scopus!$A$2:$K$49,10,FALSE) -> Q1 | K50: =VLOOKUP($D50,Scopus!$A$2:$K$49,11,FALSE) -> 1553-877X | L50: =VLOOKUP(H50,$M$1:$Z$40,14,FALSE) -> #N/A
A51: EADN: An Efficient Deep Learning Model for Anomaly Detection in Videos | B51: Sareer Ul Amin; Mohib Ullah; Muhammad Sajjad; Faouzi Alaya Cheikh; Mohammad Hijji; Abdulrahman Hijji; Khan Muhammad | C51: 2022 | D51: Mathematics | E51: Detection (classical ML) | F51: systems/empirical | G51: 142 | H51: 10.3390/math10091555 | I51: =VLOOKUP($D51,Scopus!$A$2:$K$49,3,FALSE) -> 92.0% 33/414 General Mathematics | J51: =VLOOKUP($D51,Scopus!$A$2:$K$49,10,FALSE) -> Q2 | K51: =VLOOKUP($D51,Scopus!$A$2:$K$49,11,FALSE) -> 2227-7390 | L51: =VLOOKUP(H51,$M$1:$Z$40,14,FALSE) -> #N/A
A52: Towards Synoptic Water Monitoring Systems: A Review of AI Methods for Automating Water Body Detection and Water Quality Monitoring Using Remote Sensing | B52: Liping Yang; Joshua Driscol; Sarigai Sarigai; Qiusheng Wu; Christopher D. Lippitt; Melinda Morgan | C52: 2022 | D52: Sensors | E52: Detection (classical ML) | F52: unscreened(rule-classified) | G52: 124 | H52: 10.3390/s22062416 | I52: =VLOOKUP($D52,Scopus!$A$2:$K$49,3,FALSE) -> 91.0% 19/206 Instrumentation | J52: =VLOOKUP($D52,Scopus!$A$2:$K$49,10,FALSE) -> Q1 | K52: =VLOOKUP($D52,Scopus!$A$2:$K$49,11,FALSE) -> 1424-8220 | L52: =VLOOKUP(H52,$M$1:$Z$40,14,FALSE) -> #N/A
... A89: An LLM-Based Agentic Network Traffic Incident-Report Approach Towards Explainable-AI Network Defense | B89: Chia-Hong Chou; Arjun Sudheer; Younghee Park | C89: 2026 | D89: Journal of Sensor and Actuator Networks | E89: LLM / agentic ops | F89: systems/empirical | G89: 1 | H89: 10.3390/jsan15020032 | I89: =VLOOKUP($D89,Scopus!$A$2:$K$49,3,FALSE) -> 97.0% 6/198 Control and Optimization | J89: =VLOOKUP($D89,Scopus!$A$2:$K$49,10,FALSE) -> Q2 | K89: =VLOOKUP($D89,Scopus!$A$2:$K$49,11,FALSE) -> 2224-2708 | L89: =VLOOKUP(H89,$M$1:$Z$40,14,FALSE) -> #N/A
A90: VAGNet: Vision-based Accident Anticipation with Global Features | B90: Vipooshan Vipulananthan; Charith D. Chitraranjan | C90: 2026 | D90: IEEE Open Journal of Vehicular Technology, vol. 7, pp. 1873-1883, 2026 | E90: Alert triage & correlation | F90: unscreened(rule-classified) | H90: 10.1109/ojvt.2026.3704953 | I90: =VLOOKUP($D90,Scopus!$A$2:$K$49,3,FALSE) -> #N/A | J90: =VLOOKUP($D90,Scopus!$A$2:$K$49,10,FALSE) -> #N/A | K90: =VLOOKUP($D90,Scopus!$A$2:$K$49,11,FALSE) -> #N/A | L90: =VLOOKUP(H90,$M$1:$Z$40,14,FALSE) -> #N/A
A91: TELESTO: A Graph Neural Network Model for Anomaly Classification in Cloud Services | B91: Dominik Scheinert; Alexander Acker | C91: 2021 | D91: Springer ICSOC LNCS 12632 (2020) 214-227 | E91: Automated remediation | F91: unscreened(rule-classified) | H91: 10.1007/978-3-030-76352-7_23 | I91: =VLOOKUP($D91,Scopus!$A$2:$K$49,3,FALSE) -> #N/A | J91: =VLOOKUP($D91,Scopus!$A$2:$K$49,10,FALSE) -> #N/A | K91: =VLOOKUP($D91,Scopus!$A$2:$K$49,11,FALSE) -> #N/A | L91: =VLOOKUP(H91,$M$1:$Z$40,14,FALSE) -> #N/A
A92: A Decentralised Self-Healing Approach for Network Topology Maintenance | B92: Arles Rodríguez; Jonatan Gómez; Ada Diaconescu | C92: 2020 | D92: Autonomous Agents and Multi-Agent Systems | E92: Automated remediation | F92: systems/empirical | H92: 10.1007/s10458-020-09486-3 | I92: =VLOOKUP($D92,Scopus!$A$2:$K$49,3,FALSE) -> 76.0% 137/570 Artificial Intelligence | J92: =VLOOKUP($D92,Scopus!$A$2:$K$49,10,FALSE) -> Q2 | K92: =VLOOKUP($D92,Scopus!$A$2:$K$49,11,FALSE) -> 1387-2532 | L92: =VLOOKUP(H92,$M$1:$Z$40,14,FALSE) -> #N/A
A93: A unified framework for detecting point and collective anomalies in operating system logs via collaborative transformers | B93: Mohammad Nasirzadeh; Jafar Tahmoresnezhad; Parviz Rashidi-Khazaee | C93: 2025 | D93: Scientific Reports | E93: Detection (classical ML) | F93: systems/empirical | H93: 10.1038/s41598-025-27693-4 | I93: =VLOOKUP($D93,Scopus!$A$2:$K$49,3,FALSE) -> 87.0% 29/223 | J93: =VLOOKUP($D93,Scopus!$A$2:$K$49,10,FALSE) -> Q1 | K93: =VLOOKUP($D93,Scopus!$A$2:$K$49,11,FALSE) -> 2045-2322 | L93: =VLOOKUP(H93,$M$1:$Z$40,14,FALSE) -> #N/A
A94: TARGET: Automated Scenario Generation from Traffic Rules for Testing Autonomous Vehicles via Validated LLM-Guided Knowledge Extraction | B94: Yao Deng; Jiaohong Yao; Zhi Tu; Xi Zheng; Mengshi Zhang; Tianyi Zhang | C94: 2023 | D94: IEEE Transactions on Software Engineering | E94: LLM / agentic ops | F94: unscreened(rule-classified) | H94: 10.1109/tse.2025.3569086 | I94: =VLOOKUP($D94,Scopus!$A$2:$K$49,3,FALSE) -> 92.0% 36/503 Software | J94: =VLOOKUP($D94,Scopus!$A$2:$K$49,10,FALSE) -> Q1 | K94: =VLOOKUP($D94,Scopus!$A$2:$K$49,11,FALSE) -> 0098-5589 | L94: =VLOOKUP(H94,$M$1:$Z$40,14,FALSE) -> #N/A

Sheet Classificados
A1: title | B1: authors | C1: year | D1: venue | E1: cluster | F1: paper_type | G1: citations | H1: doi | I1: Scopus (Percentil) | J1: SJR Quartile | K1: ISSN / e-ISSN | M1: ID | N1: Título | O1: Venue | P1: DOI | Q1: Qualis (2025-2028) | R1: Scopus (Percentil) | S1: SJR Quartile | T1: ISSN / e-ISSN | U1: Year | V1: Citações OpenAlex | W1: Citações Crossref | X1: Citações Scopus | Y1: Citações (verificado em) | Z1: ID
A2: Transforming cybersecurity with agentic AI to combat emerging cyber threats | B2: Nir Kshetri | C2: 2025 | D2: Telecommunications Policy | E2: Security IR / SOC | F2: unscreened(rule-classified) | G2: 51 | H2: 10.1016/j.telpol.2025.102976 | I2: =VLOOKUP($D2,Scopus!$A$2:$K$49,3,FALSE) -> 97.0% 14/541 Communication | J2: =VLOOKUP($D2,Scopus!$A$2:$K$49,10,FALSE) -> Q1 | K2: =VLOOKUP($D2,Scopus!$A$2:$K$49,11,FALSE) -> 0308-5961 | L2: =VLOOKUP(H2,$M$1:$Z$40,14,FALSE) -> #N/A | M2: P01 | N2: Trustworthy agentic AI systems: a cross-layer review of architectures, threat models and governance strategies | O2: F1000Research | P2: 10.12688/f1000research.169927.1 | Q2: A2 | R2: 0.77 | S2: Q1 | T2: 2046-1402 | U2: 2025 | V2: 19 | W2: 21 | X2: NÃO INDEXADO | Y2: 46230 | Z2: P01
A3: Deep Learning for Time Series Anomaly Detection: A Survey | B3: Zahra Zamanzadeh Darban; Geoffrey I. Webb; Shirui Pan; Charų C. Aggarwal; Mahsa Salehi | C3: 2024 | D3: ACM Computing Surveys | E3: Detection (classical ML) | F3: survey/position | G3: 506 | H3: 10.1145/3691338 | I3: =VLOOKUP($D3,Scopus!$A$2:$K$49,3,FALSE) -> 99.0% 1/241 General Computer Science | J3: =VLOOKUP($D3,Scopus!$A$2:$K$49,10,FALSE) -> Q1 | K3: =VLOOKUP($D3,Scopus!$A$2:$K$49,11,FALSE) -> 0360-0300 | L3: =VLOOKUP(H3,$M$1:$Z$40,14,FALSE) -> #N/A | M3: P02 | N3: The role of agentic AI in shaping a smart future: A systematic review | O3: Array | P3: 10.1016/j.array.2025.100399 | Q3: A1 | R3: 0.88 | S3: Q1 | T3: 2590-0056 | U3: 2025 | V3: 180 | W3: 190 | X3: 175 | Y3: 46230 | Z3: P02
A4: AgentAI: A comprehensive survey on autonomous agents in distributed AI for industry 4.0 | B4: Francesco Piccialli; Diletta Chiaro; Sundas Sarwar; Donato Cerciello; Pian Qi; Valeria Mele | C4: 2025 | D4: Expert Systems with Applications | E4: Agent foundations | F4: unscreened(rule-classified) | G4: 59 | H4: 10.1016/j.eswa.2025.128404 | I4: =VLOOKUP($D4,Scopus!$A$2:$K$49,3,FALSE) -> 97.0% 10/351 General Engineering | J4: =VLOOKUP($D4,Scopus!$A$2:$K$49,10,FALSE) -> Q1 | K4: =VLOOKUP($D4,Scopus!$A$2:$K$49,11,FALSE) -> 0957-4174 | L4: =VLOOKUP(H4,$M$1:$Z$40,14,FALSE) -> #N/A | M4: P03 | N4: A Research Landscape of Agentic AI and Large Language Models | O4: Algorithms | P4: 10.3390/a18080499 | Q4: A2 | R4: 0.78 | S4: Q2 | T4: 1999-4893 | U4: 2025 | V4: 38 | W4: 45 | X4: 39 | Y4: 46230 | Z4: P03
A5: LLM-Based Multi-Agent Systems for Software Engineering: Literature Review, Vision, and the Road Ahead | B5: Junda He; Christoph Treude; David Lo | C5: 2025 | D5: ACM Transactions on Software Engineering and Methodology | E5: Agent foundations | F5: unscreened(rule-classified) | G5: 177 | H5: 10.1145/3712003 | I5: =VLOOKUP($D5,Scopus!$A$2:$K$49,3,FALSE) -> 89.0% 53/503 Software | J5: =VLOOKUP($D5,Scopus!$A$2:$K$49,10,FALSE) -> Q1 | K5: =VLOOKUP($D5,Scopus!$A$2:$K$49,11,FALSE) -> 1049-331X | L5: =VLOOKUP(H5,$M$1:$Z$40,14,FALSE) -> #N/A | M5: P04 | N5: LLM-Based Multi-Agent Systems for Software Engineering | O5: ACM TRANSACTIONS ON SOFTWARE ENGINEERING AND METHODOLOGY | P5: 10.1145/3712003 | Q5: A2 | R5: 0.82 | S5: Q1 | T5: 1049-331X | U5: 2024 | V5: 144 | W5: 173 | X5: 134 | Y5: 46230 | Z5: P04
A6: AI Agents vs. Agentic AI: A Conceptual taxonomy, applications and challenges | B6: Ranjan Sapkota; Konstantinos I. Roumeliotis; Manoj Karkee | C6: 2025 | D6: Information Fusion | E6: Agent foundations | F6: survey/position | G6: 169 | H6: 10.1016/j.inffus.2025.103599 | I6: =VLOOKUP($D6,Scopus!$A$2:$K$49,3,FALSE) -> 99.0% 1/203 Signal Processing | J6: =VLOOKUP($D6,Scopus!$A$2:$K$49,10,FALSE) -> Q1 | K6: =VLOOKUP($D6,Scopus!$A$2:$K$49,11,FALSE) -> 1566-2535 | L6: =VLOOKUP(H6,$M$1:$Z$40,14,FALSE) -> #N/A | M6: P05 | N6: A Survey of AIOps in the Era of Large Language Models | O6: ACM Computing Surveys | P6: 10.1145/3746635 | Q6: A1 | R6: 0.99 | S6: Q1 | T6: 0360-0300 | U6: 2025 | V6: 19 | W6: 28 | X6: 24 | Y6: 46230 | Z6: P05
A7: Task Failure Prediction in Cloud Data Centers Using Deep Learning | B7: Jiechao Gao; Haoyu Wang; Haiying Shen | C7: 2020 | D7: IEEE Transactions on Services Computing | E7: Detection (classical ML) | F7: unscreened(rule-classified) | G7: 217 | H7: 10.1109/tsc.2020.2993728 | I7: =VLOOKUP($D7,Scopus!$A$2:$K$49,3,FALSE) -> 93.0% 17/245 Hardware and Architecture | J7: =VLOOKUP($D7,Scopus!$A$2:$K$49,10,FALSE) -> Q1 | K7: =VLOOKUP($D7,Scopus!$A$2:$K$49,11,FALSE) -> 1939-1374 | L7: =VLOOKUP(H7,$M$1:$Z$40,14,FALSE) -> #N/A | M7: P06 | N7: Agentic AI: A Comprehensive Survey of Technologies, Applications, and Societal Implications | O7: IEEE Access | P7: 10.1109/ACCESS.2025.3585609 | Q7: A1 | R7: 0.9 | S7: Q1 | T7: 2169-3536 | U7: 2025 | V7: 48 | W7: 57 | X7: 44 | Y7: 46230 | Z7: P06
A8: TAMO:Fine-Grained Root Cause Analysis via Tool-Assisted LLM Agent With Multi-Modality Observation Data in Cloud-Native Systems | B8: Xiao Zhang; Qi Wang; Mingyi Li; Yuan Yuan; Mengbai Xiao; Fuzhen Zhuang; Dongxiao Yu | C8: 2025 | D8: IEEE Transactions on Services Computing | E8: LLM / agentic ops | F8: unscreened(rule-classified) | G8: 7 | H8: 10.1109/TSC.2025.3629066 | I8: =VLOOKUP($D8,Scopus!$A$2:$K$49,3,FALSE) -> 93.0% 17/245 Hardware and Architecture | J8: =VLOOKUP($D8,Scopus!$A$2:$K$49,10,FALSE) -> Q1 | K8: =VLOOKUP($D8,Scopus!$A$2:$K$49,11,FALSE) -> 1939-1374 | L8: =VLOOKUP(H8,$M$1:$Z$40,14,FALSE) -> #N/A | M8: P07 | N8: Artificial Empathy: A New Perspective for Analyzing and Designing Multi-Agent Systems | O8: IEEE Access | P8: 10.1109/ACCESS.2020.3029502 | Q8: A1 | R8: 0.9 | S8: Q1 | T8: 2169-3536 | U8: 2020 | V8: 10 | W8: 9 | X8: 8 | Y8: 46230 | Z8: P07
A9: Surveying Root Cause Analysis Techniques: A Comprehensive Review of Aspects for Multi-Service Applications | B9: Zhijing Li; Jianbo Yu; Zhijun Huang; Yusheng Huang | C9: 2025 | D9: IEEE Transactions on Services Computing | E9: Root-cause analysis | F9: unscreened(rule-classified) | G9: 0 | H9: 10.1109/TSC.2025.3631913 | I9: =VLOOKUP($D9,Scopus!$A$2:$K$49,3,FALSE) -> 93.0% 17/245 Hardware and Architecture | J9: =VLOOKUP($D9,Scopus!$A$2:$K$49,10,FALSE) -> Q1 | K9: =VLOOKUP($D9,Scopus!$A$2:$K$49,11,FALSE) -> 1939-1374 | L9: =VLOOKUP(H9,$M$1:$Z$40,14,FALSE) -> #N/A | M9: P08 | N9: Applications, Challenges, and Future Directions of Human-in-the-Loop Learning | O9: IEEE Access | P9: 10.1109/ACCESS.2024.3401547 | Q9: A1 | R9: 0.9 | S9: Q1 | T9: 2169-3536 | U9: 2024 | V9: 135 | W9: 134 | X9: 141 | Y9: 46230 | Z9: P08
A10: A Research Landscape of Agentic AI and Large Language Models: Applications, Challenges and Future Directions | B10: Sarfraz Nawaz Brohi; Qurat-ul-ain Mastoi; N. Z. Jhanjhi; Thulasyammal Ramiah Pillai | C10: 2025 | D10: Algorithms | E10: Security IR / SOC | F10: unscreened(rule-classified) | G10: 44 | H10: 10.3390/a18080499 | I10: =VLOOKUP($D10,Scopus!$A$2:$K$49,3,FALSE) -> 84.0% 34/212 Computational Mathematics | J10: =VLOOKUP($D10,Scopus!$A$2:$K$49,10,FALSE) -> Q2 | K10: =VLOOKUP($D10,Scopus!$A$2:$K$49,11,FALSE) -> 1999-4893 | L10: =VLOOKUP(H10,$M$1:$Z$40,14,FALSE) -> #N/A | M10: P09 | N10: AI Agents vs. Agentic AI: A Conceptual taxonomy, applications and challenges | O10: Information Fusion | P10: 10.1016/j.inffus.2025.103599 | Q10: A1 | R10: 0.99 | S10: Q1 | T10: 1566-2535 | U10: 2025 | V10: 132 | W10: 149 | X10: 136 | Y10: 46230 | Z10: P09
A11: The Rise of Agentic AI: A Review of Definitions, Frameworks, Architectures, Applications, Evaluation Metrics, and Challenges | B11: Ajay Bandi; Bhavani Kongari; Roshini Naguru; Sahitya Pasnoor; Sri Vidya Vilipala | C11: 2025 | D11: Future Internet | E11: Security IR / SOC | F11: unscreened(rule-classified) | G11: 126 | H11: 10.3390/fi17090404 | I11: =VLOOKUP($D11,Scopus!$A$2:$K$49,3,FALSE) -> 88.0% 65/568 Computer Networks and Communications | J11: =VLOOKUP($D11,Scopus!$A$2:$K$49,10,FALSE) -> Q1 | K11: =VLOOKUP($D11,Scopus!$A$2:$K$49,11,FALSE) -> 1999-5903 | L11: =VLOOKUP(H11,$M$1:$Z$40,14,FALSE) -> #N/A | M11: P10 | N11: Agentic AI: Autonomous Intelligence for Complex Goals — A Comprehensive Survey | O11: IEEE Access | P11: 10.1109/ACCESS.2025.3532853 | Q11: A1 | R11: 0.9 | S11: Q1 | T11: 2169-3536 | U11: 2025 | V11: 487 | W11: 534 | X11: 509 | Y11: 46230 | Z11: P10
A12: Trustworthy agentic AI systems: a cross-layer review of architectures, threat models, and governance strategies for real-world deployment | B12: IBRAHIM ADABARA; Bashir Olaniyi Sadiq; Aliyu Nuhu Shuaibu; Yale Ibrahim Danjuma; Maninti Venkateswarlu | C12: 2025 | D12: F1000Research | E12: LLM / agentic ops | F12: unscreened(rule-classified) | G12: 21 | H12: 10.12688/f1000research.169927.1 | I12: =VLOOKUP($D12,Scopus!$A$2:$K$49,3,FALSE) -> 79.0% 139/692 Arts and Humanities (miscellaneous) | J12: =VLOOKUP($D12,Scopus!$A$2:$K$49,10,FALSE) -> Q1 | K12: =VLOOKUP($D12,Scopus!$A$2:$K$49,11,FALSE) -> 2046-1402 | L12: =VLOOKUP(H12,$M$1:$Z$40,14,FALSE) -> #N/A | M12: P11 | N12: Co-Evolving Multi-Agent Transfer Reinforcement Learning via Scenario Independent Representation | O12: IEEE Access | P12: 10.1109/ACCESS.2024.3430037 | Q12: A1 | R12: 0.9 | S12: Q1 | T12: 2169-3536 | U12: 2024 | V12: 9 | W12: 9 | X12: 10 | Y12: 46230 | Z12: P11
A13: A Review of Agentic AI in Cybersecurity: Cognitive Autonomy, Ethical Governance, and Quantum-Resilient Defense | B13: IBRAHIM ADABARA; Bashir Olaniyi Sadiq; Aliyu Nuhu Shuaibu; Yale Ibrahim Danjuma; Maninti Venkateswarlu | C13: 2025 | D13: F1000Research | E13: Security IR / SOC | F13: survey/position | G13: 13 | H13: 10.12688/f1000research.169337.1 | I13: =VLOOKUP($D13,Scopus!$A$2:$K$49,3,FALSE) -> 79.0% 139/692 Arts and Humanities (miscellaneous) | J13: =VLOOKUP($D13,Scopus!$A$2:$K$49,10,FALSE) -> Q1 | K13: =VLOOKUP($D13,Scopus!$A$2:$K$49,11,FALSE) -> 2046-1402 | L13: =VLOOKUP(H13,$M$1:$Z$40,14,FALSE) -> #N/A | M13: P12 | N13: Enhancing autonomous system security and resilience with generative AI | O13: IEEE Access | P13: 10.1109/ACCESS.2024.3439363 | Q13: A1 | R13: 0.9 | S13: Q1 | T13: 2169-3536 | U13: 2024 | V13: 86 | W13: 93 | X13: 101 | Y13: 46230 | Z13: P12
A14: A Practical Approach to Defining a Framework for Developing an Agentic AIOps System | B14: Răzvan Daniel Zota; Corneliu Bărbulescu; Radu Constantinescu | C14: 2025 | D14: Electronics | E14: LLM / agentic ops | F14: systems/empirical | G14: 24 | H14: 10.3390/electronics14091775 | I14: =VLOOKUP($D14,Scopus!$A$2:$K$49,3,FALSE) -> 83.0% 35/203 Signal Processing | J14: =VLOOKUP($D14,Scopus!$A$2:$K$49,10,FALSE) -> Q2 | K14: =VLOOKUP($D14,Scopus!$A$2:$K$49,11,FALSE) -> 2079-9292 | L14: =VLOOKUP(H14,$M$1:$Z$40,14,FALSE) -> #N/A | M14: P13 | N14: Retail Resilience Engine: An Agentic AI Framework for Building Reliable Retail Systems | O14: IEEE Access | P14: 10.1109/ACCESS.2025.3552592 | Q14: A1 | R14: 0.9 | S14: Q1 | T14: 2169-3536 | U14: 2025 | V14: 29 | W14: 33 | X14: 31 | Y14: 46230 | Z14: P13
... A40: Variational LSTM Enhanced Anomaly Detection for Industrial Big Data | B40: Xiaokang Zhou; Yiyong Hu; Wei Liang; Jianhua Ma; Qun Jin | C40: 2020 | D40: IEEE Transactions on Industrial Informatics | E40: Automated remediation | F40: unscreened(rule-classified) | G40: 401 | H40: 10.1109/tii.2020.3022432 | I40: =VLOOKUP($D40,Scopus!$A$2:$K$49,3,FALSE) -> 98.0% 10/519 Information Systems | J40: =VLOOKUP($D40,Scopus!$A$2:$K$49,10,FALSE) -> Q1 | K40: =VLOOKUP($D40,Scopus!$A$2:$K$49,11,FALSE) -> 1551-3203 | L40: =VLOOKUP(H40,$M$1:$Z$40,14,FALSE) -> #N/A | M40: P40 | N40: A Comprehensive Survey on LLM-Based Network Management and Operations | O40: International Journal of Network Management | P40: 10.1002/nem.70029 | Q40: A3 | R40: 0.68 | S40: Q2 | T40: 1055-7148 | U40: 2025 | V40: 11 | W40: 13 | X40: 7 | Y40: 46230 | Z40: P40
A41: Artificial Intelligence for Predictive Maintenance Applications: Key Components, Trustworthiness, and Future Trends | B41: Ayşegül Uçar; Mehmet Karaköse; Necim Kırımça | C41: 2024 | D41: Applied Sciences | E41: Detection (classical ML) | F41: survey/position | G41: 396 | H41: 10.3390/app14020898 | I41: =VLOOKUP($D41,Scopus!$A$2:$K$49,3,FALSE) -> 82.0% 18/99 Fluid Flow and Transfer Processes | J41: =VLOOKUP($D41,Scopus!$A$2:$K$49,10,FALSE) -> Q2 | K41: =VLOOKUP($D41,Scopus!$A$2:$K$49,11,FALSE) -> 2076-3417 | L41: =VLOOKUP(H41,$M$1:$Z$40,14,FALSE) -> #N/A
A42: Deep Industrial Image Anomaly Detection: A Survey | B42: Jiaqi Liu; Guoyang Xie; Jinbao Wang; Shangnian Li; Chengjie Wang; Feng Zheng; Yaochu Jin | C42: 2024 | D42: Machine Intelligence Research | E42: Detection (classical ML) | F42: survey/position | G42: 389 | H42: 10.1007/s11633-023-1459-z | I42: =VLOOKUP($D42,Scopus!$A$2:$K$49,3,FALSE) -> 99.0% 2/397 Modeling and Simulation | J42: =VLOOKUP($D42,Scopus!$A$2:$K$49,10,FALSE) -> Q1 | K42: =VLOOKUP($D42,Scopus!$A$2:$K$49,11,FALSE) -> 2731-538X | L42: =VLOOKUP(H42,$M$1:$Z$40,14,FALSE) -> #N/A
A43: Anomaly detection with density estimation | B43: Benjamin Nachman; David Shih | C43: 2020 | D43: Physical review D | E43: Detection (classical ML) | F43: systems/empirical | G43: 315 | H43: 10.1103/physrevd.101.075042 | I43: =VLOOKUP($D43,Scopus!$A$2:$K$49,3,FALSE) -> 93.0% 7/97 Nuclear and High Energy Physics | J43: =VLOOKUP($D43,Scopus!$A$2:$K$49,10,FALSE) -> Q1 | K43: =VLOOKUP($D43,Scopus!$A$2:$K$49,11,FALSE) -> 2470-0010 | L43: =VLOOKUP(H43,$M$1:$Z$40,14,FALSE) -> #N/A
A44: From Corrective to Predictive Maintenance—A Review of Maintenance Approaches for the Power Industry | B44: Marek Molęda; Bożena Małysiak-Mrozek; Weiping Ding; Vaidy Sunderam; Dariusz Mrozek | C44: 2023 | D44: Sensors | E44: Detection (classical ML) | F44: survey/position | G44: 264 | H44: 10.3390/s23135970 | I44: =VLOOKUP($D44,Scopus!$A$2:$K$49,3,FALSE) -> 91.0% 19/206 Instrumentation | J44: =VLOOKUP($D44,Scopus!$A$2:$K$49,10,FALSE) -> Q1 | K44: =VLOOKUP($D44,Scopus!$A$2:$K$49,11,FALSE) -> 1424-8220 | L44: =VLOOKUP(H44,$M$1:$Z$40,14,FALSE) -> #N/A
A45: From knowledge-based to big data analytic model: a novel IoT and machine learning based decision support system for predictive maintenance in Industry 4.0 | B45: Riccardo Rosati; Luca Romeo; Gianalberto Cecchini; F. Tonetto; Paolo Viti; Adriano Mancini; Emanuele Frontoni | C45: 2022 | D45: Journal of Intelligent Manufacturing | E45: Detection (classical ML) | F45: systems/empirical | G45: 247 | H45: 10.1007/s10845-022-01960-x | I45: =VLOOKUP($D45,Scopus!$A$2:$K$49,3,FALSE) -> 96.0% 17/503 Software | J45: =VLOOKUP($D45,Scopus!$A$2:$K$49,10,FALSE) -> Q1 | K45: =VLOOKUP($D45,Scopus!$A$2:$K$49,11,FALSE) -> 0956-5515 | L45: =VLOOKUP(H45,$M$1:$Z$40,14,FALSE) -> #N/A
A46: A Neuroergonomics Approach to Mental Workload, Engagement and Human Performance | B46: Frédéric Dehais; Alex Lafont; Raphaëlle N. Roy; Stephen Fairclough | C46: 2020 | D46: Frontiers in Neuroscience | E46: Human factors | F46: survey/position | G46: 245 | H46: 10.3389/fnins.2020.00268 | I46: =VLOOKUP($D46,Scopus!$A$2:$K$49,3,FALSE) -> 74.0% 29/112 General Neuroscience | J46: =VLOOKUP($D46,Scopus!$A$2:$K$49,10,FALSE) -> Q2 | K46: =VLOOKUP($D46,Scopus!$A$2:$K$49,11,FALSE) -> 1662-453X | L46: =VLOOKUP(H46,$M$1:$Z$40,14,FALSE) -> #N/A
A47: The Chatbot Usability Scale: the Design and Pilot of a Usability Scale for Interaction with AI-Based Conversational Agents | B47: Simone Borsci; Alessio Malizia; Martin Schmettow; Frank van der Velde; Gunay Tariverdiyeva; Divyaa Balaji; Alan Chamberlain | C47: 2021 | D47: Personal and Ubiquitous Computing | E47: Benchmarks & evaluation | F47: unscreened(rule-classified) | G47: 233 | H47: 10.1007/s00779-021-01582-9 | I47: =VLOOKUP($D47,Scopus!$A$2:$K$49,3,FALSE) -> 92.0% 24/296 Library and Information Sciences | J47: =VLOOKUP($D47,Scopus!$A$2:$K$49,10,FALSE) -> Q2 | K47: =VLOOKUP($D47,Scopus!$A$2:$K$49,11,FALSE) -> 1617-4909 | L47: =VLOOKUP(H47,$M$1:$Z$40,14,FALSE) -> #N/A
A48: A Review of Machine Learning and Deep Learning Techniques for Anomaly Detection in IoT Data | B48: Redhwan Al-amri; Raja Kumar Murugesan; Mustafa Man; Alaa Fareed; Mohammed A. Al‐Sharafi; Ammar Ahmed Alkahtani | C48: 2021 | D48: Applied Sciences | E48: Detection (classical ML) | F48: survey/position | G48: 202 | H48: 10.3390/app11125320 | I48: =VLOOKUP($D48,Scopus!$A$2:$K$49,3,FALSE) -> 82.0% 18/99 Fluid Flow and Transfer Processes | J48: =VLOOKUP($D48,Scopus!$A$2:$K$49,10,FALSE) -> Q2 | K48: =VLOOKUP($D48,Scopus!$A$2:$K$49,11,FALSE) -> 2076-3417 | L48: =VLOOKUP(H48,$M$1:$Z$40,14,FALSE) -> #N/A
A49: Deep learning for anomaly detection in log data: A survey | B49: Max Landauer; Sebastian Onder; Florian Skopik; Markus Wurzenberger | C49: 2023 | D49: Machine Learning with Applications | E49: Detection (classical ML) | F49: survey/position | G49: 194 | H49: 10.1016/j.mlwa.2023.100470 | I49: =VLOOKUP($D49,Scopus!$A$2:$K$49,3,FALSE) -> 93.0% 13/203 Computational Theory and Mathematics | J49: =VLOOKUP($D49,Scopus!$A$2:$K$49,10,FALSE) -> Q1 | K49: =VLOOKUP($D49,Scopus!$A$2:$K$49,11,FALSE) -> 2666-8270 | L49: =VLOOKUP(H49,$M$1:$Z$40,14,FALSE) -> #N/A
A50: Zero Touch Management: A Survey of Network Automation Solutions for 5G and 6G Networks | B50: Estefanía Coronado; Rasoul Behravesh; Tejas Subramanya; Adriana Fernández–Fernández; Muhammad Shuaib Siddiqui; Xavier Costa‐Pérez; Roberto Riggio | C50: 2022 | D50: IEEE Communications Surveys and Tutorials | E50: Security IR / SOC | F50: unscreened(rule-classified) | G50: 176 | H50: 10.1109/comst.2022.3212586 | I50: =VLOOKUP($D50,Scopus!$A$2:$K$49,3,FALSE) -> 99.0% 1/1030 Electrical and Electronic Engineering | J50: =VLOOKUP($D50,Scopus!$A$2:$K$49,10,FALSE) -> Q1 | K50: =VLOOKUP($D50,Scopus!$A$2:$K$49,11,FALSE) -> 1553-877X | L50: =VLOOKUP(H50,$M$1:$Z$40,14,FALSE) -> #N/A
A51: EADN: An Efficient Deep Learning Model for Anomaly Detection in Videos | B51: Sareer Ul Amin; Mohib Ullah; Muhammad Sajjad; Faouzi Alaya Cheikh; Mohammad Hijji; Abdulrahman Hijji; Khan Muhammad | C51: 2022 | D51: Mathematics | E51: Detection (classical ML) | F51: systems/empirical | G51: 142 | H51: 10.3390/math10091555 | I51: =VLOOKUP($D51,Scopus!$A$2:$K$49,3,FALSE) -> 92.0% 33/414 General Mathematics | J51: =VLOOKUP($D51,Scopus!$A$2:$K$49,10,FALSE) -> Q2 | K51: =VLOOKUP($D51,Scopus!$A$2:$K$49,11,FALSE) -> 2227-7390 | L51: =VLOOKUP(H51,$M$1:$Z$40,14,FALSE) -> #N/A
A52: Towards Synoptic Water Monitoring Systems: A Review of AI Methods for Automating Water Body Detection and Water Quality Monitoring Using Remote Sensing | B52: Liping Yang; Joshua Driscol; Sarigai Sarigai; Qiusheng Wu; Christopher D. Lippitt; Melinda Morgan | C52: 2022 | D52: Sensors | E52: Detection (classical ML) | F52: unscreened(rule-classified) | G52: 124 | H52: 10.3390/s22062416 | I52: =VLOOKUP($D52,Scopus!$A$2:$K$49,3,FALSE) -> 91.0% 19/206 Instrumentation | J52: =VLOOKUP($D52,Scopus!$A$2:$K$49,10,FALSE) -> Q1 | K52: =VLOOKUP($D52,Scopus!$A$2:$K$49,11,FALSE) -> 1424-8220 | L52: =VLOOKUP(H52,$M$1:$Z$40,14,FALSE) -> #N/A
... A89: An LLM-Based Agentic Network Traffic Incident-Report Approach Towards Explainable-AI Network Defense | B89: Chia-Hong Chou; Arjun Sudheer; Younghee Park | C89: 2026 | D89: Journal of Sensor and Actuator Networks | E89: LLM / agentic ops | F89: systems/empirical | G89: 1 | H89: 10.3390/jsan15020032 | I89: =VLOOKUP($D89,Scopus!$A$2:$K$49,3,FALSE) -> 97.0% 6/198 Control and Optimization | J89: =VLOOKUP($D89,Scopus!$A$2:$K$49,10,FALSE) -> Q2 | K89: =VLOOKUP($D89,Scopus!$A$2:$K$49,11,FALSE) -> 2224-2708 | L89: =VLOOKUP(H89,$M$1:$Z$40,14,FALSE) -> #N/A
A90: VAGNet: Vision-based Accident Anticipation with Global Features | B90: Vipooshan Vipulananthan; Charith D. Chitraranjan | C90: 2026 | D90: IEEE Open Journal of Vehicular Technology, vol. 7, pp. 1873-1883, 2026 | E90: Alert triage & correlation | F90: unscreened(rule-classified) | H90: 10.1109/ojvt.2026.3704953 | I90: =VLOOKUP($D90,Scopus!$A$2:$K$49,3,FALSE) -> #N/A | J90: =VLOOKUP($D90,Scopus!$A$2:$K$49,10,FALSE) -> #N/A | K90: =VLOOKUP($D90,Scopus!$A$2:$K$49,11,FALSE) -> #N/A | L90: =VLOOKUP(H90,$M$1:$Z$40,14,FALSE) -> #N/A
A91: TELESTO: A Graph Neural Network Model for Anomaly Classification in Cloud Services | B91: Dominik Scheinert; Alexander Acker | C91: 2021 | D91: Springer ICSOC LNCS 12632 (2020) 214-227 | E91: Automated remediation | F91: unscreened(rule-classified) | H91: 10.1007/978-3-030-76352-7_23 | I91: =VLOOKUP($D91,Scopus!$A$2:$K$49,3,FALSE) -> #N/A | J91: =VLOOKUP($D91,Scopus!$A$2:$K$49,10,FALSE) -> #N/A | K91: =VLOOKUP($D91,Scopus!$A$2:$K$49,11,FALSE) -> #N/A | L91: =VLOOKUP(H91,$M$1:$Z$40,14,FALSE) -> #N/A
A92: A Decentralised Self-Healing Approach for Network Topology Maintenance | B92: Arles Rodríguez; Jonatan Gómez; Ada Diaconescu | C92: 2020 | D92: Autonomous Agents and Multi-Agent Systems | E92: Automated remediation | F92: systems/empirical | H92: 10.1007/s10458-020-09486-3 | I92: =VLOOKUP($D92,Scopus!$A$2:$K$49,3,FALSE) -> 76.0% 137/570 Artificial Intelligence | J92: =VLOOKUP($D92,Scopus!$A$2:$K$49,10,FALSE) -> Q2 | K92: =VLOOKUP($D92,Scopus!$A$2:$K$49,11,FALSE) -> 1387-2532 | L92: =VLOOKUP(H92,$M$1:$Z$40,14,FALSE) -> #N/A
A93: A unified framework for detecting point and collective anomalies in operating system logs via collaborative transformers | B93: Mohammad Nasirzadeh; Jafar Tahmoresnezhad; Parviz Rashidi-Khazaee | C93: 2025 | D93: Scientific Reports | E93: Detection (classical ML) | F93: systems/empirical | H93: 10.1038/s41598-025-27693-4 | I93: =VLOOKUP($D93,Scopus!$A$2:$K$49,3,FALSE) -> 87.0% 29/223 | J93: =VLOOKUP($D93,Scopus!$A$2:$K$49,10,FALSE) -> Q1 | K93: =VLOOKUP($D93,Scopus!$A$2:$K$49,11,FALSE) -> 2045-2322 | L93: =VLOOKUP(H93,$M$1:$Z$40,14,FALSE) -> #N/A
A94: TARGET: Automated Scenario Generation from Traffic Rules for Testing Autonomous Vehicles via Validated LLM-Guided Knowledge Extraction | B94: Yao Deng; Jiaohong Yao; Zhi Tu; Xi Zheng; Mengshi Zhang; Tianyi Zhang | C94: 2023 | D94: IEEE Transactions on Software Engineering | E94: LLM / agentic ops | F94: unscreened(rule-classified) | H94: 10.1109/tse.2025.3569086 | I94: =VLOOKUP($D94,Scopus!$A$2:$K$49,3,FALSE) -> 92.0% 36/503 Software | J94: =VLOOKUP($D94,Scopus!$A$2:$K$49,10,FALSE) -> Q1 | K94: =VLOOKUP($D94,Scopus!$A$2:$K$49,11,FALSE) -> 0098-5589 | L94: =VLOOKUP(H94,$M$1:$Z$40,14,FALSE) -> #N/A

Sheet Scopus
A1: https://www.scopus.com/sources.uri | B1: 2026-09-06 12:28 (GMT-3)
A2: Source title | B2: CiteScore | C2: Highest percentile | D2: 2022-25 Citations | E2: 2022-25 Documents | F2: % Cited | G2: SNIP | H2: SJR | I2: Publisher | J2: SJR Quartile | K2: ISSN / e-ISSN | P2: Venue | Q2: cluster | R2: paper_type | S2: citations | T2: doi | U2: Scopus (Percentil) | V2: SJR Quartile | W2: ISSN / e-ISSN | AB2: Venue | AC2: SJR | AD2: ISSN | AE2: SJR Site Details
A3: IEEE Communications Surveys and Tutorials | B3: 98.7 | C3: 99.0% 1/1030 Electrical and Electronic Engineering | D3: 33254 | E3: 337 | F3: 99 | G3: 14.933 | H3: 14.838 | I3: IEEE | J3: Q1 | K3: 1553-877X | P3: Telecommunications Policy | Q3: Security IR / SOC | R3: unscreened(rule-classified) | S3: 51 | T3: 10.1016/j.telpol.2025.102976 | U3: 0.97 | V3: Q1 | W3: 0308-5961 | X3: =VLOOKUP(P3,A2:$K$45,2,FALSE) -> 12.7 | AB3: IEEE Transactions on Software Engineering | AC3: Q1 | AD3: 0098-5589 | AE3: =CONCATENATE("https://www.scimagojr.com/journalsearch.php?q=",AD3) -> https://www.scimagojr.com/journalsearch.php?q=0098-5589
A4: ACM Computing Surveys | B4: 65.2 | C4: 99.0% 1/241 General Computer Science | D4: 90231 | E4: 1383 | F4: 92 | G4: 11.121 | H4: 5.985 | I4: Association for Computing Machinery | J4: Q1 | K4: 0360-0300 | P4: ACM Computing Surveys | Q4: Detection (classical ML) | R4: survey/position | S4: 506 | T4: 10.1145/3691338 | U4: 0.99 | V4: Q1 | W4: 0360-0300 | X4: =VLOOKUP(P4,A3:$K$45,2,FALSE) -> 65.2 | AB4: Scientific Reports | AC4: Q1 | AD4: 2045-2322 | AE4: =CONCATENATE("https://www.scimagojr.com/journalsearch.php?q=",AD4) -> https://www.scimagojr.com/journalsearch.php?q=2045-2322
A5: Artificial Intelligence Review | B5: 36.1 | C5: 99.0% 1/1221 Linguistics and Language | D5: 48984 | E5: 1358 | F5: 94 | G5: 6.191 | H5: 3.638 | I5: Springer Nature | J5: Q1 | K5: 0269-2821 | P5: Expert Systems with Applications | Q5: Agent foundations | R5: unscreened(rule-classified) | S5: 59 | T5: 10.1016/j.eswa.2025.128404 | U5: 0.97 | V5: Q1 | W5: 0957-4174 | X5: =VLOOKUP(P5,A4:$K$45,2,FALSE) -> 17 | AB5: Autonomous Agents and Multi-Agent Systems | AC5: Q2 | AD5: 1387-2532 | AE5: =CONCATENATE("https://www.scimagojr.com/journalsearch.php?q=",AD5) -> https://www.scimagojr.com/journalsearch.php?q=1387-2532
A6: Information Fusion | B6: 26.7 | C6: 99.0% 1/203 Signal Processing | D6: 43665 | E6: 1635 | F6: 93 | G6: 4.517 | H6: 4.197 | I6: Elsevier | J6: Q1 | K6: 1566-2535 | P6: ACM Transactions on Software Engineering and Methodology | Q6: Agent foundations | R6: unscreened(rule-classified) | S6: 177 | T6: 10.1145/3712003 | U6: 0.82 | V6: Q1 | W6: 1049-331X | X6: =VLOOKUP(P6,A5:$K$45,2,FALSE) -> 11.6 | AB6: IEEE Open Journal of Vehicular Technology | AC6: Q1 | AD6: 2644-1330 | AE6: =CONCATENATE("https://www.scimagojr.com/journalsearch.php?q=",AD6) -> https://www.scimagojr.com/journalsearch.php?q=2644-1330
A7: IEEE Transactions on Industrial Informatics | B7: 22.4 | C7: 98.0% 10/519 Information Systems | D7: 90744 | E7: 4055 | F7: 91 | G7: 2.607 | H7: 2.983 | I7: IEEE | J7: Q1 | K7: 1551-3203 | P7: Information Fusion | Q7: Agent foundations | R7: survey/position | S7: 169 | T7: 10.1016/j.inffus.2025.103599 | U7: 0.99 | V7: Q1 | W7: 1566-2535 | X7: =VLOOKUP(P7,A6:$K$45,2,FALSE) -> 26.7 | AB7: Journal of Sensor and Actuator Networks | AC7: Q2 | AD7: 2224-2708 | AE7: =CONCATENATE("https://www.scimagojr.com/journalsearch.php?q=",AD7) -> https://www.scimagojr.com/journalsearch.php?q=2224-2708
A8: IEEE Transactions on Intelligent Transportation Systems | B8: 20.5 | C8: 98.0% 2/143 Automotive Engineering | D8: 129839 | E8: 6346 | F8: 88 | G8: 2.758 | H8: 2.608 | I8: IEEE | J8: Q1 | K8: 1524-9050 | P8: IEEE Transactions on Services Computing | Q8: Detection (classical ML) | R8: unscreened(rule-classified) | S8: 217 | T8: 10.1109/tsc.2020.2993728 | U8: 0.9 | V8: Q1 | W8: 1939-1374 | X8: =VLOOKUP(P8,A7:$K$45,2,FALSE) -> 12.9 | AB8: Journal of Universal Computer Science | AC8: Q3 | AD8: 0948-695X | AE8: =CONCATENATE("https://www.scimagojr.com/journalsearch.php?q=",AD8) -> https://www.scimagojr.com/journalsearch.php?q=0948-695X
A9: Journal of Intelligent Manufacturing | B9: 18.5 | C9: 96.0% 17/503 Software | D9: 14942 | E9: 808 | F9: 96 | G9: 2.771 | H9: 1.888 | I9: Springer Nature | J9: Q1 | K9: 0956-5515 | P9: IEEE Transactions on Services Computing | Q9: LLM / agentic ops | R9: unscreened(rule-classified) | S9: 7 | T9: 10.1109/TSC.2025.3629066 | U9: 0.9 | V9: Q1 | W9: 1939-1374 | X9: =VLOOKUP(P9,A8:$K$45,2,FALSE) -> 12.9 | AB9: Computational Intelligence and Neuroscience | AC9: Sem Classificação | AD9: 1687-5265 | AE9: =CONCATENATE("https://www.scimagojr.com/journalsearch.php?q=",AD9) -> https://www.scimagojr.com/journalsearch.php?q=1687-5265
A10: Machine Intelligence Research | B10: 17.8 | C10: 99.0% 2/397 Modeling and Simulation | D10: 4087 | E10: 229 | F10: 77 | G10: 3.072 | H10: 1.894 | I10: Chinese Academy of Sciences | J10: Q1 | K10: 2731-538X | P10: IEEE Transactions on Services Computing | Q10: Root-cause analysis | R10: unscreened(rule-classified) | S10: 0 | T10: 10.1109/TSC.2025.3631913 | U10: 0.9 | V10: Q1 | W10: 1939-1374 | X10: =VLOOKUP(P10,A9:$K$45,2,FALSE) -> 12.9 | AB10: Cognition, Technology and Work | AC10: Q1 | AD10: 1435-5558 | AE10: =CONCATENATE("https://www.scimagojr.com/journalsearch.php?q=",AD10) -> https://www.scimagojr.com/journalsearch.php?q=1435-5558
A11: Expert Systems with Applications | B11: 17 | C11: 97.0% 10/351 General Engineering | D11: 190824 | E11: 11200 | F11: 91 | G11: 2.421 | H11: 1.939 | I11: Elsevier | J11: Q1 | K11: 0957-4174 | P11: Algorithms | Q11: Security IR / SOC | R11: unscreened(rule-classified) | S11: 44 | T11: 10.3390/a18080499 | U11: 0.78 | V11: Q2 | W11: 1999-4893 | X11: =VLOOKUP(P11,A10:$K$45,2,FALSE) -> 5.4 | AB11: Quality and Reliability Engineering International | AC11: Q2 | AD11: 0748-8017 | AE11: =CONCATENATE("https://www.scimagojr.com/journalsearch.php?q=",AD11) -> https://www.scimagojr.com/journalsearch.php?q=0748-8017
A12: IEEE Transactions on Software Engineering | B12: 13.9 | C12: 92.0% 36/503 Software | D12: 13396 | E12: 966 | F12: 84 | G12: 2.412 | H12: 1.568 | I12: IEEE | J12: Q1 | K12: 0098-5589 | P12: Future Internet | Q12: Security IR / SOC | R12: unscreened(rule-classified) | S12: 126 | T12: 10.3390/fi17090404 | U12: 0.84 | V12: Q1 | W12: 1999-5903 | X12: =VLOOKUP(P12,A11:$K$45,2,FALSE) -> 10 | AB12: Journal of International Crisis and Risk Communication Research | AC12: Sem Classificação | AD12: 2576-0017 | AE12: =CONCATENATE("https://www.scimagojr.com/journalsearch.php?q=",AD12) -> https://www.scimagojr.com/journalsearch.php?q=2576-0017
A13: Computers and Industrial Engineering | B13: 13.5 | C13: 96.0% 12/351 General Engineering | D13: 42857 | E13: 3171 | F13: 88 | G13: 1.788 | H13: 1.588 | I13: Elsevier | J13: Q1 | K13: 0360-8352 | P13: F1000Research | Q13: LLM / agentic ops | R13: unscreened(rule-classified) | S13: 21 | T13: 10.12688/f1000research.169927.1 | U13: 0.77 | V13: Q1 | W13: 2046-1402 | X13: =VLOOKUP(P13,A12:$K$45,2,FALSE) -> 2.9 | AB13: Intelligent Systems with Applications | AC13: Q1 | AD13: 2667-3053 | AE13: =CONCATENATE("https://www.scimagojr.com/journalsearch.php?q=",AD13) -> https://www.scimagojr.com/journalsearch.php?q=2667-3053
A14: Intelligent Systems with Applications | B14: 13.1 | C14: 93.0% 12/179 Computer Science (miscellaneous) | D14: 6884 | E14: 526 | F14: 85 | G14: 1.862 | H14: 1.142 | I14: Elsevier | J14: Q1 | K14: 2667-3053 | P14: F1000Research | Q14: Security IR / SOC | R14: survey/position | S14: 13 | T14: 10.12688/f1000research.169337.1 | U14: 0.77 | V14: Q1 | W14: 2046-1402 | X14: =VLOOKUP(P14,A13:$K$45,2,FALSE) -> 2.9 | AB14: Journal of Computational Analysis and Applications | AC14: Sem Classificação | AD14: 1521-1398 | AE14: =CONCATENATE("https://www.scimagojr.com/journalsearch.php?q=",AD14) -> https://www.scimagojr.com/journalsearch.php?q=1521-1398
... A40: Algorithms | B40: 5.4 | C40: 84.0% 34/212 Computational Mathematics | D40: 13039 | E40: 2409 | F40: 72 | G40: 1.01 | H40: 0.57 | I40: Multidisciplinary Digital Publishing Institute (MDPI) | J40: Q2 | K40: 1999-4893 | P40: Array | Q40: LLM / agentic ops | R40: unscreened(rule-classified) | S40: 216 | T40: 10.1016/j.array.2025.100399 | U40: 0.88 | V40: Q1 | W40: 2590-0056 | X40: =VLOOKUP(P40,A39:$K$45,2,FALSE) -> #N/A | AB40: Algorithms | AC40: Q2 | AD40: 1999-4893 | AE40: =CONCATENATE("https://www.scimagojr.com/journalsearch.php?q=",AD40) -> https://www.scimagojr.com/journalsearch.php?q=1999-4893
A41: Mathematics | B41: 5.4 | C41: 92.0% 33/414 General Mathematics | D41: 95684 | E41: 17727 | F41: 73 | G41: 0.932 | H41: 0.497 | I41: Multidisciplinary Digital Publishing Institute (MDPI) | J41: Q2 | K41: 2227-7390 | P41: IEEE Transactions on Industrial Informatics | Q41: Automated remediation | R41: unscreened(rule-classified) | S41: 401 | T41: 10.1109/tii.2020.3022432 | U41: #N/A | V41: Q1 | W41: 1551-3203 | X41: =VLOOKUP(P41,A40:$K$45,2,FALSE) -> #N/A | AB41: IEEE Transactions on Services Computing | AC41: Q1 | AD41: 1939-1374 | AE41: =CONCATENATE("https://www.scimagojr.com/journalsearch.php?q=",AD41) -> https://www.scimagojr.com/journalsearch.php?q=1939-1374
A42: Computational Intelligence | B42: 5.3 | C42: 83.0% 36/212 Computational Mathematics | D42: 1679 | E42: 316 | F42: 68 | G42: 0.775 | H42: 0.488 | I42: John Wiley & Sons | J42: Q2 | K42: 0824-7935 | P42: Applied Sciences | Q42: Detection (classical ML) | R42: survey/position | S42: 396 | T42: 10.3390/app14020898 | U42: #N/A | V42: #N/A | W42: #N/A | X42: =VLOOKUP(P42,A41:$K$45,2,FALSE) -> #N/A | AB42: Information Fusion | AC42: Q1 | AD42: 1566-2535 | AE42: =CONCATENATE("https://www.scimagojr.com/journalsearch.php?q=",AD42) -> https://www.scimagojr.com/journalsearch.php?q=1566-2535
A43: Computation | B43: 5.2 | C43: 85.0% 101/680 Applied Mathematics | D43: 5224 | E43: 1014 | F43: 73 | G43: 0.988 | H43: 0.477 | I43: Multidisciplinary Digital Publishing Institute (MDPI) | J43: Q2 | K43: 2079-3197 | P43: Machine Intelligence Research | Q43: Detection (classical ML) | R43: survey/position | S43: 389 | T43: 10.1007/s11633-023-1459-z | U43: #N/A | V43: #N/A | W43: #N/A | X43: =VLOOKUP(P43,A42:$K$45,2,FALSE) -> #N/A | AB43: ACM Transactions on Software Engineering and Methodology | AC43: Q1 | AD43: 1049-331X | AE43: =CONCATENATE("https://www.scimagojr.com/journalsearch.php?q=",AD43) -> https://www.scimagojr.com/journalsearch.php?q=1049-331X
A44: F1000Research | B44: 2.9 | C44: 79.0% 139/692 Arts and Humanities (miscellaneous) | D44: 7558 | E44: 2612 | F44: 64 | G44: 0.641 | H44: 0.432 | I44: Taylor & Francis | J44: Q1 | K44: 2046-1402 | P44: Physical review. D/Physical review. D. | Q44: Detection (classical ML) | R44: systems/empirical | S44: 315 | T44: 10.1103/physrevd.101.075042 | U44: #N/A | V44: #N/A | W44: #N/A | X44: =VLOOKUP(P44,A43:$K$45,2,FALSE) -> #N/A | AB44: Expert Systems with Applications | AC44: Q1 | AD44: 0957-4174 | AE44: =CONCATENATE("https://www.scimagojr.com/journalsearch.php?q=",AD44) -> https://www.scimagojr.com/journalsearch.php?q=0957-4174
A45: Journal of Universal Computer Science | B45: 2.6 | C45: 47.0% 71/135 Theoretical Computer Science | D45: 681 | E45: 258 | F45: 62 | G45: 0.491 | H45: 0.308 | I45: Technische Universitat Graz from Austria | J45: Q3 | K45: 0948-695X | P45: Sensors | Q45: Detection (classical ML) | R45: survey/position | S45: 264 | T45: 10.3390/s23135970 | U45: #N/A | V45: #N/A | W45: #N/A | X45: =VLOOKUP(P45,A44:$K$45,2,FALSE) -> #N/A | AB45: ACM Computing Surveys | AC45: Q1 | AD45: 0360-0300 | AE45: =CONCATENATE("https://www.scimagojr.com/journalsearch.php?q=",AD45) -> https://www.scimagojr.com/journalsearch.php?q=0360-0300
A46: IEEE Access | B46: 9.3 | C46: 91.0% 31/351 General Engineering | D46: 437277 | E46: 46875 | F46: 79 | G46: 1.483 | H46: 0.884 | I46: IEEE | J46: Q1 | K46: 2169-3536 | P46: Journal of Intelligent Manufacturing | Q46: Detection (classical ML) | R46: systems/empirical | S46: 247 | T46: 10.1007/s10845-022-01960-x | U46: #N/A | V46: #N/A | W46: #N/A | X46: =VLOOKUP(P46,A45:$K$45,2,FALSE) -> #N/A | AB46: Telecommunications Policy | AC46: Q1 | AD46: 0308-5961 | AE46: =CONCATENATE("https://www.scimagojr.com/journalsearch.php?q=",AD46) -> https://www.scimagojr.com/journalsearch.php?q=0308-5961
A47: Electronics | B47: 7 | C47: 83.0% 35/203 Signal Processing | D47: 134403 | E47: 19097 | F47: 78 | G47: 1.034 | H47: 0.623 | I47: Multidisciplinary Digital Publishing Institute (MDPI) | J47: Q2 | K47: 2079-9292 | P47: Frontiers in Neuroscience | Q47: Human factors | R47: survey/position | S47: 245 | T47: 10.3389/fnins.2020.00268 | U47: #N/A | V47: #N/A | W47: #N/A | X47: =VLOOKUP(P47,A$45:$K46,2,FALSE) -> #N/A | AB47: Array | AC47: Q1 | AD47: 2590-0056 | AE47: =CONCATENATE("https://www.scimagojr.com/journalsearch.php?q=",AD47) -> https://www.scimagojr.com/journalsearch.php?q=2590-0056
A48: Computers | B48: 9.1 | C48: 86.0% 25/179 Computer Science (miscellaneous) | D48: 12296 | E48: 1347 | F48: 74 | G48: 1.8 | H48: 0.935 | I48: Multidisciplinary Digital Publishing Institute (MDPI) | J48: Q1 | K48: 2073-431X | P48: Personal and Ubiquitous Computing | Q48: Benchmarks & evaluation | R48: unscreened(rule-classified) | S48: 233 | T48: 10.1007/s00779-021-01582-9 | U48: #N/A | V48: #N/A | W48: #N/A | X48: =VLOOKUP(P48,A$45:$K47,2,FALSE) -> #N/A | AB48: IEEE Transactions on Industrial Informatics | AC48: Q1 | AD48: 1551-3203 | AE48: =CONCATENATE("https://www.scimagojr.com/journalsearch.php?q=",AD48) -> https://www.scimagojr.com/journalsearch.php?q=1551-3203
A49: Cognition, Technology and Work | B49: 8.2 | C49: 99.0% 9/891 Philosophy | D49: 1228 | E49: 149 | F49: 76 | G49: 1.572 | H49: 0.839 | I49: Springer Nature | J49: Q1 | K49: 1435-5558 | P49: Applied Sciences | Q49: Detection (classical ML) | R49: survey/position | S49: 202 | T49: 10.3390/app11125320 | U49: #N/A | V49: #N/A | W49: #N/A | X49: =VLOOKUP(P49,A$45:$K48,2,FALSE) -> #N/A | AB49: IEEE Access | AC49: Q1 | AD49: 2169-3536 | AE49: =CONCATENATE("https://www.scimagojr.com/journalsearch.php?q=",AD49) -> https://www.scimagojr.com/journalsearch.php?q=2169-3536
A50: Computers and Industrial Engineering | B50: 13.5 | C50: 96.0% 12/351 General Engineering | D50: 42857 | E50: 3171 | F50: 88 | G50: 1.788 | H50: 1.588 | I50: Elsevier | J50: Q1 | K50: 0360-8352 | P50: Machine Learning with Applications | Q50: Detection (classical ML) | R50: survey/position | S50: 194 | T50: 10.1016/j.mlwa.2023.100470 | U50: #N/A | V50: #N/A | W50: #N/A | X50: =VLOOKUP(P50,A$45:$K49,2,FALSE) -> #N/A | AB50: Electronics | AC50: Q2 | AD50: 2079-9292 | AE50: =CONCATENATE("https://www.scimagojr.com/journalsearch.php?q=",AD50) -> https://www.scimagojr.com/journalsearch.php?q=2079-9292
P51: IEEE Communications Surveys & Tutorials | Q51: Security IR / SOC | R51: unscreened(rule-classified) | S51: 176 | T51: 10.1109/comst.2022.3212586 | U51: #N/A | V51: #N/A | W51: #N/A | X51: =VLOOKUP(P51,A$45:$K50,2,FALSE) -> #N/A | AB51: Computers | AC51: Q1 | AD51: 2073-431X | AE51: =CONCATENATE("https://www.scimagojr.com/journalsearch.php?q=",AD51) -> https://www.scimagojr.com/journalsearch.php?q=2073-431X
P52: Mathematics | Q52: Detection (classical ML) | R52: systems/empirical | S52: 142 | T52: 10.3390/math10091555 | U52: #N/A | V52: #N/A | W52: #N/A | X52: =VLOOKUP(P52,A$45:$K51,2,FALSE) -> #N/A
P53: Sensors | Q53: Detection (classical ML) | R53: unscreened(rule-classified) | S53: 124 | T53: 10.3390/s22062416 | U53: #N/A | V53: #N/A | W53: #N/A | X53: =VLOOKUP(P53,A$45:$K52,2,FALSE) -> #N/A
P54: Computers & Industrial Engineering | Q54: Root-cause analysis | R54: systems/empirical | S54: 87 | T54: 10.1016/j.cie.2021.107580 | U54: #N/A | V54: #N/A | W54: #N/A | X54: =VLOOKUP(P54,A$45:$K53,2,FALSE) -> #N/A
P55: Energies | Q55: Detection (classical ML) | R55: systems/empirical | S55: 80 | T55: 10.3390/en14071845 | U55: #N/A | V55: #N/A | W55: #N/A | X55: =VLOOKUP(P55,A$45:$K54,2,FALSE) -> #N/A
P56: Frontiers in Neuroscience | Q56: Detection (classical ML) | R56: unscreened(rule-classified) | S56: 71 | T56: 10.3389/fnins.2020.549524 | U56: #N/A | V56: #N/A | W56: #N/A | X56: =VLOOKUP(P56,A$45:$K55,2,FALSE) -> #N/A
P57: IEEE Transactions on Dependable and Secure Computing | Q57: Detection (classical ML) | R57: systems/empirical | S57: 68 | T57: 10.1109/tdsc.2020.3037903 | U57: #N/A | V57: #N/A | W57: #N/A | X57: =VLOOKUP(P57,A$45:$K56,2,FALSE) -> #N/A
P58: Frontiers in Computer Science | Q58: Automated remediation | R58: unscreened(rule-classified) | S58: 62 | T58: 10.3389/fcomp.2020.00036 | U58: #N/A | V58: #N/A | W58: #N/A | X58: =VLOOKUP(P58,A$45:$K57,2,FALSE) -> #N/A
P59: Computation | Q59: Security IR / SOC | R59: survey/position | S59: 57 | T59: 10.3390/computation13020030 | U59: #N/A | V59: #N/A | W59: #N/A | X59: =VLOOKUP(P59,A$45:$K58,2,FALSE) -> #N/A
P60: Energies | Q60: Alert triage & correlation | R60: unscreened(rule-classified) | S60: 53 | T60: 10.3390/en14061728 | U60: #N/A | V60: #N/A | W60: #N/A | X60: =VLOOKUP(P60,A$45:$K59,2,FALSE) -> #N/A
P61: Applied Sciences | Q61: Alert triage & correlation | R61: systems/empirical | S61: 52 | T61: 10.3390/app13116610 | U61: #N/A | V61: #N/A | W61: #N/A | X61: =VLOOKUP(P61,A$45:$K60,2,FALSE) -> #N/A
P62: Information | Q62: LLM / agentic ops | R62: unscreened(rule-classified) | S62: 52 | T62: 10.3390/info16020087 | U62: #N/A | V62: #N/A | W62: #N/A | X62: =VLOOKUP(P62,A$45:$K61,2,FALSE) -> #N/A
P63: Journal of Medical Internet Research | Q63: Benchmarks & evaluation | R63: unscreened(rule-classified) | S63: 50 | T63: 10.2196/29386 | U63: #N/A | V63: #N/A | W63: #N/A | X63: =VLOOKUP(P63,A$45:$K62,2,FALSE) -> #N/A
... P90: Journal of Sensor and Actuator Networks | Q90: LLM / agentic ops | R90: systems/empirical | S90: 1 | T90: 10.3390/jsan15020032 | U90: #N/A | V90: #N/A | W90: #N/A | X90: =VLOOKUP(P90,A$45:$K89,2,FALSE) -> #N/A
P91: IEEE Open Journal of Vehicular Technology, vol. 7, pp. 1873-1883, 2026 | Q91: Alert triage & correlation | R91: unscreened(rule-classified) | T91: 10.1109/ojvt.2026.3704953 | U91: #N/A | V91: #N/A | W91: #N/A | X91: =VLOOKUP(P91,A$45:$K90,2,FALSE) -> #N/A
P92: Springer ICSOC LNCS 12632 (2020) 214-227 | Q92: Automated remediation | R92: unscreened(rule-classified) | T92: 10.1007/978-3-030-76352-7_23 | U92: #N/A | V92: #N/A | W92: #N/A | X92: =VLOOKUP(P92,A$45:$K91,2,FALSE) -> #N/A
P93: Autonomous Agents and Multi-Agent Systems, 35(1), 6 (2020) | Q93: Automated remediation | R93: systems/empirical | T93: 10.1007/s10458-020-09486-3 | U93: #N/A | V93: #N/A | W93: #N/A | X93: =VLOOKUP(P93,A$45:$K92,2,FALSE) -> #N/A
P94: Scientific Reports 15, 45698 (2025) | Q94: Detection (classical ML) | R94: systems/empirical | T94: 10.1038/s41598-025-27693-4 | U94: #N/A | V94: #N/A | W94: #N/A | X94: =VLOOKUP(P94,A$45:$K93,2,FALSE) -> #N/A
P95: IEEE Transactions on Software Engineering, Jul. 2025, pp. 1950-1968, vol. 51 | Q95: LLM / agentic ops | R95: unscreened(rule-classified) | T95: 10.1109/tse.2025.3569086 | U95: #N/A | V95: #N/A | W95: #N/A | X95: =VLOOKUP(P95,A$45:$K94,2,FALSE) -> #N/A

Sheet Sheet5
D1: ISSN | E1: Venue | F1: SJR | G1: SJR Site Details
C2: 1 | D2: 0098-5589 | E2: IEEE Transactions on Software Engineering | F2: Q1 | G2: =CONCATENATE("https://www.scimagojr.com/journalsearch.php?q=",D2) -> https://www.scimagojr.com/journalsearch.php?q=0098-5589
C3: 2 | D3: 2045-2322 | E3: Scientific Reports | F3: Q1 | G3: =CONCATENATE("https://www.scimagojr.com/journalsearch.php?q=",D3) -> https://www.scimagojr.com/journalsearch.php?q=2045-2322
C4: 3 | D4: 1387-2532 | E4: Autonomous Agents and Multi-Agent Systems | F4: Q2 | G4: =CONCATENATE("https://www.scimagojr.com/journalsearch.php?q=",D4) -> https://www.scimagojr.com/journalsearch.php?q=1387-2532
C5: 4 | D5: 2644-1330 | E5: IEEE Open Journal of Vehicular Technology | F5: Q1 | G5: =CONCATENATE("https://www.scimagojr.com/journalsearch.php?q=",D5) -> https://www.scimagojr.com/journalsearch.php?q=2644-1330
C6: 5 | D6: 2224-2708 | E6: Journal of Sensor and Actuator Networks | F6: Q2 | G6: =CONCATENATE("https://www.scimagojr.com/journalsearch.php?q=",D6) -> https://www.scimagojr.com/journalsearch.php?q=2224-2708
C7: 6 | D7: 0948-695X | E7: Journal of Universal Computer Science | F7: Q3 | G7: =CONCATENATE("https://www.scimagojr.com/journalsearch.php?q=",D7) -> https://www.scimagojr.com/journalsearch.php?q=0948-695X
C8: 7 | D8: 1687-5265 | E8: Computational Intelligence and Neuroscience | F8: Sem Classificação | G8: =CONCATENATE("https://www.scimagojr.com/journalsearch.php?q=",D8) -> https://www.scimagojr.com/journalsearch.php?q=1687-5265
C9: 8 | D9: 1435-5558 | E9: Cognition, Technology and Work | F9: Q1 | G9: =CONCATENATE("https://www.scimagojr.com/journalsearch.php?q=",D9) -> https://www.scimagojr.com/journalsearch.php?q=1435-5558
C10: 9 | D10: 0748-8017 | E10: Quality and Reliability Engineering International | F10: Q2 | G10: =CONCATENATE("https://www.scimagojr.com/journalsearch.php?q=",D10) -> https://www.scimagojr.com/journalsearch.php?q=0748-8017
C11: 10 | D11: 2576-0017 | E11: Journal of International Crisis and Risk Communication Research | F11: Sem Classificação | G11: =CONCATENATE("https://www.scimagojr.com/journalsearch.php?q=",D11) -> https://www.scimagojr.com/journalsearch.php?q=2576-0017
C12: 11 | D12: 2667-3053 | E12: Intelligent Systems with Applications | F12: Q1 | G12: =CONCATENATE("https://www.scimagojr.com/journalsearch.php?q=",D12) -> https://www.scimagojr.com/journalsearch.php?q=2667-3053
C13: 12 | D13: 1521-1398 | E13: Journal of Computational Analysis and Applications | F13: Sem Classificação | G13: =CONCATENATE("https://www.scimagojr.com/journalsearch.php?q=",D13) -> https://www.scimagojr.com/journalsearch.php?q=1521-1398
... C47: 46 | D47: 1551-3203 | E47: IEEE Transactions on Industrial Informatics | F47: Q1 | G47: =CONCATENATE("https://www.scimagojr.com/journalsearch.php?q=",D47) -> https://www.scimagojr.com/journalsearch.php?q=1551-3203

Sheet Sheet3
G1: 0308-5961
G2: 0360-0300
G3: 0957-4174
G4: 1049-331X
G5: 1566-2535
G6: 1939-1374
G7: 1999-4893
G8: 1999-5903
G9: 2046-1402
G10: 2079-9292
G11: 2169-3536

Sheet Detail1
A1: Details for Count of title - venue: ACM Computing Surveys (+)
A3: title | B3: authors | C3: year | D3: venue | E3: cluster | F3: paper_type | G3: citations | H3: doi | I3: arxiv_or_openalex_id | J3: in_your_seed_set | K3: is_landmark | L3: src
A4: From LLM Reasoning to Autonomous AI Agents: A Comprehensive Review | B4: Mohamed Amine Ferrag; Norbert Tihanyi; Mérouane Debbah | C4: 2026 | D4: IEEE Access | E4: Agent foundations | F4: survey/position | G4: 7.0 | H4: 10.1109/access.2026.3698694 | I4: W4416982487 | J4: 0 | K4: 0 | L4: openalex
A5: AI Agents vs. Agentic AI: A Conceptual taxonomy, applications and challenges | B5: Ranjan Sapkota; Konstantinos I. Roumeliotis; Manoj Karkee | C5: 2025 | D5: Information Fusion | E5: Agent foundations | F5: survey/position | G5: 169.0 | H5: 10.1016/j.inffus.2025.103599 | I5: W4413427262 | J5: 1 | K5: 0 | L5: openalex
A6: Telemetry and Agentic AI: Foundations for Optical Network Automation | B6: Sergio Cruzes | C6: 2025 | D6: IEEE Access | E6: Agent foundations | F6: unscreened(rule-classified) | G6: 3.0 | H6: 10.1109/access.2025.3649768 | I6: W7117556955 | J6: 0 | K6: 0 | L6: openalex
A7: AgentAI: A comprehensive survey on autonomous agents in distributed AI for industry 4.0 | B7: Francesco Piccialli; Diletta Chiaro; Sundas Sarwar; Donato Cerciello; Pian Qi; Valeria Mele | C7: 2025 | D7: Expert Systems with Applications | E7: Agent foundations | F7: unscreened(rule-classified) | G7: 59.0 | H7: 10.1016/j.eswa.2025.128404 | I7: W4410954314 | J7: 1 | K7: 0 | L7: openalex
A8: LLM-Based Multi-Agent Systems for Software Engineering: Literature Review, Vision, and the Road Ahead | B8: Junda He; Christoph Treude; David Lo | C8: 2025 | D8: ACM Transactions on Software Engineering and Methodology | E8: Agent foundations | F8: unscreened(rule-classified) | G8: 177.0 | H8: 10.1145/3712003 | I8: W4406325768 | J8: 1 | K8: 0 | L8: openalex
A9: Small Language Model Agent for the Operations of Continuously Updating ICT Systems | B9: Nobukazu Fukuda; Haruhisa Nozue; Haruo Oishi | C9: 2025 | D9: IEEE Access | E9: Agent foundations | F9: unscreened(rule-classified) | G9: 0.0 | H9: 10.1109/ACCESS.2025.3544637 | I9: W4407900333 | J9: 1 | K9: 0 | L9: openalex
A10: Co-Evolving Multi-Agent Transfer Reinforcement Learning via Scenario Independent Representation | B10: Ayesha Siddiqua; Siming Liu; Ayesha Siddika Nipu; Anthony M. Harris; Yan Liu | C10: 2024 | D10: IEEE Access | E10: Agent foundations | F10: unscreened(rule-classified) | G10: 9.0 | H10: 10.1109/ACCESS.2024.3430037 | I10: W4400726849 | J10: 1 | K10: 0 | L10: openalex
A11: Agent System Mining: Vision, Benefits, and Challenges | B11: Andrei Tour; Artem Polyvyanyy; Anna Kalenkova | C11: 2021 | D11: IEEE Access | E11: Agent foundations | F11: unscreened(rule-classified) | G11: 32.0 | H11: 10.1109/ACCESS.2021.3095464 | I11: W3180674049 | J11: 1 | K11: 0 | L11: openalex
A12: Artificial Empathy: A New Perspective for Analyzing and Designing Multi-Agent Systems | B12: Jize Chen; Dali Zhang; Zhenshen Qu; Changhong Wang | C12: 2020 | D12: IEEE Access | E12: Agent foundations | F12: unscreened(rule-classified) | G12: 10.0 | H12: 10.1109/ACCESS.2020.3029502 | I12: W3092406976 | J12: 1 | K12: 0 | L12: openalex
A13: VAGNet: Vision-based Accident Anticipation with Global Features | B13: Vipooshan Vipulananthan; Charith D. Chitraranjan | C13: 2026 | D13: IEEE Open Journal of Vehicular Technology, vol. 7, pp. 1873-1883, 2026 | E13: Alert triage & correlation | F13: unscreened(rule-classified) | H13: 10.1109/ojvt.2026.3704953 | I13: 2604.09305 | J13: 0 | K13: 0 | L13: arxiv
A14: AI-Assisted Security Alert Data Analysis with Imbalanced Learning Methods | B14: Samuel Ndichu; Tao Ban; Takeshi Takahashi; Daisuke Inoue | C14: 2023 | D14: Applied Sciences | E14: Alert triage & correlation | F14: systems/empirical | G14: 19.0 | H14: 10.3390/app13031977 | I14: W4319080536 | J14: 0 | K14: 0 | L14: openalex
A15: Breaking Alert Fatigue: AI-Assisted SIEM Framework for Effective Incident Response | B15: Tao Ban; Takeshi Takahashi; Samuel Ndichu; Daisuke Inoue | C15: 2023 | D15: Applied Sciences | E15: Alert triage & correlation | F15: systems/empirical | G15: 52.0 | H15: 10.3390/app13116610 | I15: W4381569470 | J15: 0 | K15: 0 | L15: openalex
A16: Wind Turbine Fault Detection Using Highly Imbalanced Real SCADA Data | B16: Cristian Velandia; Yolanda Vidal; Francesc Pozo | C16: 2021 | D16: Energies | E16: Alert triage & correlation | F16: unscreened(rule-classified) | G16: 53.0 | H16: 10.3390/en14061728 | I16: W3137151386 | J16: 0 | K16: 0 | L16: openalex
A17: Thermographic and cognitive assessment of fatigue in vessel traffic service operators: a socio-technical approach | B17: Fernando Crestelo Moreno; John González; Juan Suardíaz Muro; R. López-Alonso | C17: 2025 | D17: Cognition Technology & Work | E17: Automated remediation | F17: unscreened(rule-classified) | G17: 6.0 | H17: 10.1007/s10111-025-00804-x | I17: W4411424618 | J17: 0 | K17: 0 | L17: openalex
A18: Toward Robust Security Orchestration and Automated Response in Security Operations Centers with a Hyper-Automation Approach Using Agentic Artificial Intelligence | B18: Ismail Ismail; Rahmat Kurnia; Zilmas Arjuna Brata; Ghitha Afina Nelistiani; Shinwook Heo; Hyeongon Kim; Hyeongon Kim; Howon Kim; Howon Kim | C18: 2025 | D18: Information | E18: Automated remediation | F18: unscreened(rule-classified) | G18: 31.0 | H18: 10.3390/info16050365 | I18: W4409965657 | J18: 0 | K18: 0 | L18: openalex
A19: Transparent Automated Advice to Mitigate the Impact of Variation in Automation Reliability | B19: Isabella Gegoff; Monica Tatasciore; Vanessa K. Bowden; Jason S. McCarley; Shayne Loft | C19: 2023 | D19: Human Factors The Journal of the Human Factors and Ergonomics Society | E19: Automated remediation | F19: unscreened(rule-classified) | G19: 24.0 | H19: 10.1177/00187208231196738 | I19: W4386209057 | J19: 0 | K19: 0 | L19: openalex
A20: Using fNIRS to Verify Trust in Highly Automated Driving | B20: Jaume Perelló-March; Christopher Burns; Roger Woodman; Mark T. Elliott; Stewart Birrell | C20: 2022 | D20: IEEE Transactions on Intelligent Transportation Systems | E20: Automated remediation | F20: unscreened(rule-classified) | G20: 33.0 | H20: 10.1109/tits.2022.3211089 | I20: W4312966716 | J20: 0 | K20: 0 | L20: openalex
A21: TELESTO: A Graph Neural Network Model for Anomaly Classification in Cloud Services | B21: Dominik Scheinert; Alexander Acker | C21: 2021 | D21: Springer ICSOC LNCS 12632 (2020) 214-227 | E21: Automated remediation | F21: unscreened(rule-classified) | H21: 10.1007/978-3-030-76352-7_23 | I21: 2102.12877 | J21: 0 | K21: 0 | L21: arxiv
A22: A Decentralised Self-Healing Approach for Network Topology Maintenance | B22: Arles Rodríguez; Jonatan Gómez; Ada Diaconescu | C22: 2020 | D22: Autonomous Agents and Multi-Agent Systems, 35(1), 6 (2020) | E22: Automated remediation | F22: systems/empirical | H22: 10.1007/s10458-020-09486-3 | I22: 2010.11146 | J22: 0 | K22: 0 | L22: arxiv
A23: The Challenges of Leveraging Threat Intelligence to Stop Data Breaches | B23: Amani S. Ibrahim; Dhananjay Thiruvady; Jean-Guy Schneider; Mohamed Abdelrazek | C23: 2020 | D23: Frontiers in Computer Science | E23: Automated remediation | F23: unscreened(rule-classified) | G23: 62.0 | H23: 10.3389/fcomp.2020.00036 | I23: W3081936891 | J23: 0 | K23: 0 | L23: openalex
A24: Variational LSTM Enhanced Anomaly Detection for Industrial Big Data | B24: Xiaokang Zhou; Yiyong Hu; Wei Liang; Jianhua Ma; Qun Jin | C24: 2020 | D24: IEEE Transactions on Industrial Informatics | E24: Automated remediation | F24: unscreened(rule-classified) | G24: 401.0 | H24: 10.1109/tii.2020.3022432 | I24: W3086419524 | J24: 0 | K24: 0 | L24: openalex
A25: Multi-Agent Coordination Strategies vs. Retrieval-Augmented Generation in LLMs: A Comparative Evaluation | B25: Irina Radeva; Иван Попчев; Lyubka Doukovska; Miroslava Dimitrova | C25: 2025 | D25: Electronics | E25: Benchmarks & evaluation | F25: unscreened(rule-classified) | G25: 0.0 | H25: 10.3390/electronics14244883 | I25: W4417244517 | J25: 1 | K25: 0 | L25: openalex
A26: Retail Resilience Engine: An Agentic AI Framework for Building Reliable Retail Systems With Test-Driven Development Approach | B26: Lalit Narayan Mishra; Biswaranjan Senapati | C26: 2025 | D26: IEEE Access | E26: Benchmarks & evaluation | F26: unscreened(rule-classified) | G26: 34.0 | H26: 10.1109/ACCESS.2025.3552592 | I26: W4408564575 | J26: 1 | K26: 0 | L26: openalex
A27: Availability analysis of redundant and replicated cloud services with Bayesian networks | B27: Otto Bibartiu; Frank Dürr; Kurt Rothermel; Beate Ottenwälder; Andreas Grau | C27: 2023 | D27: Quality and Reliability Engineering International | E27: Benchmarks & evaluation | F27: systems/empirical | G27: 7.0 | H27: 10.1002/qre.3414 | I27: W4385241681 | J27: 0 | K27: 0 | L27: openalex
A28: The Chatbot Usability Scale: the Design and Pilot of a Usability Scale for Interaction with AI-Based Conversational Agents | B28: Simone Borsci; Alessio Malizia; Martin Schmettow; Frank van der Velde; Gunay Tariverdiyeva; Divyaa Balaji; Alan Chamberlain | C28: 2021 | D28: Personal and Ubiquitous Computing | E28: Benchmarks & evaluation | F28: unscreened(rule-classified) | G28: 233.0 | H28: 10.1007/s00779-021-01582-9 | I28: W3187911027 | J28: 0 | K28: 0 | L28: openalex
A29: The Impact of Explanations on Layperson Trust in Artificial Intelligence–Driven Symptom Checker Apps: Experimental Study | B29: Claire Woodcock; Brent Mittelstadt; Dan Busbridge; Grant Blank | C29: 2021 | D29: Journal of Medical Internet Research | E29: Benchmarks & evaluation | F29: unscreened(rule-classified) | G29: 50.0 | H29: 10.2196/29386 | I29: W3210874941 | J29: 0 | K29: 0 | L29: openalex
A30: Tools and Benchmarks for Automated Log Parsing | B30: Jieming Zhu; Shilin He; Jinyang Liu; Pinjia He; Qi Xie; Zibin Zheng; Michael R. Lyu | C30: 2019 | D30: conference-paper | E30: Benchmarks & evaluation | F30: unscreened(rule-classified) | G30: 538.0 | H30: 10.1109/icse-seip.2019.00021 | I30: W2963999143 | J30: 0 | K30: 0 | L30: openalex
A31: Using AI to Monitor AI: Automated Operations Through Log-Driven Intelligence | B31: Chen Qi; Xiaoying Qiao | C31: 2026 | D31: conference-paper | E31: Detection (classical ML) | F31: unscreened(rule-classified) | G31: 0.0 | H31: 10.1109/icbase70763.2026.11619459 | I31: W7171729227 | J31: 0 | K31: 0 | L31: openalex
A32: A unified framework for detecting point and collective anomalies in operating system logs via collaborative transformers | B32: Mohammad Nasirzadeh; Jafar Tahmoresnezhad; Parviz Rashidi-Khazaee | C32: 2025 | D32: Scientific Reports 15, 45698 (2025) | E32: Detection (classical ML) | F32: systems/empirical | H32: 10.1038/s41598-025-27693-4 | I32: 2512.23380 | J32: 0 | K32: 0 | L32: arxiv
A33: Towards Autonomous Planetary Exploration | B33: Martin J. Schuster; Sebastian G. Brunner; Kristin Bussmann; Stefan Büttner; Andreas Dömel; Matthias Hellerer; Hannah Lehner; Peter Lehner; Oliver Porges; Josef Reill; Sebastian Riedel; Mallikarjuna Vayugundla; Bernhard Vodermayer; Tim Bodenmüller; Christoph Brand; Werner Friedl; Iris Grixa; Heiko Hirschmüller; Michael Kaßecker; Zoltán-Csaba Márton; Christian Nissler; Felix Ruess; Michael Suppa; Ar | C33: 2017 | D33: Journal of Intelligent & Robotic Systems | E33: Detection (classical ML) | F33: unscreened(rule-classified) | G33: 91.0 | H33: 10.1007/s10846-017-0680-9 | I33: W2767694002 | J33: 0 | K33: 0 | L33: openalex
A34: Artificial Intelligence for Predictive Maintenance Applications: Key Components, Trustworthiness, and Future Trends | B34: Ayşegül Uçar; Mehmet Karaköse; Necim Kırımça | C34: 2024 | D34: Applied Sciences | E34: Detection (classical ML) | F34: survey/position | G34: 396.0 | H34: 10.3390/app14020898 | I34: W4391098453 | J34: 0 | K34: 0 | L34: openalex
A35: Cloud Network Anomaly Detection Using Machine and Deep Learning Techniques— Recent Research Advancements | B35: Amira Mahamat Abdallah; Aysha Saif Rashed Obaid Alkaabi; Ghaya Bark Nasser Douman Alameri; Saida Hafsa Rafique; Nura Shifa Musa; M. Thangavel | C35: 2024 | D35: IEEE Access | E35: Detection (classical ML) | F35: survey/position | G35: 78.0 | H35: 10.1109/access.2024.3390844 | I35: W4394939094 | J35: 0 | K35: 0 | L35: openalex
A36: Chained Anomaly Detection Models for Federated Learning: An Intrusion Detection Case Study | B36: Davy Preuveneers; Vera Rimmer; Ilias Tsingenopoulos; Jan Spooren; Wouter Joosen; Elisabeth Ilie‐Zudor | C36: 2018 | D36: Applied Sciences | E36: Detection (classical ML) | F36: systems/empirical | G36: 320.0 | H36: 10.3390/app8122663 | I36: W2903872466 | J36: 0 | K36: 0 | L36: openalex
A37: Unsupervised Anomaly Detection With LSTM Neural Networks | B37: Tolga Ergen; Süleyman S. Kozat | C37: 2019 | D37: IEEE Transactions on Neural Networks and Learning Systems | E37: Detection (classical ML) | F37: unscreened(rule-classified) | G37: 379.0 | H37: 10.1109/tnnls.2019.2935975 | I37: W2766761849 | J37: 0 | K37: 0 | L37: openalex
A38: Deep Industrial Image Anomaly Detection: A Survey | B38: Jiaqi Liu; Guoyang Xie; Jinbao Wang; Shangnian Li; Chengjie Wang; Feng Zheng; Yaochu Jin | C38: 2024 | D38: Machine Intelligence Research | E38: Detection (classical ML) | F38: survey/position | G38: 389.0 | H38: 10.1007/s11633-023-1459-z | I38: W4390875033 | J38: 0 | K38: 0 | L38: openalex
A39: Deep Learning for Time Series Anomaly Detection: A Survey | B39: Zahra Zamanzadeh Darban; Geoffrey I. Webb; Shirui Pan; Charų C. Aggarwal; Mahsa Salehi | C39: 2024 | D39: ACM Computing Surveys | E39: Detection (classical ML) | F39: survey/position | G39: 506.0 | H39: 10.1145/3691338 | I39: W4402056503 | J39: 0 | K39: 0 | L39: openalex
A40: Deep Learning or Classical Machine Learning? An Empirical Study on Log-Based Anomaly Detection | B40: Boxi Yu; Jiayi Yao; Qiuai Fu; Zhiqing Zhong; Haotian Xie; Y.C. Wu; Yuchi Ma; Pinjia He | C40: 2024 | D40: conference-paper | E40: Detection (classical ML) | F40: systems/empirical | G40: 57.0 | H40: 10.1145/3597503.3623308 | I40: W4391558391 | J40: 0 | K40: 0 | L40: openalex
A41: A Hybrid Deep Learning-Based Model for Anomaly Detection in Cloud Datacenter Networks | B41: Sahil Garg; Kuljeet Kaur; Neeraj Kumar; Georges Kaddoum; Albert Y. Zomaya; Rajiv Ranjan | C41: 2019 | D41: IEEE Transactions on Network and Service Management | E41: Detection (classical ML) | F41: systems/empirical | G41: 286.0 | H41: 10.1109/tnsm.2019.2927886 | I41: W2959716986 | J41: 0 | K41: 0 | L41: openalex
A42: WAUC: A Multi-Modal Database for Mental Workload Assessment Under Physical Activity | B42: Isabela Albuquerque; Abhishek Tiwari; Mark Parent; Raymundo Cassani; Jean‐François Gagnon; Daniel Lafond; Sébastien Tremblay; Tiago H. Falk | C42: 2020 | D42: Frontiers in Neuroscience | E42: Detection (classical ML) | F42: unscreened(rule-classified) | G42: 71.0 | H42: 10.3389/fnins.2020.549524 | I42: W3110225343 | J42: 0 | K42: 0 | L42: openalex
A43: WaitGPT: Monitoring and Steering Conversational LLM Agent in Data Analysis with On-the-Fly Code Visualization | B43: Liwenhan Xie; Chengbo Zheng; Haijun Xia; Huamin Qu; Zhutian Chen | C43: 2024 | D43: conference-paper | E43: Detection (classical ML) | F43: unscreened(rule-classified) | G43: 45.0 | H43: 10.1145/3654777.3676374 | I43: W4403334501 | J43: 0 | K43: 0 | L43: openalex
A44: Task Failure Prediction in Cloud Data Centers Using Deep Learning | B44: Jiechao Gao; Haoyu Wang; Haiying Shen | C44: 2020 | D44: IEEE Transactions on Services Computing | E44: Detection (classical ML) | F44: unscreened(rule-classified) | G44: 217.0 | H44: 10.1109/tsc.2020.2993728 | I44: W3025035827 | J44: 0 | K44: 0 | L44: openalex
... A63: Deep Learning for Anomaly Detection in Time-Series Data: Review, Analysis, and Guidelines | B63: Kukjin Choi; Jihun Yi; Changhwa Park; Sungroh Yoon | C63: 2021 | D63: IEEE Access | E63: Detection (classical ML) | F63: survey/position | G63: 576.0 | H63: 10.1109/access.2021.3107975 | I63: W3198381997 | J63: 0 | K63: 0 | L63: openalex
A64: Complacency and Bias in Human Use of Automation: An Attentional Integration | B64: Raja Parasuraman; Dietrich Manzey | C64: 2010 | D64: Human Factors The Journal of the Human Factors and Ergonomics Society | E64: Human factors | F64: systems/empirical | G64: 1501.0 | H64: 10.1177/0018720810376055 | J64: 0 | K64: 1 | L64: landmark
A65: Autopilot, Mind Wandering, and the Out of the Loop Performance Problem | B65: Jonas Gouraud; Arnaud Delorme; Bruno Berberian | C65: 2017 | D65: Frontiers in Neuroscience | E65: Human factors | F65: survey/position | G65: 57.0 | H65: 10.3389/fnins.2017.00541 | I65: W2763605495 | J65: 0 | K65: 0 | L65: openalex
A66: A Neuroergonomics Approach to Mental Workload, Engagement and Human Performance | B66: Frédéric Dehais; Alex Lafont; Raphaëlle N. Roy; Stephen Fairclough | C66: 2020 | D66: Frontiers in Neuroscience | E66: Human factors | F66: survey/position | G66: 245.0 | H66: 10.3389/fnins.2020.00268 | I66: W3015212512 | J66: 0 | K66: 0 | L66: openalex
A67: Zero-touch AIOps in multi-operator 5G networks | B67: Katherine Barabash ∗ Gino Carrozzo † Dean Lorenz ∗ Kalman Meth ∗ Shuaib M. Siddiqui | C67: 2022 | D67: Zenodo (CERN European Organization for Nuclear Research) | E67: Human factors | F67: unscreened(rule-classified) | G67: 3.0 | H67: 10.5281/zenodo.7438857 | I67: W4311566849 | J67: 0 | K67: 0 | L67: openalex
A68: A Review of Trustworthy and Explainable Artificial Intelligence (XAI) | B68: Vinay Chamola; Vikas Hassija; A. Razia Sulthana; Debshishu Ghosh; Divyansh Dhingra; Biplab Sikdar | C68: 2023 | D68: IEEE Access | E68: Human factors | F68: unscreened(rule-classified) | G68: 316.0 | H68: 10.1109/ACCESS.2023.3294569 | I68: W4385059984 | J68: 1 | K68: 0 | L68: openalex
A69: Applications, Challenges, and Future Directions of Human-in-the-Loop Learning | B69: Sushant Kumar; Sumit Datta; Vishakha Singh; Deepanwita Datta; Sanjay Kumar Singh; Ritesh Sharma | C69: 2024 | D69: IEEE Access | E69: Human factors | F69: unscreened(rule-classified) | G69: 147.0 | H69: 10.1109/ACCESS.2024.3401547 | I69: W4396941516 | J69: 1 | K69: 0 | L69: openalex
A70: Enhancing Control Room Operator Decision Making | B70: Joseph Mietkiewicz; Ammar N. Abbas; Chidera Winifred Amazu; Gabriele Baldissone; Anders Madsen; Micaela Demichela; Maria Chiara Leva | C70: 2024 | D70: Processes | E70: Human factors | F70: systems/empirical | G70: 18.0 | H70: 10.3390/pr12020328 | I70: W4391530538 | J70: 0 | K70: 0 | L70: openalex
A71: TARGET: Automated Scenario Generation from Traffic Rules for Testing Autonomous Vehicles via Validated LLM-Guided Knowledge Extraction | B71: Yao Deng; Jiaohong Yao; Zhi Tu; Xi Zheng; Mengshi Zhang; Tianyi Zhang | C71: 2023 | D71: IEEE Transactions on Software Engineering, Jul. 2025, pp. 1950-1968, vol. 51 | E71: LLM / agentic ops | F71: unscreened(rule-classified) | H71: 10.1109/tse.2025.3569086 | I71: 2305.06018 | J71: 0 | K71: 0 | L71: arxiv
A72: Xpert: Empowering Incident Management with Query Recommendations via Large Language Models | B72: Yuxuan Jiang; Chaoyun Zhang; Shilin He; Z. Q. Yang; Minghua Ma; Si Qin; Yu Kang; Yingnong Dang; Saravan Rajmohan; Qingwei Lin; Dongmei Zhang | C72: 2024 | D72: conference-paper | E72: LLM / agentic ops | F72: unscreened(rule-classified) | G72: 36.0 | H72: 10.1145/3597503.3639081 | I72: W4394745158 | J72: 0 | K72: 1 | L72: openalex
A73: AutoCodeRover: Autonomous Program Improvement | B73: Yuntong Zhang; Haifeng Ruan; Zhiyu Fan; Abhik Roychoudhury | C73: 2024 | D73: conference-paper | E73: LLM / agentic ops | F73: systems/empirical | G73: 141.0 | H73: 10.1145/3650212.3680384 | I73: W4402442868 | J73: 0 | K73: 0 | L73: openalex
A74: An architecture for model-based and intelligent automation in DevOps | B74: Romina Eramo; Bilal Said; Marc Oriol; Hugo Brunelière; Sergio Morales | C74: 2024 | D74: Journal of Systems and Software | E74: LLM / agentic ops | F74: systems/empirical | G74: 22.0 | H74: 10.1016/j.jss.2024.112180 | I74: W4401270762 | J74: 1 | K74: 0 | L74: openalex
A75: The role of agentic AI in shaping a smart future: A systematic review | B75: Soodeh Hosseini; Hossein Seilani | C75: 2025 | D75: Array | E75: LLM / agentic ops | F75: unscreened(rule-classified) | G75: 216.0 | H75: 10.1016/j.array.2025.100399 | I75: W4410197190 | J75: 1 | K75: 0 | L75: openalex
A76: Agentic AI: Autonomous Intelligence for Complex Goals—A Comprehensive Survey | B76: Deepak Bhaskar Acharya; Karthigeyan Kuppan; B Divya | C76: 2025 | D76: IEEE Access | E76: LLM / agentic ops | F76: unscreened(rule-classified) | G76: 562.0 | H76: 10.1109/ACCESS.2025.3532853 | I76: W4406728221 | J76: 1 | K76: 0 | L76: openalex
A77: Agentic AI: A Comprehensive Survey of Technologies, Applications, and Societal Implications | B77: Ashis Kumar Pati | C77: 2025 | D77: IEEE Access | E77: LLM / agentic ops | F77: unscreened(rule-classified) | G77: 65.0 | H77: 10.1109/ACCESS.2025.3585609 | I77: W4411995908 | J77: 1 | K77: 0 | L77: openalex
A78: VerilogCoder: Autonomous Verilog Coding Agents with Graph-based Planning and Abstract Syntax Tree (AST)-based Waveform Tracing Tool | B78: Chia-Tung Ho; Haoxing Ren; Brucek Khailany | C78: 2025 | D78: Proceedings of the AAAI Conference on Artificial Intelligence | E78: LLM / agentic ops | F78: unscreened(rule-classified) | G78: 45.0 | H78: 10.1609/aaai.v39i1.32007 | I78: W4409369309 | J78: 0 | K78: 0 | L78: openalex
A79: Trustworthy agentic AI systems: a cross-layer review of architectures, threat models, and governance strategies for real-world deployment | B79: IBRAHIM ADABARA; Bashir Olaniyi Sadiq; Aliyu Nuhu Shuaibu; Yale Ibrahim Danjuma; Maninti Venkateswarlu | C79: 2025 | D79: F1000Research | E79: LLM / agentic ops | F79: unscreened(rule-classified) | G79: 21.0 | H79: 10.12688/f1000research.169927.1 | I79: W4414133540 | J79: 1 | K79: 0 | L79: openalex
A80: Triangle: Empowering Incident Triage with Multi-Agent | B80: Zhaoyang Yu; Aoyang Fang; Minghua Ma; Jaskaran Singh Walia; Chaoyun Zhang; Shu Chi; Ze Li; Murali Chintalapati; Xuchao Zhang; Rujia Wang; Chetan Bansal; Saravan Rajmohan; Qingwei Lin; Shenglin Zhang; Dan Pei; Pinjia He | C80: 2025 | D80: conference-paper | E80: LLM / agentic ops | F80: unscreened(rule-classified) | G80: 3.0 | H80: 10.1109/ase63991.2025.00062 | I80: W7125951857 | J80: 0 | K80: 0 | L80: openalex
A81: Transitioning from MLOps to LLMOps: Navigating the Unique Challenges of Large Language Models | B81: Saurabh Pahune; Zahid Akhtar | C81: 2025 | D81: Information | E81: LLM / agentic ops | F81: unscreened(rule-classified) | G81: 52.0 | H81: 10.3390/info16020087 | I81: W4406756422 | J81: 0 | K81: 0 | L81: openalex
A82: Traceability and Accountability in Role-Specialized Multi-Agent LLM Pipelines | B82: Amine Barrak | C82: 2025 | D82: conference-paper | E82: LLM / agentic ops | F82: unscreened(rule-classified) | G82: 7.0 | H82: 10.1109/asew67777.2025.00064 | I82: W7124863487 | J82: 0 | K82: 0 | L82: openalex
A83: TAMO:Fine-Grained Root Cause Analysis via Tool-Assisted LLM Agent With Multi-Modality Observation Data in Cloud-Native Systems | B83: Xiao Zhang; Qi Wang; Mingyi Li; Yuan Yuan; Mengbai Xiao; Fuzhen Zhuang; Dongxiao Yu | C83: 2025 | D83: IEEE Transactions on Services Computing | E83: LLM / agentic ops | F83: unscreened(rule-classified) | G83: 7.0 | H83: 10.1109/TSC.2025.3629066 | I83: W4415933773 | J83: 1 | K83: 0 | L83: openalex
... A90: AI-Enhanced Cloud Reliability Engineering: Integrating Incident Automation And Aiops For National Resilience | B90: Saravanan Raj | C90: 2025 | D90: Journal of International Crisis and Risk Communication Research | E90: LLM / agentic ops | F90: systems/empirical | G90: 10.0 | H90: 10.63278/jicrcr.vi.3522 | I90: W7116766021 | J90: 0 | K90: 0 | L90: openalex
A91: From Automated to Autonomous: Hierarchical Agent-native Network Architecture (HANA) | B91: Binghan Wu; Shoufeng Wang; Yunxin Liu; Ya-Qin Zhang; Joseph Sifakis; Ye Ouyang | C91: 2026 | D91: B. Wu, S. Wang, Y. Liu, Y. -Q. Zhang, J. Sifakis and Y. Ouyang, "From Automated to Autonomous: Hierarchical Agent-native Network Architecture (HANA)," in IEEE Networking Letters, 2026 | E91: LLM / agentic ops | F91: systems/empirical | H91: 10.1109/lnet.2026.3693226 | I91: 2605.20608 | J91: 0 | K91: 0 | L91: arxiv
A92: An LLM-Based Agentic Network Traffic Incident-Report Approach Towards Explainable-AI Network Defense | B92: Chia-Hong Chou; Arjun Sudheer; Younghee Park | C92: 2026 | D92: Journal of Sensor and Actuator Networks | E92: LLM / agentic ops | F92: systems/empirical | G92: 1.0 | H92: 10.3390/jsan15020032 | I92: W7151474267 | J92: 0 | K92: 0 | L92: openalex
A93: A big data-driven root cause analysis system: Application of Machine Learning in quality problem solving | B93: Qiuping Ma; Hongyan Li; Anders Thorstenson | C93: 2021 | D93: Computers & Industrial Engineering | E93: Root-cause analysis | F93: systems/empirical | G93: 87.0 | H93: 10.1016/j.cie.2021.107580 | I93: W3190028216 | J93: 0 | K93: 0 | L93: openalex
A94: TraceDiag: Adaptive, Interpretable, and Efficient Root Cause Analysis on Large-Scale Microservice Systems | B94: Ruomeng Ding; Chaoyun Zhang; Lu Wang; Yong Xu; Minghua Ma; Xiaomin Wu; Meng Zhang; Qingjun Chen; Xin Gao; X. Y. Gao; Hao Fan; Saravan Rajmohan; Qingwei Lin; Dongmei Zhang | C94: 2023 | D94: conference-paper | E94: Root-cause analysis | F94: unscreened(rule-classified) | G94: 21.0 | H94: 10.1145/3611643.3613864 | I94: W4389209173 | J94: 0 | K94: 0 | L94: openalex
A95: Distributed Tracing for Troubleshooting of Native Cloud Applications via Rule-Induction Systems | B95: Arnak Poghosyan; Ashot Harutyunyan; Naira Grigoryan; Clement Chun Cheong Pang | C95: 2023 | D95: JUCS - Journal of Universal Computer Science | E95: Root-cause analysis | F95: systems/empirical | G95: 6.0 | H95: 10.3897/jucs.112513 | I95: W4388838946 | J95: 0 | K95: 0 | L95: openalex
A96: Surveying Root Cause Analysis Techniques: A Comprehensive Review of Aspects for Multi-Service Applications | B96: Zhijing Li; Jianbo Yu; Zhijun Huang; Yusheng Huang | C96: 2025 | D96: IEEE Transactions on Services Computing | E96: Root-cause analysis | F96: unscreened(rule-classified) | G96: 0.0 | H96: 10.1109/TSC.2025.3631913 | I96: W4416178230 | J96: 1 | K96: 0 | L96: openalex
A97: AI-driven anomaly detection and root cause analysis: Using machine learning on logs, metrics, and traces to detect subtle performance anomalies, security threats, or failures in complex cloud environments | B97: Raviteja Guntupalli | C97: 2025 | D97: World Journal of Advanced Research and Reviews | E97: Root-cause analysis | F97: systems/empirical | G97: 4.0 | H97: 10.30574/wjarr.2025.26.2.1521 | I97: W4410280982 | J97: 0 | K97: 0 | L97: openalex
A98: An Entropy-Based Network Anomaly Detection Method | B98: Przemysław Bereziński; Bartosz Jasiul; Marcin Szpyrka | C98: 2015 | D98: Entropy | E98: Security IR / SOC | F98: systems/empirical | G98: 202.0 | H98: 10.3390/e17042367 | I98: W2141910941 | J98: 0 | K98: 0 | L98: openalex
A99: Features Dimensionality Reduction Approaches for Machine Learning Based Network Intrusion Detection | B99: Razan Abdulhammed; Hassan Musafer; Ali Alessa; Miad Faezipour; Abdelshakour Abuzneid | C99: 2019 | D99: Electronics | E99: Security IR / SOC | F99: systems/empirical | G99: 325.0 | H99: 10.3390/electronics8030322 | I99: W2921708219 | J99: 0 | K99: 0 | L99: openalex
A100: Benchmarking of Machine Learning for Anomaly Based Intrusion Detection Systems in the CICIDS2017 Dataset | B100: Ziadoon Kamil Maseer; Robiah Yusof; Nazrulazhar Bahaman; Salama A. Mostafa; Cik Feresa Mohd Foozy | C100: 2021 | D100: IEEE Access | E100: Security IR / SOC | F100: systems/empirical | G100: 456.0 | H100: 10.1109/access.2021.3056614 | I100: W3126814579 | J100: 0 | K100: 0 | L100: openalex
A101: Zero Touch Management: A Survey of Network Automation Solutions for 5G and 6G Networks | B101: Estefanía Coronado; Rasoul Behravesh; Tejas Subramanya; Adriana Fernández–Fernández; Muhammad Shuaib Siddiqui; Xavier Costa‐Pérez; Roberto Riggio | C101: 2022 | D101: IEEE Communications Surveys & Tutorials | E101: Security IR / SOC | F101: unscreened(rule-classified) | G101: 176.0 | H101: 10.1109/comst.2022.3212586 | I101: W4312924812 | J101: 0 | K101: 0 | L101: openalex
A102: The SRE Playbook: Multi-Cloud Observability, Security, and Automation | B102: Vijay Kartik Sikha | C102: 2023 | D102: Journal of Artificial Intelligence & Cloud Computing | E102: Security IR / SOC | F102: unscreened(rule-classified) | G102: 9.0 | H102: 10.47363/jaicc/2023(2)e136 | I102: W4402095265 | J102: 0 | K102: 0 | L102: openalex
A103: Enhancing Cloud Security—Proactive Threat Monitoring and Detection Using a SIEM-Based Approach | B103: Emmanuel Tuyishime; Titus Bălan; Petru Adrian Cotfas; Daniel Tudor Cotfas; Alexandre Rekeraho | C103: 2023 | D103: Applied Sciences | E103: Security IR / SOC | F103: systems/empirical | G103: 32.0 | H103: 10.3390/app132212359 | I103: W4388694085 | J103: 0 | K103: 0 | L103: openalex
... A116: Advancing Cyber Incident Timeline Analysis Through Retrieval-Augmented Generation and Large Language Models | B116: Fatma Yasmine Loumachi; Mohamed Chahine Ghanem; Mohamed Amine Ferrag | C116: 2025 | D116: Computers | E116: Security IR / SOC | F116: systems/empirical | G116: 27.0 | H116: 10.3390/computers14020067 | I116: W4407509125 | J116: 0 | K116: 0 | L116: openalex

Sheet Detail2
A1: Details for Count of title - venue: ACM Computing Surveys (+)
A3: title | B3: authors | C3: year | D3: venue | E3: cluster | F3: paper_type | G3: citations | H3: doi | I3: arxiv_or_openalex_id | J3: in_your_seed_set | K3: is_landmark | L3: src
A4: Enhancing Autonomous System Security and Resilience With Generative AI: A Comprehensive Survey | B4: Martin Andreoni Lopez; Willian T. Lunardi; George Lawton; Shreekant Thakkar | C4: 2024 | D4: IEEE Access | E4: Security IR / SOC | F4: unscreened(rule-classified) | G4: 92.0 | H4: 10.1109/ACCESS.2024.3439363 | I4: W4401357555 | J4: 1 | K4: 0 | L4: openalex
A5: Towards Autonomous Planetary Exploration | B5: Martin J. Schuster; Sebastian G. Brunner; Kristin Bussmann; Stefan Büttner; Andreas Dömel; Matthias Hellerer; Hannah Lehner; Peter Lehner; Oliver Porges; Josef Reill; Sebastian Riedel; Mallikarjuna Vayugundla; Bernhard Vodermayer; Tim Bodenmüller; Christoph Brand; Werner Friedl; Iris Grixa; Heiko Hirschmüller; Michael Kaßecker; Zoltán-Csaba Márton; Christian Nissler; Felix Ruess; Michael Suppa; Ar | C5: 2017 | D5: Journal of Intelligent & Robotic Systems | E5: Detection (classical ML) | F5: unscreened(rule-classified) | G5: 91.0 | H5: 10.1007/s10846-017-0680-9 | I5: W2767694002 | J5: 0 | K5: 0 | L5: openalex
A6: Co-Evolving Multi-Agent Transfer Reinforcement Learning via Scenario Independent Representation | B6: Ayesha Siddiqua; Siming Liu; Ayesha Siddika Nipu; Anthony M. Harris; Yan Liu | C6: 2024 | D6: IEEE Access | E6: Agent foundations | F6: unscreened(rule-classified) | G6: 9.0 | H6: 10.1109/ACCESS.2024.3430037 | I6: W4400726849 | J6: 1 | K6: 0 | L6: openalex
A7: The SRE Playbook: Multi-Cloud Observability, Security, and Automation | B7: Vijay Kartik Sikha | C7: 2023 | D7: Journal of Artificial Intelligence & Cloud Computing | E7: Security IR / SOC | F7: unscreened(rule-classified) | G7: 9.0 | H7: 10.47363/jaicc/2023(2)e136 | I7: W4402095265 | J7: 0 | K7: 0 | L7: openalex
A8: A big data-driven root cause analysis system: Application of Machine Learning in quality problem solving | B8: Qiuping Ma; Hongyan Li; Anders Thorstenson | C8: 2021 | D8: Computers & Industrial Engineering | E8: Root-cause analysis | F8: systems/empirical | G8: 87.0 | H8: 10.1016/j.cie.2021.107580 | I8: W3190028216 | J8: 0 | K8: 0 | L8: openalex
A9: A Data-Mining Approach for Wind Turbine Fault Detection Based on SCADA Data Analysis Using Artificial Neural Networks | B9: Annalisa Santolamazza; Daniele Dadi; Vito Introna | C9: 2021 | D9: Energies | E9: Detection (classical ML) | F9: systems/empirical | G9: 80.0 | H9: 10.3390/en14071845 | I9: W3146685335 | J9: 0 | K9: 0 | L9: openalex
A10: Cloud Network Anomaly Detection Using Machine and Deep Learning Techniques— Recent Research Advancements | B10: Amira Mahamat Abdallah; Aysha Saif Rashed Obaid Alkaabi; Ghaya Bark Nasser Douman Alameri; Saida Hafsa Rafique; Nura Shifa Musa; M. Thangavel | C10: 2024 | D10: IEEE Access | E10: Detection (classical ML) | F10: survey/position | G10: 78.0 | H10: 10.1109/access.2024.3390844 | I10: W4394939094 | J10: 0 | K10: 0 | L10: openalex
A11: Application of Large Language Models in Cybersecurity: A Systematic Literature Review | B11: Ismayil Hasanov; Seppo Virtanen; Antti Hakkala; Jouni Isoaho | C11: 2024 | D11: IEEE Access | E11: Security IR / SOC | F11: survey/position | G11: 76.0 | H11: 10.1109/access.2024.3505983 | I11: W4404688214 | J11: 0 | K11: 0 | L11: openalex
A12: WAUC: A Multi-Modal Database for Mental Workload Assessment Under Physical Activity | B12: Isabela Albuquerque; Abhishek Tiwari; Mark Parent; Raymundo Cassani; Jean‐François Gagnon; Daniel Lafond; Sébastien Tremblay; Tiago H. Falk | C12: 2020 | D12: Frontiers in Neuroscience | E12: Detection (classical ML) | F12: unscreened(rule-classified) | G12: 71.0 | H12: 10.3389/fnins.2020.549524 | I12: W3110225343 | J12: 0 | K12: 0 | L12: openalex
A13: From LLM Reasoning to Autonomous AI Agents: A Comprehensive Review | B13: Mohamed Amine Ferrag; Norbert Tihanyi; Mérouane Debbah | C13: 2026 | D13: IEEE Access | E13: Agent foundations | F13: survey/position | G13: 7.0 | H13: 10.1109/access.2026.3698694 | I13: W4416982487 | J13: 0 | K13: 0 | L13: openalex
A14: Availability analysis of redundant and replicated cloud services with Bayesian networks | B14: Otto Bibartiu; Frank Dürr; Kurt Rothermel; Beate Ottenwälder; Andreas Grau | C14: 2023 | D14: Quality and Reliability Engineering International | E14: Benchmarks & evaluation | F14: systems/empirical | G14: 7.0 | H14: 10.1002/qre.3414 | I14: W4385241681 | J14: 0 | K14: 0 | L14: openalex
A15: TAMO:Fine-Grained Root Cause Analysis via Tool-Assisted LLM Agent With Multi-Modality Observation Data in Cloud-Native Systems | B15: Xiao Zhang; Qi Wang; Mingyi Li; Yuan Yuan; Mengbai Xiao; Fuzhen Zhuang; Dongxiao Yu | C15: 2025 | D15: IEEE Transactions on Services Computing | E15: LLM / agentic ops | F15: unscreened(rule-classified) | G15: 7.0 | H15: 10.1109/TSC.2025.3629066 | I15: W4415933773 | J15: 1 | K15: 0 | L15: openalex
... A80: Artificial Intelligence Agent-Enabled Predictive Maintenance: Conceptual Proposal and Basic Framework | B80: Wenyu Jiang; Fuwen Hu | C80: 2025 | D80: Computers | E80: LLM / agentic ops | F80: systems/empirical | G80: 16.0 | H80: 10.3390/computers14080329 | I80: W4413380618 | J80: 0 | K80: 0 | L80: openalex
A81: Complacency and Bias in Human Use of Automation: An Attentional Integration | B81: Raja Parasuraman; Dietrich Manzey | C81: 2010 | D81: Human Factors The Journal of the Human Factors and Ergonomics Society | E81: Human factors | F81: systems/empirical | G81: 1501.0 | H81: 10.1177/0018720810376055 | J81: 0 | K81: 1 | L81: landmark
A82: A Multi-Agent System for Cybersecurity Threat Detection and Correlation Using Large Language Models | B82: Yasser Hmimou; Mohamed Tabaa; Azeddine Khiat; Zineb Hidila | C82: 2025 | D82: IEEE Access | E82: Security IR / SOC | F82: systems/empirical | G82: 15.0 | H82: 10.1109/ACCESS.2025.3602681 | I82: W4413556821 | J82: 1 | K82: 0 | L82: openalex
A83: Applications, Challenges, and Future Directions of Human-in-the-Loop Learning | B83: Sushant Kumar; Sumit Datta; Vishakha Singh; Deepanwita Datta; Sanjay Kumar Singh; Ritesh Sharma | C83: 2024 | D83: IEEE Access | E83: Human factors | F83: unscreened(rule-classified) | G83: 147.0 | H83: 10.1109/ACCESS.2024.3401547 | I83: W4396941516 | J83: 1 | K83: 0 | L83: openalex
A84: EADN: An Efficient Deep Learning Model for Anomaly Detection in Videos | B84: Sareer Ul Amin; Mohib Ullah; Muhammad Sajjad; Faouzi Alaya Cheikh; Mohammad Hijji; Abdulrahman Hijji; Khan Muhammad | C84: 2022 | D84: Mathematics | E84: Detection (classical ML) | F84: systems/empirical | G84: 142.0 | H84: 10.3390/math10091555 | I84: W4229008034 | J84: 0 | K84: 0 | L84: openalex
A85: A Review of Agentic AI in Cybersecurity: Cognitive Autonomy, Ethical Governance, and Quantum-Resilient Defense | B85: IBRAHIM ADABARA; Bashir Olaniyi Sadiq; Aliyu Nuhu Shuaibu; Yale Ibrahim Danjuma; Maninti Venkateswarlu | C85: 2025 | D85: F1000Research | E85: Security IR / SOC | F85: survey/position | G85: 13.0 | H85: 10.12688/f1000research.169337.1 | I85: W4413880655 | J85: 1 | K85: 0 | L85: openalex
A86: The Rise of Agentic AI: A Review of Definitions, Frameworks, Architectures, Applications, Evaluation Metrics, and Challenges | B86: Ajay Bandi; Bhavani Kongari; Roshini Naguru; Sahitya Pasnoor; Sri Vidya Vilipala | C86: 2025 | D86: Future Internet | E86: Security IR / SOC | F86: unscreened(rule-classified) | G86: 126.0 | H86: 10.3390/fi17090404 | I86: W4414023998 | J86: 1 | K86: 0 | L86: openalex
A87: Towards Synoptic Water Monitoring Systems: A Review of AI Methods for Automating Water Body Detection and Water Quality Monitoring Using Remote Sensing | B87: Liping Yang; Joshua Driscol; Sarigai Sarigai; Qiusheng Wu; Christopher D. Lippitt; Melinda Morgan | C87: 2022 | D87: Sensors | E87: Detection (classical ML) | F87: unscreened(rule-classified) | G87: 124.0 | H87: 10.3390/s22062416 | I87: W4221087595 | J87: 0 | K87: 0 | L87: openalex
A88: Distributed system anomaly detection using deep learning‐based log analysis | B88: Pengfei Han; Huakang Li; Gang Xue; Chao Zhang | C88: 2023 | D88: Computational Intelligence | E88: Detection (classical ML) | F88: systems/empirical | G88: 12.0 | H88: 10.1111/coin.12573 | I88: W4366768971 | J88: 0 | K88: 0 | L88: openalex
A89: Anomaly Detection and Root Cause Analysis in Cloud-Native Environments Using Large Language Models and Bayesian Networks | B89: Diego Frazatto Pedroso; Luís Almeida; Lucas Eduardo Gulka Pulcinelli; William Akihiro Alves Aisawa; Inês Dutra; Sarita Mazzini Bruschi | C89: 2025 | D89: IEEE Access | E89: LLM / agentic ops | F89: systems/empirical | G89: 12.0 | H89: 10.1109/access.2025.3565220 | I89: W4409916700 | J89: 0 | K89: 0 | L89: openalex
A90: A Survey on Observability of Distributed Edge & Container-Based Microservices | B90: Muhammad Usman; Simone Ferlin; Anna Brunström; Javid Taheri | C90: 2022 | D90: IEEE Access | E90: Detection (classical ML) | F90: survey/position | G90: 115.0 | H90: 10.1109/access.2022.3193102 | I90: W4286544722 | J90: 0 | K90: 0 | L90: openalex
A91: AIOps for log anomaly detection in the era of LLMs: A systematic literature review | B91: Miguel De la Cruz Cabello; Tiago Prince Sales; Marcos Machado | C91: 2025 | D91: Intelligent Systems with Applications | E91: LLM / agentic ops | F91: survey/position | G91: 11.0 | H91: 10.1016/j.iswa.2025.200608 | I91: W4416426157 | J91: 1 | K91: 0 | L91: openalex
A92: Enhancing Security Operations Center: Wazuh Security Event Response with Retrieval-Augmented-Generation-Driven Copilot | B92: Ismail Ismail; Rahmat Kurnia; Farid Widyatama; Ilham Mirwansyah Wibawa; Zilmas Arjuna Brata; Ukasyah; Ghitha Afina Nelistiani; Howon Kim | C92: 2025 | D92: Sensors | E92: Security IR / SOC | F92: systems/empirical | G92: 11.0 | H92: 10.3390/s25030870 | I92: W4407006955 | J92: 0 | K92: 0 | L92: openalex
A93: Edge-IIoTset: A New Comprehensive Realistic Cyber Security Dataset of IoT and IIoT Applications for Centralized and Federated Learning | B93: Mohamed Amine Ferrag; Othmane Friha; Djallel Hamouda; Λέανδρος Μαγλαράς; Helge Janicke | C93: 2022 | D93: IEEE Access | E93: Detection (classical ML) | F93: systems/empirical | G93: 1060.0 | H93: 10.1109/access.2022.3165809 | I93: W4226319939 | J93: 0 | K93: 0 | L93: openalex
... A99: Surveying Root Cause Analysis Techniques: A Comprehensive Review of Aspects for Multi-Service Applications | B99: Zhijing Li; Jianbo Yu; Zhijun Huang; Yusheng Huang | C99: 2025 | D99: IEEE Transactions on Services Computing | E99: Root-cause analysis | F99: unscreened(rule-classified) | G99: 0.0 | H99: 10.1109/TSC.2025.3631913 | I99: W4416178230 | J99: 1 | K99: 0 | L99: openalex
A100: VAGNet: Vision-based Accident Anticipation with Global Features | B100: Vipooshan Vipulananthan; Charith D. Chitraranjan | C100: 2026 | D100: IEEE Open Journal of Vehicular Technology, vol. 7, pp. 1873-1883, 2026 | E100: Alert triage & correlation | F100: unscreened(rule-classified) | H100: 10.1109/ojvt.2026.3704953 | I100: 2604.09305 | J100: 0 | K100: 0 | L100: arxiv
A101: TELESTO: A Graph Neural Network Model for Anomaly Classification in Cloud Services | B101: Dominik Scheinert; Alexander Acker | C101: 2021 | D101: Springer ICSOC LNCS 12632 (2020) 214-227 | E101: Automated remediation | F101: unscreened(rule-classified) | H101: 10.1007/978-3-030-76352-7_23 | I101: 2102.12877 | J101: 0 | K101: 0 | L101: arxiv
A102: A Decentralised Self-Healing Approach for Network Topology Maintenance | B102: Arles Rodríguez; Jonatan Gómez; Ada Diaconescu | C102: 2020 | D102: Autonomous Agents and Multi-Agent Systems, 35(1), 6 (2020) | E102: Automated remediation | F102: systems/empirical | H102: 10.1007/s10458-020-09486-3 | I102: 2010.11146 | J102: 0 | K102: 0 | L102: arxiv
A103: A unified framework for detecting point and collective anomalies in operating system logs via collaborative transformers | B103: Mohammad Nasirzadeh; Jafar Tahmoresnezhad; Parviz Rashidi-Khazaee | C103: 2025 | D103: Scientific Reports 15, 45698 (2025) | E103: Detection (classical ML) | F103: systems/empirical | H103: 10.1038/s41598-025-27693-4 | I103: 2512.23380 | J103: 0 | K103: 0 | L103: arxiv
A104: TARGET: Automated Scenario Generation from Traffic Rules for Testing Autonomous Vehicles via Validated LLM-Guided Knowledge Extraction | B104: Yao Deng; Jiaohong Yao; Zhi Tu; Xi Zheng; Mengshi Zhang; Tianyi Zhang | C104: 2023 | D104: IEEE Transactions on Software Engineering, Jul. 2025, pp. 1950-1968, vol. 51 | E104: LLM / agentic ops | F104: unscreened(rule-classified) | H104: 10.1109/tse.2025.3569086 | I104: 2305.06018 | J104: 0 | K104: 0 | L104: arxiv

Sheet Sheet2
A1: title | B1: authors | C1: year | D1: venue | E1: cluster | F1: paper_type | G1: citations | H1: doi | I1: Scopus (Percentil) | J1: SJR Quartile | K1: ISSN / e-ISSN | N1: ID | O1: Título | P1: Venue | Q1: DOI | R1: Qualis (2025-2028) | S1: Scopus (Percentil) | T1: SJR Quartile | U1: ISSN / e-ISSN | V1: Year | W1: Citações OpenAlex | X1: Citações Crossref | Y1: Citações Scopus | Z1: Citações (verificado em) | AA1: Classificados
A2: Edge-IIoTset: A New Comprehensive Realistic Cyber Security Dataset of IoT and IIoT Applications for Centralized and Federated Learning | B2: Mohamed Amine Ferrag; Othmane Friha; Djallel Hamouda; Λέανδρος Μαγλαράς; Helge Janicke | C2: 2022 | D2: IEEE Access | E2: Detection (classical ML) | F2: systems/empirical | G2: 1060 | H2: 10.1109/access.2022.3165809 | I2: =VLOOKUP($D2,P:U,4,FALSE) -> 0.9 | J2: =VLOOKUP($D2,P:U,5,FALSE) -> Q1 | K2: =VLOOKUP($D2,P:U,6,FALSE) -> 2169-3536 | N2: P01 | O2: Trustworthy agentic AI systems: a cross-layer review of architectures, threat models and governance strategies | P2: F1000Research | Q2: 10.12688/f1000research.169927.1 | R2: A2 | S2: 0.77 | T2: Q1 | U2: 2046-1402 | V2: 2025 | W2: 19 | X2: 21 | Y2: NÃO INDEXADO | Z2: 46230 | AA2: =VLOOKUP(Q2,$H$1:$I$94,2,FALSE) -> 0.77
A3: Deep Learning for Anomaly Detection in Time-Series Data: Review, Analysis, and Guidelines | B3: Kukjin Choi; Jihun Yi; Changhwa Park; Sungroh Yoon | C3: 2021 | D3: IEEE Access | E3: Detection (classical ML) | F3: survey/position | G3: 576 | H3: 10.1109/access.2021.3107975 | I3: =VLOOKUP($D3,P:U,4,FALSE) -> 0.9 | J3: =VLOOKUP($D3,P:U,5,FALSE) -> Q1 | K3: =VLOOKUP($D3,P:U,6,FALSE) -> 2169-3536 | N3: P02 | O3: The role of agentic AI in shaping a smart future: A systematic review | P3: Array | Q3: 10.1016/j.array.2025.100399 | R3: A1 | S3: 0.88 | T3: Q1 | U3: 2590-0056 | V3: 2025 | W3: 180 | X3: 190 | Y3: 175 | Z3: 46230 | AA3: =VLOOKUP(Q3,$H$1:$I$94,2,FALSE) -> 0.88
A4: Agentic AI: Autonomous Intelligence for Complex Goals—A Comprehensive Survey | B4: Deepak Bhaskar Acharya; Karthigeyan Kuppan; B Divya | C4: 2025 | D4: IEEE Access | E4: LLM / agentic ops | F4: unscreened(rule-classified) | G4: 562 | H4: 10.1109/ACCESS.2025.3532853 | I4: =VLOOKUP($D4,P:U,4,FALSE) -> 0.9 | J4: =VLOOKUP($D4,P:U,5,FALSE) -> Q1 | K4: =VLOOKUP($D4,P:U,6,FALSE) -> 2169-3536 | N4: P03 | O4: A Research Landscape of Agentic AI and Large Language Models | P4: Algorithms | Q4: 10.3390/a18080499 | R4: A2 | S4: 0.78 | T4: Q2 | U4: 1999-4893 | V4: 2025 | W4: 38 | X4: 45 | Y4: 39 | Z4: 46230 | AA4: =VLOOKUP(Q4,$H$1:$I$94,2,FALSE) -> 0.78
A5: Deep Learning for Time Series Anomaly Detection: A Survey | B5: Zahra Zamanzadeh Darban; Geoffrey I. Webb; Shirui Pan; Charų C. Aggarwal; Mahsa Salehi | C5: 2024 | D5: ACM Computing Surveys | E5: Detection (classical ML) | F5: survey/position | G5: 506 | H5: 10.1145/3691338 | I5: =VLOOKUP($D5,P:U,4,FALSE) -> 0.99 | J5: =VLOOKUP($D5,P:U,5,FALSE) -> Q1 | K5: =VLOOKUP($D5,P:U,6,FALSE) -> 0360-0300 | N5: P04 | O5: LLM-Based Multi-Agent Systems for Software Engineering | P5: ACM TRANSACTIONS ON SOFTWARE ENGINEERING AND METHODOLOGY | Q5: 10.1145/3712003 | R5: A2 | S5: 0.82 | T5: Q1 | U5: 1049-331X | V5: 2024 | W5: 144 | X5: 173 | Y5: 134 | Z5: 46230 | AA5: =VLOOKUP(Q5,$H$1:$I$94,2,FALSE) -> 0.82
A6: Benchmarking of Machine Learning for Anomaly Based Intrusion Detection Systems in the CICIDS2017 Dataset | B6: Ziadoon Kamil Maseer; Robiah Yusof; Nazrulazhar Bahaman; Salama A. Mostafa; Cik Feresa Mohd Foozy | C6: 2021 | D6: IEEE Access | E6: Security IR / SOC | F6: systems/empirical | G6: 456 | H6: 10.1109/access.2021.3056614 | I6: =VLOOKUP($D6,P:U,4,FALSE) -> 0.9 | J6: =VLOOKUP($D6,P:U,5,FALSE) -> Q1 | K6: =VLOOKUP($D6,P:U,6,FALSE) -> 2169-3536 | N6: P05 | O6: A Survey of AIOps in the Era of Large Language Models | P6: ACM Computing Surveys | Q6: 10.1145/3746635 | R6: A1 | S6: 0.99 | T6: Q1 | U6: 0360-0300 | V6: 2025 | W6: 19 | X6: 28 | Y6: 24 | Z6: 46230 | AA6: =VLOOKUP(Q6,$H$1:$I$94,2,FALSE) -> #N/A
A7: Variational LSTM Enhanced Anomaly Detection for Industrial Big Data | B7: Xiaokang Zhou; Yiyong Hu; Wei Liang; Jianhua Ma; Qun Jin | C7: 2020 | D7: IEEE Transactions on Industrial Informatics | E7: Automated remediation | F7: unscreened(rule-classified) | G7: 401 | H7: 10.1109/tii.2020.3022432 | I7: =VLOOKUP($D7,P:U,4,FALSE) -> #N/A | J7: =VLOOKUP($D7,P:U,5,FALSE) -> #N/A | K7: =VLOOKUP($D7,P:U,6,FALSE) -> #N/A | N7: P06 | O7: Agentic AI: A Comprehensive Survey of Technologies, Applications, and Societal Implications | P7: IEEE Access | Q7: 10.1109/ACCESS.2025.3585609 | R7: A1 | S7: 0.9 | T7: Q1 | U7: 2169-3536 | V7: 2025 | W7: 48 | X7: 57 | Y7: 44 | Z7: 46230 | AA7: =VLOOKUP(Q7,$H$1:$I$94,2,FALSE) -> 0.9
A8: Artificial Intelligence for Predictive Maintenance Applications: Key Components, Trustworthiness, and Future Trends | B8: Ayşegül Uçar; Mehmet Karaköse; Necim Kırımça | C8: 2024 | D8: Applied Sciences | E8: Detection (classical ML) | F8: survey/position | G8: 396 | H8: 10.3390/app14020898 | I8: =VLOOKUP($D8,P:U,4,FALSE) -> #N/A | J8: =VLOOKUP($D8,P:U,5,FALSE) -> #N/A | K8: =VLOOKUP($D8,P:U,6,FALSE) -> #N/A | N8: P07 | O8: Artificial Empathy: A New Perspective for Analyzing and Designing Multi-Agent Systems | P8: IEEE Access | Q8: 10.1109/ACCESS.2020.3029502 | R8: A1 | S8: 0.9 | T8: Q1 | U8: 2169-3536 | V8: 2020 | W8: 10 | X8: 9 | Y8: 8 | Z8: 46230 | AA8: =VLOOKUP(Q8,$H$1:$I$94,2,FALSE) -> 0.9
A9: Deep Industrial Image Anomaly Detection: A Survey | B9: Jiaqi Liu; Guoyang Xie; Jinbao Wang; Shangnian Li; Chengjie Wang; Feng Zheng; Yaochu Jin | C9: 2024 | D9: Machine Intelligence Research | E9: Detection (classical ML) | F9: survey/position | G9: 389 | H9: 10.1007/s11633-023-1459-z | I9: =VLOOKUP($D9,P:U,4,FALSE) -> #N/A | J9: =VLOOKUP($D9,P:U,5,FALSE) -> #N/A | K9: =VLOOKUP($D9,P:U,6,FALSE) -> #N/A | N9: P08 | O9: Applications, Challenges, and Future Directions of Human-in-the-Loop Learning | P9: IEEE Access | Q9: 10.1109/ACCESS.2024.3401547 | R9: A1 | S9: 0.9 | T9: Q1 | U9: 2169-3536 | V9: 2024 | W9: 135 | X9: 134 | Y9: 141 | Z9: 46230 | AA9: =VLOOKUP(Q9,$H$1:$I$94,2,FALSE) -> 0.9
A10: Anomaly-Based Intrusion Detection From Network Flow Features Using Variational Autoencoder | B10: Sultan Zavrak; Murat İskefiyeli | C10: 2020 | D10: IEEE Access | E10: Detection (classical ML) | F10: systems/empirical | G10: 321 | H10: 10.1109/access.2020.3001350 | I10: =VLOOKUP($D10,P:U,4,FALSE) -> 0.9 | J10: =VLOOKUP($D10,P:U,5,FALSE) -> Q1 | K10: =VLOOKUP($D10,P:U,6,FALSE) -> 2169-3536 | N10: P09 | O10: AI Agents vs. Agentic AI: A Conceptual taxonomy, applications and challenges | P10: Information Fusion | Q10: 10.1016/j.inffus.2025.103599 | R10: A1 | S10: 0.99 | T10: Q1 | U10: 1566-2535 | V10: 2025 | W10: 132 | X10: 149 | Y10: 136 | Z10: 46230 | AA10: =VLOOKUP(Q10,$H$1:$I$94,2,FALSE) -> 0.99
A11: A Review of Trustworthy and Explainable Artificial Intelligence (XAI) | B11: Vinay Chamola; Vikas Hassija; A. Razia Sulthana; Debshishu Ghosh; Divyansh Dhingra; Biplab Sikdar | C11: 2023 | D11: IEEE Access | E11: Human factors | F11: unscreened(rule-classified) | G11: 316 | H11: 10.1109/ACCESS.2023.3294569 | I11: =VLOOKUP($D11,P:U,4,FALSE) -> 0.9 | J11: =VLOOKUP($D11,P:U,5,FALSE) -> Q1 | K11: =VLOOKUP($D11,P:U,6,FALSE) -> 2169-3536 | N11: P10 | O11: Agentic AI: Autonomous Intelligence for Complex Goals — A Comprehensive Survey | P11: IEEE Access | Q11: 10.1109/ACCESS.2025.3532853 | R11: A1 | S11: 0.9 | T11: Q1 | U11: 2169-3536 | V11: 2025 | W11: 487 | X11: 534 | Y11: 509 | Z11: 46230 | AA11: =VLOOKUP(Q11,$H$1:$I$94,2,FALSE) -> 0.9
A12: Anomaly detection with density estimation | B12: Benjamin Nachman; David Shih | C12: 2020 | D12: Physical review. D/Physical review. D. | E12: Detection (classical ML) | F12: systems/empirical | G12: 315 | H12: 10.1103/physrevd.101.075042 | I12: =VLOOKUP($D12,P:U,4,FALSE) -> #N/A | J12: =VLOOKUP($D12,P:U,5,FALSE) -> #N/A | K12: =VLOOKUP($D12,P:U,6,FALSE) -> #N/A | N12: P11 | O12: Co-Evolving Multi-Agent Transfer Reinforcement Learning via Scenario Independent Representation | P12: IEEE Access | Q12: 10.1109/ACCESS.2024.3430037 | R12: A1 | S12: 0.9 | T12: Q1 | U12: 2169-3536 | V12: 2024 | W12: 9 | X12: 9 | Y12: 10 | Z12: 46230 | AA12: =VLOOKUP(Q12,$H$1:$I$94,2,FALSE) -> 0.9
A13: An Unsupervised Deep Learning Model for Early Network Traffic Anomaly Detection | B13: Ren‐Hung Hwang; Min-Chun Peng; Chien‐Wei Huang; Po‐Ching Lin; Van-Linh Nguyen | C13: 2020 | D13: IEEE Access | E13: Detection (classical ML) | F13: systems/empirical | G13: 278 | H13: 10.1109/access.2020.2973023 | I13: =VLOOKUP($D13,P:U,4,FALSE) -> 0.9 | J13: =VLOOKUP($D13,P:U,5,FALSE) -> Q1 | K13: =VLOOKUP($D13,P:U,6,FALSE) -> 2169-3536 | N13: P12 | O13: Enhancing autonomous system security and resilience with generative AI | P13: IEEE Access | Q13: 10.1109/ACCESS.2024.3439363 | R13: A1 | S13: 0.9 | T13: Q1 | U13: 2169-3536 | V13: 2024 | W13: 86 | X13: 93 | Y13: 101 | Z13: 46230 | AA13: =VLOOKUP(Q13,$H$1:$I$94,2,FALSE) -> 0.9
A14: From Corrective to Predictive Maintenance—A Review of Maintenance Approaches for the Power Industry | B14: Marek Molęda; Bożena Małysiak-Mrozek; Weiping Ding; Vaidy Sunderam; Dariusz Mrozek | C14: 2023 | D14: Sensors | E14: Detection (classical ML) | F14: survey/position | G14: 264 | H14: 10.3390/s23135970 | I14: =VLOOKUP($D14,P:U,4,FALSE) -> #N/A | J14: =VLOOKUP($D14,P:U,5,FALSE) -> #N/A | K14: =VLOOKUP($D14,P:U,6,FALSE) -> #N/A | N14: P13 | O14: Retail Resilience Engine: An Agentic AI Framework for Building Reliable Retail Systems | P14: IEEE Access | Q14: 10.1109/ACCESS.2025.3552592 | R14: A1 | S14: 0.9 | T14: Q1 | U14: 2169-3536 | V14: 2025 | W14: 29 | X14: 33 | Y14: 31 | Z14: 46230 | AA14: =VLOOKUP(Q14,$H$1:$I$94,2,FALSE) -> 0.9
... A40: AgentAI: A comprehensive survey on autonomous agents in distributed AI for industry 4.0 | B40: Francesco Piccialli; Diletta Chiaro; Sundas Sarwar; Donato Cerciello; Pian Qi; Valeria Mele | C40: 2025 | D40: Expert Systems with Applications | E40: Agent foundations | F40: unscreened(rule-classified) | G40: 59 | H40: 10.1016/j.eswa.2025.128404 | I40: =VLOOKUP($D40,P:U,4,FALSE) -> 0.97 | J40: =VLOOKUP($D40,P:U,5,FALSE) -> Q1 | K40: =VLOOKUP($D40,P:U,6,FALSE) -> 0957-4174 | N40: P40 | O40: A Comprehensive Survey on LLM-Based Network Management and Operations | P40: International Journal of Network Management | Q40: 10.1002/nem.70029 | R40: A3 | S40: 0.68 | T40: Q2 | U40: 1055-7148 | V40: 2025 | W40: 11 | X40: 13 | Y40: 7 | Z40: 46230 | AA40: =VLOOKUP(Q40,$H$1:$I$94,2,FALSE) -> #N/A
A41: From Vulnerability to Defense: The Role of Large Language Models in Enhancing Cybersecurity | B41: Wafaa Kasri; Yassine Himeur; Hamzah Ali Alkhazaleh; Saed Tarapiah; Shadi Atalla; Wathiq Mansoor; Hussain Al-Ahmad | C41: 2025 | D41: Computation | E41: Security IR / SOC | F41: survey/position | G41: 57 | H41: 10.3390/computation13020030 | I41: =VLOOKUP($D41,P:U,4,FALSE) -> #N/A | J41: =VLOOKUP($D41,P:U,5,FALSE) -> #N/A | K41: =VLOOKUP($D41,P:U,6,FALSE) -> #N/A
A42: Wind Turbine Fault Detection Using Highly Imbalanced Real SCADA Data | B42: Cristian Velandia; Yolanda Vidal; Francesc Pozo | C42: 2021 | D42: Energies | E42: Alert triage & correlation | F42: unscreened(rule-classified) | G42: 53 | H42: 10.3390/en14061728 | I42: =VLOOKUP($D42,P:U,4,FALSE) -> #N/A | J42: =VLOOKUP($D42,P:U,5,FALSE) -> #N/A | K42: =VLOOKUP($D42,P:U,6,FALSE) -> #N/A
A43: Breaking Alert Fatigue: AI-Assisted SIEM Framework for Effective Incident Response | B43: Tao Ban; Takeshi Takahashi; Samuel Ndichu; Daisuke Inoue | C43: 2023 | D43: Applied Sciences | E43: Alert triage & correlation | F43: systems/empirical | G43: 52 | H43: 10.3390/app13116610 | I43: =VLOOKUP($D43,P:U,4,FALSE) -> #N/A | J43: =VLOOKUP($D43,P:U,5,FALSE) -> #N/A | K43: =VLOOKUP($D43,P:U,6,FALSE) -> #N/A
A44: Transitioning from MLOps to LLMOps: Navigating the Unique Challenges of Large Language Models | B44: Saurabh Pahune; Zahid Akhtar | C44: 2025 | D44: Information | E44: LLM / agentic ops | F44: unscreened(rule-classified) | G44: 52 | H44: 10.3390/info16020087 | I44: =VLOOKUP($D44,P:U,4,FALSE) -> #N/A | J44: =VLOOKUP($D44,P:U,5,FALSE) -> #N/A | K44: =VLOOKUP($D44,P:U,6,FALSE) -> #N/A
A45: Transforming cybersecurity with agentic AI to combat emerging cyber threats | B45: Nir Kshetri | C45: 2025 | D45: Telecommunications Policy | E45: Security IR / SOC | F45: unscreened(rule-classified) | G45: 51 | H45: 10.1016/j.telpol.2025.102976 | I45: =VLOOKUP($D45,P:U,4,FALSE) -> 0.97 | J45: =VLOOKUP($D45,P:U,5,FALSE) -> Q1 | K45: =VLOOKUP($D45,P:U,6,FALSE) -> 0308-5961
A46: The Impact of Explanations on Layperson Trust in Artificial Intelligence–Driven Symptom Checker Apps: Experimental Study | B46: Claire Woodcock; Brent Mittelstadt; Dan Busbridge; Grant Blank | C46: 2021 | D46: Journal of Medical Internet Research | E46: Benchmarks & evaluation | F46: unscreened(rule-classified) | G46: 50 | H46: 10.2196/29386 | I46: =VLOOKUP($D46,P:U,4,FALSE) -> #N/A | J46: =VLOOKUP($D46,P:U,5,FALSE) -> #N/A | K46: =VLOOKUP($D46,P:U,6,FALSE) -> #N/A
A47: VerilogCoder: Autonomous Verilog Coding Agents with Graph-based Planning and Abstract Syntax Tree (AST)-based Waveform Tracing Tool | B47: Chia-Tung Ho; Haoxing Ren; Brucek Khailany | C47: 2025 | D47: Proceedings of the AAAI Conference on Artificial Intelligence | E47: LLM / agentic ops | F47: unscreened(rule-classified) | G47: 45 | H47: 10.1609/aaai.v39i1.32007 | I47: =VLOOKUP($D47,P:U,4,FALSE) -> #N/A | J47: =VLOOKUP($D47,P:U,5,FALSE) -> #N/A | K47: =VLOOKUP($D47,P:U,6,FALSE) -> #N/A
A48: A Research Landscape of Agentic AI and Large Language Models: Applications, Challenges and Future Directions | B48: Sarfraz Nawaz Brohi; Qurat-ul-ain Mastoi; N. Z. Jhanjhi; Thulasyammal Ramiah Pillai | C48: 2025 | D48: Algorithms | E48: Security IR / SOC | F48: unscreened(rule-classified) | G48: 44 | H48: 10.3390/a18080499 | I48: =VLOOKUP($D48,P:U,4,FALSE) -> 0.78 | J48: =VLOOKUP($D48,P:U,5,FALSE) -> Q2 | K48: =VLOOKUP($D48,P:U,6,FALSE) -> 1999-4893
A49: Retail Resilience Engine: An Agentic AI Framework for Building Reliable Retail Systems With Test-Driven Development Approach | B49: Lalit Narayan Mishra; Biswaranjan Senapati | C49: 2025 | D49: IEEE Access | E49: Benchmarks & evaluation | F49: unscreened(rule-classified) | G49: 34 | H49: 10.1109/ACCESS.2025.3552592 | I49: =VLOOKUP($D49,P:U,4,FALSE) -> 0.9 | J49: =VLOOKUP($D49,P:U,5,FALSE) -> Q1 | K49: =VLOOKUP($D49,P:U,6,FALSE) -> 2169-3536
A50: Using fNIRS to Verify Trust in Highly Automated Driving | B50: Jaume Perelló-March; Christopher Burns; Roger Woodman; Mark T. Elliott; Stewart Birrell | C50: 2022 | D50: IEEE Transactions on Intelligent Transportation Systems | E50: Automated remediation | F50: unscreened(rule-classified) | G50: 33 | H50: 10.1109/tits.2022.3211089 | I50: =VLOOKUP($D50,P:U,4,FALSE) -> #N/A | J50: =VLOOKUP($D50,P:U,5,FALSE) -> #N/A | K50: =VLOOKUP($D50,P:U,6,FALSE) -> #N/A
A51: Agent System Mining: Vision, Benefits, and Challenges | B51: Andrei Tour; Artem Polyvyanyy; Anna Kalenkova | C51: 2021 | D51: IEEE Access | E51: Agent foundations | F51: unscreened(rule-classified) | G51: 32 | H51: 10.1109/ACCESS.2021.3095464 | I51: =VLOOKUP($D51,P:U,4,FALSE) -> 0.9 | J51: =VLOOKUP($D51,P:U,5,FALSE) -> Q1 | K51: =VLOOKUP($D51,P:U,6,FALSE) -> 2169-3536
A52: Enhancing Cloud Security—Proactive Threat Monitoring and Detection Using a SIEM-Based Approach | B52: Emmanuel Tuyishime; Titus Bălan; Petru Adrian Cotfas; Daniel Tudor Cotfas; Alexandre Rekeraho | C52: 2023 | D52: Applied Sciences | E52: Security IR / SOC | F52: systems/empirical | G52: 32 | H52: 10.3390/app132212359 | I52: =VLOOKUP($D52,P:U,4,FALSE) -> #N/A | J52: =VLOOKUP($D52,P:U,5,FALSE) -> #N/A | K52: =VLOOKUP($D52,P:U,6,FALSE) -> #N/A
... A89: Surveying Root Cause Analysis Techniques: A Comprehensive Review of Aspects for Multi-Service Applications | B89: Zhijing Li; Jianbo Yu; Zhijun Huang; Yusheng Huang | C89: 2025 | D89: IEEE Transactions on Services Computing | E89: Root-cause analysis | F89: unscreened(rule-classified) | G89: 0 | H89: 10.1109/TSC.2025.3631913 | I89: =VLOOKUP($D89,P:U,4,FALSE) -> 0.9 | J89: =VLOOKUP($D89,P:U,5,FALSE) -> Q1 | K89: =VLOOKUP($D89,P:U,6,FALSE) -> 1939-1374
A90: VAGNet: Vision-based Accident Anticipation with Global Features | B90: Vipooshan Vipulananthan; Charith D. Chitraranjan | C90: 2026 | D90: IEEE Open Journal of Vehicular Technology, vol. 7, pp. 1873-1883, 2026 | E90: Alert triage & correlation | F90: unscreened(rule-classified) | H90: 10.1109/ojvt.2026.3704953 | I90: =VLOOKUP($D90,P:U,4,FALSE) -> #N/A | J90: =VLOOKUP($D90,P:U,5,FALSE) -> #N/A | K90: =VLOOKUP($D90,P:U,6,FALSE) -> #N/A
A91: TELESTO: A Graph Neural Network Model for Anomaly Classification in Cloud Services | B91: Dominik Scheinert; Alexander Acker | C91: 2021 | D91: Springer ICSOC LNCS 12632 (2020) 214-227 | E91: Automated remediation | F91: unscreened(rule-classified) | H91: 10.1007/978-3-030-76352-7_23 | I91: =VLOOKUP($D91,P:U,4,FALSE) -> #N/A | J91: =VLOOKUP($D91,P:U,5,FALSE) -> #N/A | K91: =VLOOKUP($D91,P:U,6,FALSE) -> #N/A
A92: A Decentralised Self-Healing Approach for Network Topology Maintenance | B92: Arles Rodríguez; Jonatan Gómez; Ada Diaconescu | C92: 2020 | D92: Autonomous Agents and Multi-Agent Systems, 35(1), 6 (2020) | E92: Automated remediation | F92: systems/empirical | H92: 10.1007/s10458-020-09486-3 | I92: =VLOOKUP($D92,P:U,4,FALSE) -> #N/A | J92: =VLOOKUP($D92,P:U,5,FALSE) -> #N/A | K92: =VLOOKUP($D92,P:U,6,FALSE) -> #N/A
A93: A unified framework for detecting point and collective anomalies in operating system logs via collaborative transformers | B93: Mohammad Nasirzadeh; Jafar Tahmoresnezhad; Parviz Rashidi-Khazaee | C93: 2025 | D93: Scientific Reports 15, 45698 (2025) | E93: Detection (classical ML) | F93: systems/empirical | H93: 10.1038/s41598-025-27693-4 | I93: =VLOOKUP($D93,P:U,4,FALSE) -> #N/A | J93: =VLOOKUP($D93,P:U,5,FALSE) -> #N/A | K93: =VLOOKUP($D93,P:U,6,FALSE) -> #N/A
A94: TARGET: Automated Scenario Generation from Traffic Rules for Testing Autonomous Vehicles via Validated LLM-Guided Knowledge Extraction | B94: Yao Deng; Jiaohong Yao; Zhi Tu; Xi Zheng; Mengshi Zhang; Tianyi Zhang | C94: 2023 | D94: IEEE Transactions on Software Engineering, Jul. 2025, pp. 1950-1968, vol. 51 | E94: LLM / agentic ops | F94: unscreened(rule-classified) | H94: 10.1109/tse.2025.3569086 | I94: =VLOOKUP($D94,P:U,4,FALSE) -> #N/A | J94: =VLOOKUP($D94,P:U,5,FALSE) -> #N/A | K94: =VLOOKUP($D94,P:U,6,FALSE) -> #N/A

Sheet Sheet1
A2: venue | B2: (Multiple Items)
A4: Row Labels | B4: Count of title
A5: Agent foundations | B5: 9
A6: Alert triage & correlation | B6: 4
A7: Automated remediation | B7: 8
A8: Benchmarks & evaluation | B8: 5
A9: Detection (classical ML) | B9: 29
A10: Human factors | B10: 7
A11: LLM / agentic ops | B11: 16
A12: Root-cause analysis | B12: 4
A13: Security IR / SOC | B13: 19
A14: Grand Total | B14: 101

Sheet Sheet 1 - agentic_ir_corpus (1)
A1: agentic_ir_corpus (1)
A2: title | B2: authors | C2: year | D2: venue | E2: cluster | F2: paper_type | G2: citations | H2: doi | I2: arxiv_or_openalex_id | J2: in_your_seed_set | K2: is_landmark | L2: src
A3: AgentTrace: A Structured Logging Framework for Agent System Observability | B3: Adam AlSayyad; Kelvin Yuxiang Huang; Richik Pal | C3: 2026 | D3: arXiv | E3: Agent foundations | F3: survey/position | I3: 2602.10133 | J3: 0 | K3: 0 | L3: arxiv
A4: Entropy-Based Observability for AI Agent Behavior | B4: Olasimbo Ayodeji Arigbabu | C4: 2026 | D4: arXiv | E4: Agent foundations | F4: survey/position | I4: 2606.05872 | J4: 0 | K4: 0 | L4: arxiv
A5: From LLM Reasoning to Autonomous AI Agents: A Comprehensive Review | B5: Mohamed Amine Ferrag; Norbert Tihanyi; Mérouane Debbah | C5: 2026 | D5: IEEE Access | E5: Agent foundations | F5: survey/position | G5: 7.0 | H5: 10.1109/access.2026.3698694 | I5: W4416982487 | J5: 0 | K5: 0 | L5: openalex
A6: When Errors Become Narratives: A Longitudinal Taxonomy of Silent Failures in a Production LLM Agent Runtime | B6: Wei Wu | C6: 2026 | D6: arXiv | E6: Agent foundations | F6: unscreened(rule-classified) | I6: 2606.14589 | J6: 0 | K6: 0 | L6: arxiv
A7: AGENTSAFE: A Unified Framework for Ethical Assurance and Governance in Agentic AI | B7: Rafflesia Khan; Declan Joyce; Mansura Habiba | C7: 2025 | D7: arXiv | E7: Agent foundations | F7: survey/position | I7: 2512.03180 | J7: 0 | K7: 0 | L7: arxiv
A8: AI Agents vs. Agentic AI: A Conceptual taxonomy, applications and challenges | B8: Ranjan Sapkota; Konstantinos I. Roumeliotis; Manoj Karkee | C8: 2025 | D8: Information Fusion | E8: Agent foundations | F8: survey/position | G8: 169.0 | H8: 10.1016/j.inffus.2025.103599 | I8: W4413427262 | J8: 1 | K8: 0 | L8: openalex
A9: Telemetry and Agentic AI: Foundations for Optical Network Automation | B9: Sergio Cruzes | C9: 2025 | D9: IEEE Access | E9: Agent foundations | F9: unscreened(rule-classified) | G9: 3.0 | H9: 10.1109/access.2025.3649768 | I9: W7117556955 | J9: 0 | K9: 0 | L9: openalex
A10: AgentAI: A comprehensive survey on autonomous agents in distributed AI for industry 4.0 | B10: Francesco Piccialli; Diletta Chiaro; Sundas Sarwar; Donato Cerciello; Pian Qi; Valeria Mele | C10: 2025 | D10: Expert Systems with Applications | E10: Agent foundations | F10: unscreened(rule-classified) | G10: 59.0 | H10: 10.1016/j.eswa.2025.128404 | I10: W4410954314 | J10: 1 | K10: 0 | L10: openalex
A11: LLM-Based Multi-Agent Systems for Software Engineering: Literature Review, Vision, and the Road Ahead | B11: Junda He; Christoph Treude; David Lo | C11: 2025 | D11: ACM Transactions on Software Engineering and Methodology | E11: Agent foundations | F11: unscreened(rule-classified) | G11: 177.0 | H11: 10.1145/3712003 | I11: W4406325768 | J11: 1 | K11: 0 | L11: openalex
A12: Small Language Model Agent for the Operations of Continuously Updating ICT Systems | B12: Nobukazu Fukuda; Haruhisa Nozue; Haruo Oishi | C12: 2025 | D12: IEEE Access | E12: Agent foundations | F12: unscreened(rule-classified) | G12: 0.0 | H12: 10.1109/ACCESS.2025.3544637 | I12: W4407900333 | J12: 1 | K12: 0 | L12: openalex
A13: AgentOps: Enabling Observability of LLM Agents | B13: Liming Dong; Qinghua Lu; Liming Zhu | C13: 2024 | D13: arXiv | E13: Agent foundations | F13: survey/position | I13: 2411.05285 | J13: 0 | K13: 0 | L13: arxiv
A14: Co-Evolving Multi-Agent Transfer Reinforcement Learning via Scenario Independent Representation | B14: Ayesha Siddiqua; Siming Liu; Ayesha Siddika Nipu; Anthony M. Harris; Yan Liu | C14: 2024 | D14: IEEE Access | E14: Agent foundations | F14: unscreened(rule-classified) | G14: 9.0 | H14: 10.1109/ACCESS.2024.3430037 | I14: W4400726849 | J14: 1 | K14: 0 | L14: openalex
A15: Building AI Agents for Autonomous Clouds: Challenges and Design Principles | B15: Manish Shetty; Yinfang Chen; Gagan Somashekar; Minghua Ma | C15: 2024 | E15: Agent foundations | F15: systems/empirical | G15: 27.0 | H15: 10.1145/3698038.3698525 | J15: 0 | K15: 1 | L15: landmark
A16: Agent System Mining: Vision, Benefits, and Challenges | B16: Andrei Tour; Artem Polyvyanyy; Anna Kalenkova | C16: 2021 | D16: IEEE Access | E16: Agent foundations | F16: unscreened(rule-classified) | G16: 32.0 | H16: 10.1109/ACCESS.2021.3095464 | I16: W3180674049 | J16: 1 | K16: 0 | L16: openalex
A17: Artificial Empathy: A New Perspective for Analyzing and Designing Multi-Agent Systems | B17: Jize Chen; Dali Zhang; Zhenshen Qu; Changhong Wang | C17: 2020 | D17: IEEE Access | E17: Agent foundations | F17: unscreened(rule-classified) | G17: 10.0 | H17: 10.1109/ACCESS.2020.3029502 | I17: W3092406976 | J17: 1 | K17: 0 | L17: openalex
A18: AlertGuardian: Intelligent Alert Life-Cycle Management for Large-scale Cloud Systems | B18: Guangba Yu; Genting Mai; Rui Wang; Ruipeng Li; Pengfei Chen; Long Pan; Ruijie Xu | C18: 2026 | D18: arXiv | E18: Alert triage & correlation | F18: systems/empirical | I18: 2601.14912 | J18: 0 | K18: 0 | L18: arxiv
A19: ConceptRM: The Quest to Mitigate Alert Fatigue through Consensus-Based Purity-Driven Data Cleaning for Reflection Modelling | B19: Yongda Yu; Lei Zhang; Xinxin Guo; Minghui Yu; Zhengqi Zhuang; Guoping Rong; Haifeng Shen; Zhengfeng Li | C19: 2026 | D19: arXiv | E19: Alert triage & correlation | F19: systems/empirical | I19: 2602.20166 | J19: 0 | K19: 0 | L19: arxiv
A20: Cybersecurity Detection Classification with Reasoning-enabled Language Models | B20: Amol Khanna; Manu Nandan; Cristian Viorel Popa; Joan Pujol-Roig; Diana Bolocan; Laura Vasilie; Alexandru Apostu; Chase Helwig | C20: 2026 | D20: arXiv | E20: Alert triage & correlation | F20: systems/empirical | I20: 2607.28460 | J20: 0 | K20: 0 | L20: arxiv
A21: Understanding npm Developers' Practices, Challenges, and Recommendations for Secure Package Development | B21: Anthony Peruma; Truman Choy; Gerald Lee; Italo De Oliveira Santos | C21: 2026 | D21: arXiv | E21: Alert triage & correlation | F21: unscreened(rule-classified) | H21: 10.1145/3794860.3794908 | I21: 2601.20240 | J21: 0 | K21: 0 | L21: arxiv
A22: VAGNet: Vision-based Accident Anticipation with Global Features | B22: Vipooshan Vipulananthan; Charith D. Chitraranjan | C22: 2026 | D22: IEEE Open Journal of Vehicular Technology, vol. 7, pp. 1873-1883, 2026 | E22: Alert triage & correlation | F22: unscreened(rule-classified) | H22: 10.1109/ojvt.2026.3704953 | I22: 2604.09305 | J22: 0 | K22: 0 | L22: arxiv
A23: vEcho: A Paradigm Shift from Vulnerability Verification to Proactive Discovery with Large Language Models | B23: Mingcheng Jiang; Jiancheng Huang; Jiangfei Wang; Zhengzhu Xie; Nan Fang; Guang Cheng; Xiaoyan Hu; Hua Wu | C23: 2026 | D23: arXiv | E23: Alert triage & correlation | F23: unscreened(rule-classified) | I23: 2603.01154 | J23: 0 | K23: 0 | L23: arxiv
A24: A Large-Scale Collection Of (Non-)Actionable Static Code Analysis Reports | B24: Dávid Kószó; Tamás Aladics; Rudolf Ferenc; Péter Hegedűs | C24: 2025 | D24: arXiv | E24: Alert triage & correlation | F24: systems/empirical | I24: 2511.10323 | J24: 0 | K24: 0 | L24: arxiv
A25: Triage in Software Engineering: A Systematic Review of Research and Practice | B25: Yongxin Zhao; Shenglin Zhang; Yujia Wu; Yuxin Sun; Yongqian Sun; Dan Pei; Chetan Bansal; Minghua Ma | C25: 2025 | D25: arXiv | E25: Alert triage & correlation | F25: unscreened(rule-classified) | I25: 2511.08607 | J25: 0 | K25: 0 | L25: arxiv
A26: When not to help: planning for lasting human-AI collaboration | B26: Mark Steyvers; Lukas Mayer | C26: 2025 | D26: arXiv | E26: Alert triage & correlation | F26: unscreened(rule-classified) | I26: 2508.01837 | J26: 0 | K26: 0 | L26: arxiv
A27: FaultProfIT: Hierarchical Fault Profiling of Incident Tickets in Large-scale Cloud Systems | B27: Junjie Huang; Jinyang Liu; Zhuangbin Chen; Zhihan Jiang | C27: 2024 | E27: Alert triage & correlation | F27: systems/empirical | G27: 11.0 | H27: 10.1145/3639477.3639754 | J27: 0 | K27: 1 | L27: landmark
A28: AI-Assisted Security Alert Data Analysis with Imbalanced Learning Methods | B28: Samuel Ndichu; Tao Ban; Takeshi Takahashi; Daisuke Inoue | C28: 2023 | D28: Applied Sciences | E28: Alert triage & correlation | F28: systems/empirical | G28: 19.0 | H28: 10.3390/app13031977 | I28: W4319080536 | J28: 0 | K28: 0 | L28: openalex
A29: Breaking Alert Fatigue: AI-Assisted SIEM Framework for Effective Incident Response | B29: Tao Ban; Takeshi Takahashi; Samuel Ndichu; Daisuke Inoue | C29: 2023 | D29: Applied Sciences | E29: Alert triage & correlation | F29: systems/empirical | G29: 52.0 | H29: 10.3390/app13116610 | I29: W4381569470 | J29: 0 | K29: 0 | L29: openalex
A30: That Escalated Quickly: An ML Framework for Alert Prioritization | B30: Ben Gelman; Salma Taoufiq; Tamás Vörös; Konstantin Berlin | C30: 2023 | D30: arXiv | E30: Alert triage & correlation | F30: unscreened(rule-classified) | I30: 2302.06648 | J30: 0 | K30: 0 | L30: arxiv
A31: Twin Graph-based Anomaly Detection via Attentive Multi-Modal Learning for Microservice System | B31: Jun Huang; Yang Yang; Hang Yu; Jianguo Li; Xiao Zheng | C31: 2023 | D31: arXiv | E31: Alert triage & correlation | F31: unscreened(rule-classified) | I31: 2310.04701 | J31: 0 | K31: 0 | L31: arxiv
A32: Wind Turbine Fault Detection Using Highly Imbalanced Real SCADA Data | B32: Cristian Velandia; Yolanda Vidal; Francesc Pozo | C32: 2021 | D32: Energies | E32: Alert triage & correlation | F32: unscreened(rule-classified) | G32: 53.0 | H32: 10.3390/en14061728 | I32: W3137151386 | J32: 0 | K32: 0 | L32: openalex
A33: Zero-shot learning approach to adaptive Cybersecurity using Explainable AI | B33: Dattaraj Rao; Shraddha Mane | C33: 2021 | D33: arXiv | E33: Alert triage & correlation | F33: unscreened(rule-classified) | I33: 2106.14647 | J33: 0 | K33: 0 | L33: arxiv
A34: A Snooze-less User-Aware Notification System for Proactive Conversational Agents | B34: Yara Rizk; Vatche Isahagian; Merve Unuvar; Yasaman Khazaeni | C34: 2020 | D34: arXiv | E34: Alert triage & correlation | F34: systems/empirical | I34: 2003.02097 | J34: 0 | K34: 0 | L34: arxiv
A35: The Energy Blind Spot: NVIDIA's Flagship Edge AI Hardware Cannot Support Process-Level Energy Attribution | B35: Deepak Panigrahy; Aakash Tyagi | C35: 2026 | D35: arXiv | E35: Automated remediation | F35: unscreened(rule-classified) | I35: 2605.27599 | J35: 0 | K35: 0 | L35: arxiv
A36: Towards Resiliency in Large Language Model Serving with KevlarFlow | B36: Shangshu Qian; Kipling Liu; P. C. Sruthi; Lin Tan; Yongle Zhang | C36: 2026 | D36: arXiv | E36: Automated remediation | F36: unscreened(rule-classified) | I36: 2601.22438 | J36: 0 | K36: 0 | L36: arxiv
A37: When AI Fails, What Works? A Data-Driven Taxonomy of Real-World AI Risk Mitigation Strategies | B37: Evgenija Popchanovska; Ana Gjorgjevikj; Maryan Rizinski; Lubomir Chitkushev; Irena Vodenska; Dimitar Trajanov | C37: 2026 | D37: arXiv | E37: Automated remediation | F37: unscreened(rule-classified) | I37: 2603.04259 | J37: 0 | K37: 0 | L37: arxiv
A38: A Threshold-Triggered Deep Q-Network-Based Framework for Self-Healing in Autonomic Software-Defined IIoT-Edge Networks | B38: Agrippina Mwangi; León Navarro-Hilfiker; Lukasz Brewka; Mikkel Gryning; Elena Fumagalli; Madeleine Gibescu | C38: 2025 | D38: arXiv | E38: Automated remediation | F38: systems/empirical | H38: 10.1109/tnsm.2025.3647853 | I38: 2512.14297 | J38: 0 | K38: 0 | L38: arxiv
A39: Thermographic and cognitive assessment of fatigue in vessel traffic service operators: a socio-technical approach | B39: Fernando Crestelo Moreno; John González; Juan Suardíaz Muro; R. López-Alonso | C39: 2025 | D39: Cognition Technology & Work | E39: Automated remediation | F39: unscreened(rule-classified) | G39: 6.0 | H39: 10.1007/s10111-025-00804-x | I39: W4411424618 | J39: 0 | K39: 0 | L39: openalex
A40: Toward Robust Security Orchestration and Automated Response in Security Operations Centers with a Hyper-Automation Approach Using Agentic Artificial Intelligence | B40: Ismail Ismail; Rahmat Kurnia; Zilmas Arjuna Brata; Ghitha Afina Nelistiani; Shinwook Heo; Hyeongon Kim; Hyeongon Kim; Howon Kim; Howon Kim | C40: 2025 | D40: Information | E40: Automated remediation | F40: unscreened(rule-classified) | G40: 31.0 | H40: 10.3390/info16050365 | I40: W4409965657 | J40: 0 | K40: 0 | L40: openalex
A41: Understanding Practitioners Perspectives on Monitoring Machine Learning Systems | B41: Hira Naveed; John Grundy; Chetan Arora; Hourieh Khalajzadeh; Omar Haggag | C41: 2025 | D41: arXiv | E41: Automated remediation | F41: unscreened(rule-classified) | I41: 2509.25195 | J41: 0 | K41: 0 | L41: arxiv
A42: When, Where, and What? A Novel Benchmark for Accident Anticipation and Localization with Large Language Models | B42: Haicheng Liao; Yongkang Li; Chengyue Wang; Yanchen Guan; KaHou Tam; Chunlin Tian; Li Li; Chengzhong Xu | C42: 2024 | D42: arXiv | E42: Automated remediation | F42: unscreened(rule-classified) | I42: 2407.16277 | J42: 0 | K42: 0 | L42: arxiv
A43: Transparent Automated Advice to Mitigate the Impact of Variation in Automation Reliability | B43: Isabella Gegoff; Monica Tatasciore; Vanessa K. Bowden; Jason S. McCarley; Shayne Loft | C43: 2023 | D43: Human Factors The Journal of the Human Factors and Ergonomics Society | E43: Automated remediation | F43: unscreened(rule-classified) | G43: 24.0 | H43: 10.1177/00187208231196738 | I43: W4386209057 | J43: 0 | K43: 0 | L43: openalex
A44: Unicron: Economizing Self-Healing LLM Training at Scale | B44: Tao He; Xue Li; Zhibin Wang; Kun Qian; Jing-Bo Xu; Wenyuan Yu; Jingren Zhou | C44: 2023 | D44: arXiv (Cornell University) | E44: Automated remediation | F44: unscreened(rule-classified) | G44: 5.0 | H44: 10.48550/arxiv.2401.00134 | I44: W4390529129 | J44: 0 | K44: 0 | L44: openalex
A45: Towards Self-Adaptive Peer-to-Peer Monitoring for Fog Environments | B45: Vera Colombo; Alessandro Tundo; Michele Ciavotta; Leonardo Mariani | C45: 2022 | D45: arXiv | E45: Automated remediation | F45: unscreened(rule-classified) | H45: 10.1145/3524844.3528055 | I45: 2205.04142 | J45: 0 | K45: 0 | L45: arxiv
A46: Using fNIRS to Verify Trust in Highly Automated Driving | B46: Jaume Perelló-March; Christopher Burns; Roger Woodman; Mark T. Elliott; Stewart Birrell | C46: 2022 | D46: IEEE Transactions on Intelligent Transportation Systems | E46: Automated remediation | F46: unscreened(rule-classified) | G46: 33.0 | H46: 10.1109/tits.2022.3211089 | I46: W4312966716 | J46: 0 | K46: 0 | L46: openalex
A47: Zero Day Threat Detection Using Graph and Flow Based Security Telemetry | B47: Christopher Redino; Dhruv Nandakumar; Robert Schiller; Kevin Choi; Abdul Rahman; Edward Bowen; Matthew Weeks; Aaron Shaha | C47: 2022 | D47: arXiv | E47: Automated remediation | F47: unscreened(rule-classified) | I47: 2205.02298 | J47: 0 | K47: 0 | L47: arxiv
A48: TELESTO: A Graph Neural Network Model for Anomaly Classification in Cloud Services | B48: Dominik Scheinert; Alexander Acker | C48: 2021 | D48: Springer ICSOC LNCS 12632 (2020) 214-227 | E48: Automated remediation | F48: unscreened(rule-classified) | H48: 10.1007/978-3-030-76352-7_23 | I48: 2102.12877 | J48: 0 | K48: 0 | L48: arxiv
A49: A Decentralised Self-Healing Approach for Network Topology Maintenance | B49: Arles Rodríguez; Jonatan Gómez; Ada Diaconescu | C49: 2020 | D49: Autonomous Agents and Multi-Agent Systems, 35(1), 6 (2020) | E49: Automated remediation | F49: systems/empirical | H49: 10.1007/s10458-020-09486-3 | I49: 2010.11146 | J49: 0 | K49: 0 | L49: arxiv
A50: The Challenges of Leveraging Threat Intelligence to Stop Data Breaches | B50: Amani S. Ibrahim; Dhananjay Thiruvady; Jean-Guy Schneider; Mohamed Abdelrazek | C50: 2020 | D50: Frontiers in Computer Science | E50: Automated remediation | F50: unscreened(rule-classified) | G50: 62.0 | H50: 10.3389/fcomp.2020.00036 | I50: W3081936891 | J50: 0 | K50: 0 | L50: openalex
A51: Variational LSTM Enhanced Anomaly Detection for Industrial Big Data | B51: Xiaokang Zhou; Yiyong Hu; Wei Liang; Jianhua Ma; Qun Jin | C51: 2020 | D51: IEEE Transactions on Industrial Informatics | E51: Automated remediation | F51: unscreened(rule-classified) | G51: 401.0 | H51: 10.1109/tii.2020.3022432 | I51: W3086419524 | J51: 0 | K51: 0 | L51: openalex
A52: The Dynamics of Software Composition Analysis | B52: Darius Foo; Jason Yeo; Hao Xiao; Asankhaya Sharma | C52: 2019 | D52: arXiv | E52: Automated remediation | F52: unscreened(rule-classified) | I52: 1909.00973 | J52: 0 | K52: 0 | L52: arxiv
A53: Deepchecks: Evaluating Retrieval-Augmented Generation (RAG) | B53: Assaf Gerner; Netta Madvil; Nadav Barak; Alex Zaikman; Jonatan Liberman; Liron Hamra; Rotem Brazilay; Shay Tsadok | C53: 2026 | D53: arXiv | E53: Benchmarks & evaluation | F53: systems/empirical | I53: 2605.14488 | J53: 0 | K53: 0 | L53: arxiv
A54: TelcoAgent-Bench: A Multilingual Benchmark for Telecom AI Agents | B54: Lina Bariah; Brahim Mefgouda; Farbod Tavakkoli; Enrique Molero; Louis Powell; Merouane Debbah | C54: 2026 | D54: arXiv | E54: Benchmarks & evaluation | F54: unscreened(rule-classified) | I54: 2604.06209 | J54: 0 | K54: 0 | L54: arxiv
A55: Towards Near-Real-Time Telemetry-Aware Routing with Neural Routing Algorithms | B55: Andreas Boltres; Niklas Freymuth; Benjamin Schichtholz; Michael König; Gerhard Neumann | C55: 2026 | D55: arXiv | E55: Benchmarks & evaluation | F55: unscreened(rule-classified) | I55: 2604.02927 | J55: 0 | K55: 0 | L55: arxiv
A56: Verified Tool Calls Improve LLM Agent Reliability Under Non-Atomic Failures | B56: Isham Kalappurackal Mansoor; Abhishek Phadke; Pratip Rana | C56: 2026 | D56: arXiv | E56: Benchmarks & evaluation | F56: unscreened(rule-classified) | I56: 2608.02645 | J56: 0 | K56: 0 | L56: arxiv
A57: When Retrieval Fails Before It Begins: Structurally Indirect Prerequisite Eviction as a Retention Failure in Agentic Memory | B57: Minkyu Song | C57: 2026 | D57: arXiv | E57: Benchmarks & evaluation | F57: unscreened(rule-classified) | I57: 2608.20400 | J57: 0 | K57: 0 | L57: arxiv
A58: WirelessOpsAgent: A Benchmark and Agent Design for Action Assurance in Wireless Networks | B58: Zijian Lu; Yiping Zuo; Hao Xu; Weicong Chen; Xin He; Jiajia Guo; Shi Jin | C58: 2026 | D58: arXiv | E58: Benchmarks & evaluation | F58: unscreened(rule-classified) | I58: 2608.08277 | J58: 0 | K58: 0 | L58: arxiv
A59: AIOpsLab: A Holistic Framework to Evaluate AI Agents for Enabling Autonomous Clouds | B59: Yinfang Chen; Manish Shetty; Gagan Somashekar; Minghua Ma; Yogesh Simmhan; Jonathan Mace; Chetan Bansal; Rujia Wang | C59: 2025 | D59: arXiv | E59: Benchmarks & evaluation | F59: systems/empirical | I59: 2501.06706 | J59: 0 | K59: 1 | L59: arxiv
A60: A Network Arena for Benchmarking AI Agents on Network Troubleshooting | B60: Zhihao Wang; Alessandro Cornacchia; Alessio Sacco; Franco Galante; Marco Canini; Dingde Jiang | C60: 2025 | D60: arXiv | E60: Benchmarks & evaluation | F60: systems/empirical | I60: 2512.16381 | J60: 0 | K60: 1 | L60: arxiv
A61: DFIR-Metric: A Benchmark Dataset for Evaluating Large Language Models in Digital Forensics and Incident Response | B61: Bilel Cherif; Tamas Bisztray; Richard A. Dubniczky; Aaesha Aldahmani; Saeed Alshehhi; Norbert Tihanyi | C61: 2025 | D61: arXiv | E61: Benchmarks & evaluation | F61: systems/empirical | I61: 2505.19973 | J61: 0 | K61: 0 | L61: arxiv
A62: VAGEN: Reinforcing World Model Reasoning for Multi-Turn VLM Agents | B62: Kangrui Wang; Pingyue Zhang; Zihan Wang; Yaning Gao; Linjie Li; Qineng Wang; Hanyang Chen; Chi Wan | C62: 2025 | D62: arXiv | E62: Benchmarks & evaluation | F62: unscreened(rule-classified) | I62: 2510.16907 | J62: 0 | K62: 0 | L62: arxiv
A63: Multi-Agent Coordination Strategies vs. Retrieval-Augmented Generation in LLMs: A Comparative Evaluation | B63: Irina Radeva; Иван Попчев; Lyubka Doukovska; Miroslava Dimitrova | C63: 2025 | D63: Electronics | E63: Benchmarks & evaluation | F63: unscreened(rule-classified) | G63: 0.0 | H63: 10.3390/electronics14244883 | I63: W4417244517 | J63: 1 | K63: 0 | L63: openalex
A64: Retail Resilience Engine: An Agentic AI Framework for Building Reliable Retail Systems With Test-Driven Development Approach | B64: Lalit Narayan Mishra; Biswaranjan Senapati | C64: 2025 | D64: IEEE Access | E64: Benchmarks & evaluation | F64: unscreened(rule-classified) | G64: 34.0 | H64: 10.1109/ACCESS.2025.3552592 | I64: W4408564575 | J64: 1 | K64: 0 | L64: openalex
A65: RCAEval: A Benchmark for Root Cause Analysis of Microservice Systems with Telemetry Data | B65: Luan Pham; Hongyu Zhang; Huong Ha; Flora D. Salim | C65: 2025 | E65: Benchmarks & evaluation | F65: systems/empirical | G65: 20.0 | H65: 10.1145/3701716.3715290 | J65: 0 | K65: 1 | L65: landmark
A66: OpsEval: A Comprehensive Benchmark Suite for Evaluating Large Language Models’ Capability in IT Operations Domain | B66: Yuhe Liu; Changhua Pei; Longlong Xu; Bohan Chen | C66: 2025 | E66: Benchmarks & evaluation | F66: systems/empirical | G66: 5.0 | H66: 10.1145/3696630.3728572 | J66: 0 | K66: 1 | L66: landmark
A67: ITBench: Evaluating AI Agents across Diverse Real-World IT Automation Tasks | B67: Saurabh Jha; Rohan Arora; Yuji Watanabe; Takumi Yanagawa | C67: 2025 | D67: arXiv | E67: Benchmarks & evaluation | F67: systems/empirical | I67: 2502.05352 | J67: 0 | K67: 1 | L67: landmark
A68: TinyAgent: Function Calling at the Edge | B68: Lutfi Eren Erdogan; Nicholas Lee; Siddharth Jha; Sehoon Kim; Ryan Tabrizi; Suhong Moon; Coleman Hooper; Gopala Anumanchipalli | C68: 2024 | D68: arXiv | E68: Benchmarks & evaluation | F68: unscreened(rule-classified) | I68: 2409.00608 | J68: 0 | K68: 0 | L68: arxiv
A69: Towards Automation of Human Stage of Decay Identification: An Artificial Intelligence Approach | B69: Anna-Maria Nau; Phillip Ditto; Dawnie Wolfe Steadman; Audris Mockus | C69: 2024 | D69: arXiv | E69: Benchmarks & evaluation | F69: unscreened(rule-classified) | I69: 2408.10414 | J69: 0 | K69: 0 | L69: arxiv
A70: Availability analysis of redundant and replicated cloud services with Bayesian networks | B70: Otto Bibartiu; Frank Dürr; Kurt Rothermel; Beate Ottenwälder; Andreas Grau | C70: 2023 | D70: Quality and Reliability Engineering International | E70: Benchmarks & evaluation | F70: systems/empirical | G70: 7.0 | H70: 10.1002/qre.3414 | I70: W4385241681 | J70: 0 | K70: 0 | L70: openalex
A71: The Chatbot Usability Scale: the Design and Pilot of a Usability Scale for Interaction with AI-Based Conversational Agents | B71: Simone Borsci; Alessio Malizia; Martin Schmettow; Frank van der Velde; Gunay Tariverdiyeva; Divyaa Balaji; Alan Chamberlain | C71: 2021 | D71: Personal and Ubiquitous Computing | E71: Benchmarks & evaluation | F71: unscreened(rule-classified) | G71: 233.0 | H71: 10.1007/s00779-021-01582-9 | I71: W3187911027 | J71: 0 | K71: 0 | L71: openalex
A72: The Impact of Explanations on Layperson Trust in Artificial Intelligence–Driven Symptom Checker Apps: Experimental Study | B72: Claire Woodcock; Brent Mittelstadt; Dan Busbridge; Grant Blank | C72: 2021 | D72: Journal of Medical Internet Research | E72: Benchmarks & evaluation | F72: unscreened(rule-classified) | G72: 50.0 | H72: 10.2196/29386 | I72: W3210874941 | J72: 0 | K72: 0 | L72: openalex
A73: Towards intelligent incident management: why we need it and how we make it | B73: Zhuangbin Chen; Yu Kang; Liqun Li; Xu Zhang | C73: 2020 | E73: Benchmarks & evaluation | F73: systems/empirical | G73: 91.0 | H73: 10.1145/3368089.3417055 | J73: 0 | K73: 1 | L73: landmark
A74: Tools and Benchmarks for Automated Log Parsing | B74: Jieming Zhu; Shilin He; Jinyang Liu; Pinjia He; Qi Xie; Zibin Zheng; Michael R. Lyu | C74: 2019 | D74: conference-paper | E74: Benchmarks & evaluation | F74: unscreened(rule-classified) | G74: 538.0 | H74: 10.1109/icse-seip.2019.00021 | I74: W2963999143 | J74: 0 | K74: 0 | L74: openalex
A75: CCL-D: A High-Precision Diagnostic System for Slow and Hang Anomalies in Large-Scale Model Training | B75: Yida Gu; Fakang Wang; Jianhao Fu; Zhenhang Sun; Qianyu Zhang; Hairui Zhao; Xingchen Liu; Yang Tian | C75: 2026 | D75: arXiv | E75: Detection (classical ML) | F75: systems/empirical | H75: 10.1145/3774934.3786429 | I75: 2605.04478 | J75: 0 | K75: 0 | L75: arxiv
A76: CLAD: Efficient Log Anomaly Detection Directly on Compressed Representations | B76: Benzhao Tang; Shiyu Yang | C76: 2026 | D76: arXiv | E76: Detection (classical ML) | F76: systems/empirical | I76: 2604.13024 | J76: 0 | K76: 0 | L76: arxiv
A77: ContraLog: Log File Anomaly Detection with Contrastive Learning and Masked Language Modeling | B77: Simon Dietz; Kai Klede; An Nguyen; Bjoern M Eskofier | C77: 2026 | D77: arXiv | E77: Detection (classical ML) | F77: systems/empirical | I77: 2602.03678 | J77: 0 | K77: 0 | L77: arxiv
A78: Using AI to Monitor AI: Automated Operations Through Log-Driven Intelligence | B78: Chen Qi; Xiaoying Qiao | C78: 2026 | D78: conference-paper | E78: Detection (classical ML) | F78: unscreened(rule-classified) | G78: 0.0 | H78: 10.1109/icbase70763.2026.11619459 | I78: W7171729227 | J78: 0 | K78: 0 | L78: openalex
A79: When GPUs Fail Quietly: Observability-Aware Early Warning Beyond Numeric Telemetry | B79: Michael Bidollahkhani; Freja Nordsiek; Julian M. Kunkel | C79: 2026 | D79: arXiv | E79: Detection (classical ML) | F79: unscreened(rule-classified) | I79: 2603.28781 | J79: 0 | K79: 0 | L79: arxiv
A80: A layered architecture for log analysis in complex IT systems | B80: Thorsten Wittkopp | C80: 2025 | D80: arXiv | E80: Detection (classical ML) | F80: systems/empirical | H80: 10.14279/depositonce-22012 | I80: 2509.08698 | J80: 0 | K80: 0 | L80: arxiv
A81: A unified framework for detecting point and collective anomalies in operating system logs via collaborative transformers | B81: Mohammad Nasirzadeh; Jafar Tahmoresnezhad; Parviz Rashidi-Khazaee | C81: 2025 | D81: Scientific Reports 15, 45698 (2025) | E81: Detection (classical ML) | F81: systems/empirical | H81: 10.1038/s41598-025-27693-4 | I81: 2512.23380 | J81: 0 | K81: 0 | L81: arxiv
A82: DBLoss: Decomposition-based Loss Function for Time Series Forecasting | B82: Xiangfei Qiu; Xingjian Wu; Hanyin Cheng; Xvyuan Liu; Chenjuan Guo; Jilin Hu; Bin Yang | C82: 2025 | D82: arXiv | E82: Detection (classical ML) | F82: systems/empirical | I82: 2510.23672 | J82: 0 | K82: 0 | L82: arxiv
A83: Graph Neural AI with Temporal Dynamics for Comprehensive Anomaly Detection in Microservices | B83: Qingyuan Zhang; Ning Lyu; Le Liu; Yuxi Wang; Ziyu Cheng; Cancan Hua | C83: 2025 | D83: arXiv | E83: Detection (classical ML) | F83: systems/empirical | I83: 2511.03285 | J83: 0 | K83: 0 | L83: arxiv
A84: The Agentic Regulator: Risks for AI in Finance and a Proposed Agent-based Framework for Governance | B84: Eren Kurshan; Tucker Balch; David Byrd | C84: 2025 | D84: arXiv | E84: Detection (classical ML) | F84: unscreened(rule-classified) | I84: 2512.11933 | J84: 0 | K84: 0 | L84: arxiv
A85: Unsupervised Anomaly Detection in Multivariate Time Series across Heterogeneous Domains | B85: Vincent Jacob; Yanlei Diao | C85: 2025 | D85: arXiv | E85: Detection (classical ML) | F85: unscreened(rule-classified) | I85: 2503.23060 | J85: 0 | K85: 0 | L85: arxiv
A86: Artificial Intelligence for Predictive Maintenance Applications: Key Components, Trustworthiness, and Future Trends | B86: Ayşegül Uçar; Mehmet Karaköse; Necim Kırımça | C86: 2024 | D86: Applied Sciences | E86: Detection (classical ML) | F86: survey/position | G86: 396.0 | H86: 10.3390/app14020898 | I86: W4391098453 | J86: 0 | K86: 0 | L86: openalex
A87: Cloud Network Anomaly Detection Using Machine and Deep Learning Techniques— Recent Research Advancements | B87: Amira Mahamat Abdallah; Aysha Saif Rashed Obaid Alkaabi; Ghaya Bark Nasser Douman Alameri; Saida Hafsa Rafique; Nura Shifa Musa; M. Thangavel | C87: 2024 | D87: IEEE Access | E87: Detection (classical ML) | F87: survey/position | G87: 78.0 | H87: 10.1109/access.2024.3390844 | I87: W4394939094 | J87: 0 | K87: 0 | L87: openalex
A88: Cross-System Categorization of Abnormal Traces in Microservice-Based Systems via Meta-Learning | B88: Yuqing Wang; Mika V. Mäntylä; Serge Demeyer; Mutlu Beyazit; Joanna Kisaakye; Jesse Nyyssölä | C88: 2024 | D88: arXiv | E88: Detection (classical ML) | F88: systems/empirical | H88: 10.1145/3715742 | I88: 2403.18998 | J88: 0 | K88: 0 | L88: arxiv
A89: Cross-System Software Log-based Anomaly Detection Using Meta-Learning | B89: Yuqing Wang; Mika V. Mäntylä; Jesse Nyyssölä; Ke Ping; Liqiang Wang | C89: 2024 | D89: arXiv | E89: Detection (classical ML) | F89: systems/empirical | I89: 2412.15445 | J89: 0 | K89: 0 | L89: arxiv
A90: Deep Industrial Image Anomaly Detection: A Survey | B90: Jiaqi Liu; Guoyang Xie; Jinbao Wang; Shangnian Li; Chengjie Wang; Feng Zheng; Yaochu Jin | C90: 2024 | D90: Machine Intelligence Research | E90: Detection (classical ML) | F90: survey/position | G90: 389.0 | H90: 10.1007/s11633-023-1459-z | I90: W4390875033 | J90: 0 | K90: 0 | L90: openalex
A91: Deep Learning for Time Series Anomaly Detection: A Survey | B91: Zahra Zamanzadeh Darban; Geoffrey I. Webb; Shirui Pan; Charų C. Aggarwal; Mahsa Salehi | C91: 2024 | D91: ACM Computing Surveys | E91: Detection (classical ML) | F91: survey/position | G91: 506.0 | H91: 10.1145/3691338 | I91: W4402056503 | J91: 0 | K91: 0 | L91: openalex
A92: Deep Learning or Classical Machine Learning? An Empirical Study on Log-Based Anomaly Detection | B92: Boxi Yu; Jiayi Yao; Qiuai Fu; Zhiqing Zhong; Haotian Xie; Y.C. Wu; Yuchi Ma; Pinjia He | C92: 2024 | D92: conference-paper | E92: Detection (classical ML) | F92: systems/empirical | G92: 57.0 | H92: 10.1145/3597503.3623308 | I92: W4391558391 | J92: 0 | K92: 0 | L92: openalex
A93: GraphSubDetector: Time Series Subsequence Anomaly Detection via Density-Aware Adaptive Graph Neural Network | B93: Weiqi Chen; Zhiqiang Zhou; Qingsong Wen; Liang Sun | C93: 2024 | D93: arXiv | E93: Detection (classical ML) | F93: systems/empirical | I93: 2411.17218 | J93: 0 | K93: 0 | L93: arxiv
A94: Time to Retrain? Detecting Concept Drifts in Machine Learning Systems | B94: Tri Minh Triet Pham; Karthikeyan Premkumar; Mohamed Naili; Jinqiu Yang | C94: 2024 | D94: arXiv | E94: Detection (classical ML) | F94: unscreened(rule-classified) | I94: 2410.09190 | J94: 0 | K94: 0 | L94: arxiv
A95: WaitGPT: Monitoring and Steering Conversational LLM Agent in Data Analysis with On-the-Fly Code Visualization | B95: Liwenhan Xie; Chengbo Zheng; Haijun Xia; Huamin Qu; Zhutian Chen | C95: 2024 | D95: conference-paper | E95: Detection (classical ML) | F95: unscreened(rule-classified) | G95: 45.0 | H95: 10.1145/3654777.3676374 | I95: W4403334501 | J95: 0 | K95: 0 | L95: openalex
A96: Data Drift Monitoring for Log Anomaly Detection Pipelines | B96: Dipak Wani; Samuel Ackerman; Eitan Farchi; Xiaotong Liu; Hau-wen Chang; Sarasi Lalithsena | C96: 2023 | D96: arXiv | E96: Detection (classical ML) | F96: systems/empirical | I96: 2310.14893 | J96: 0 | K96: 0 | L96: arxiv
A97: Deep learning for anomaly detection in log data: A survey | B97: Max Landauer; Sebastian Onder; Florian Skopik; Markus Wurzenberger | C97: 2023 | D97: Machine Learning with Applications | E97: Detection (classical ML) | F97: survey/position | G97: 194.0 | H97: 10.1016/j.mlwa.2023.100470 | I97: W4376288669 | J97: 0 | K97: 0 | L97: openalex
A98: Distributed system anomaly detection using deep learning‐based log analysis | B98: Pengfei Han; Huakang Li; Gang Xue; Chao Zhang | C98: 2023 | D98: Computational Intelligence | E98: Detection (classical ML) | F98: systems/empirical | G98: 12.0 | H98: 10.1111/coin.12573 | I98: W4366768971 | J98: 0 | K98: 0 | L98: openalex
A99: From Corrective to Predictive Maintenance—A Review of Maintenance Approaches for the Power Industry | B99: Marek Molęda; Bożena Małysiak-Mrozek; Weiping Ding; Vaidy Sunderam; Dariusz Mrozek | C99: 2023 | D99: Sensors | E99: Detection (classical ML) | F99: survey/position | G99: 264.0 | H99: 10.3390/s23135970 | I99: W4382402849 | J99: 0 | K99: 0 | L99: openalex
A100: GLAD: Content-aware Dynamic Graphs For Log Anomaly Detection | B100: Yufei Li; Yanchi Liu; Haoyu Wang; Zhengzhang Chen; Wei Cheng; Yuncong Chen; Wenchao Yu; Haifeng Chen | C100: 2023 | D100: arXiv | E100: Detection (classical ML) | F100: systems/empirical | I100: 2309.05953 | J100: 0 | K100: 0 | L100: arxiv
...
